Workbook
Name \0: #REF!
Name \0: #REF!
Name \a: #REF!
Name \a: #REF!
Name \d: #REF!
Name \d: #REF!
Name \e: #REF!
Name \e: #REF!
Name \f: #REF!
Name \f: #REF!
Name \g: #REF!
Name \g: #REF!
Name \h: #REF!
Name \h: #REF!
Name \i: #REF!
Name \i: #REF!
Name \j: #REF!
Name \j: #REF!
Name \k: #REF!
Name \k: #REF!
Name \l: #REF!
Name \l: #REF!
Name \m: #REF!
Name \m: #REF!
Name \n: #REF!
Name \n: #REF!
Name \o: #REF!
Name \o: #REF!
Name \p: #REF!
Name \p: #REF!
Name \T: #REF!
Name \T: #REF!
Name \z: #REF!
Name \z: #REF!
Name _: #REF!
Name _: #REF!
Name _?: #REF!
Name _?: #REF!
Name _??: #REF!
Name _??: #REF!
Name _???: #REF!
Name _???: #REF!
Name _??????: #REF!
Name _??????: #REF!
Name __________FIL2: #REF!
Name __________FIL2: #REF!
Name __________Ph30: #REF!
Name __________Ph30: #REF!
Name __________PXB80: #REF!
Name __________PXB80: #REF!
Name __________xb80: #REF!
Name __________xb80: #REF!
Name _____A65700: #REF!
Name _____A65700: #REF!
Name _____A65800: #REF!
Name _____A65800: #REF!
Name _____A67000: #REF!
Name _____A67000: #REF!
Name _____A68000: #REF!
Name _____A68000: #REF!

Sheet 1. Tổng hợp
A1: BẢNG TỔNG HỢP
A3: I | B3: Hiệu quả tài chính của dự án | C3: Đơn vị | D3: Giá trị
A4: 1 | B4: Dòng tiền dự án
B5: IRR dự án | C5: % | D5: ='8. Hiệu quả dự án và CĐT'!C21 -> 0.11584594
B6: NPV dự án | C6: đồng | D6: ='8. Hiệu quả dự án và CĐT'!C20 -> 7.6848969e+10
B7: IRR chủ đầu tư | C7: % | D7: ='8. Hiệu quả dự án và CĐT'!C49 -> 0.17607408
B8: NPV chủ đầu tư | C8: đồng | D8: ='8. Hiệu quả dự án và CĐT'!C48 -> 1.6125998e+10
B9: Return on Investment (ROI) | C9: % | D9: ='7. P&L TOÀN DỰ ÁN'!C24/('3. TMDT'!G15-'4. Vay'!C9) -> 0.45114229
A10: 2 | B10: Dòng tiền ngân hàng
B11: Vay ngân hàng | C11: đồng | D11: ='4. Vay'!C9 -> 7.9947434e+11
B12: Thời gian vay vốn | C12: năm | D12: =(COUNTIF('4. Vay'!E11:AS11,">1")+1)/4 -> 4
B13: Thời gian ân hạn | C13: năm | D13: =COUNTBLANK('4. Vay'!N10:AG10)/4 -> 2
A15: II | B15: Phương án Kinh doanh | C15: Đơn vị | D15: Giá trước thuế | E15: Thuế GTGT | F15: Giá sau thuế
B16: Tỷ lệ tăng giá bán hàng năm | C16: 0
A18: III | B18: Các chi phí khác
A19: 1 | B19: Chi phí bán hàng | C19: % doanh thu | D19: =D20+D21 -> 0.02
B20: Chi phí hoa hồng đại lý, môi giới | C20: % doanh thu | D20: 0
B21: Truyền thông Marketing | C21: % doanh thu | D21: 0.02
A22: 2 | B22: Chính sách bán hàng | C22: % doanh thu | D22: 0
A23: 3 | B23: Chi phí quản lý doanh nghiệp | C23: % doanh thu | D23: 0.02
A24: 4 | B24: Thuế VAT | D24: 0.1
A25: 5 | B25: Thuế TNDN | D25: 0.2
A26: 6 | B26: Lãi vay ngân hàng | C26: %/năm | D26: ='4. Vay'!E7*2/5+'4. Vay'!U7*3/5 -> 0.065
A29: IV | B29: Cơ cấu vốn | C29: Giá trị | D29: Tỷ lệ | E29: Chi phí vốn
A30: 1 | B30: Vốn CSH | C30: ='9. Cân đối dòng tiền (VCSH)'!C9 -> 249000000000 | D30: =C30/$C$33 -> 0.2097507 | E30: 0.15
A31: 3 | B31: Vốn vay | C31: ='9. Cân đối dòng tiền (VCSH)'!C8 -> 7.9947434e+11 | D31: =C31/$C$33 -> 0.67345503 | E31: =D26 -> 0.065
A32: 4 | B32: Vốn huy động khác (doanh thu bán hàng) | C32: =C33-C31-C30 -> 1.3864923e+11 | D32: =C32/$C$33 -> 0.11679427 | E32: 0.05
B33: TMĐT | C33: ='3. TMDT'!G15 -> 1.1871236e+12 | D33: =SUM(D30:D32) -> 1 | E33: =D30*E30+D31*E31*(1-D25)+D32*E32 -> 0.07232198
F35: IRR dự án
G36: Tỷ lệ thay đổi TMĐT
B37: Tỷ lệ thay đổi giá bán | C37: =0% -> 0 | E37: Tỷ lệ thay đổi giá bán | F37: =D5 -> 0.11584594 | G37: -0.05 | H37: -0.04 | I37: -0.03 | J37: -0.02 | K37: -0.01 | L37: 0 | M37: 0.01 | N37: 0.02 | O37: 0.03 | P37: 0.04 | Q37: 0.05
B38: Tỷ lệ thay đổi TMĐT | C38: =0% -> 0 | F38: -0.2 | G38: 0.14242528 | H38: 0.13686422 | I38: 0.13142963 | J38: 0.12611755 | K38: 0.12092421 | L38: 0.11584594 | M38: 0.11087925 | N38: 0.10602076 | O38: 0.10126724 | P38: 0.096615566 | Q38: 0.092062741
F39: -0.15 | G39: 0.14242528 | H39: 0.13686422 | I39: 0.13142963 | J39: 0.12611755 | K39: 0.12092421 | L39: 0.11584594 | M39: 0.11087925 | N39: 0.10602076 | O39: 0.10126724 | P39: 0.096615566 | Q39: 0.092062741
F40: -0.1 | G40: 0.14242528 | H40: 0.13686422 | I40: 0.13142963 | J40: 0.12611755 | K40: 0.12092421 | L40: 0.11584594 | M40: 0.11087925 | N40: 0.10602076 | O40: 0.10126724 | P40: 0.096615566 | Q40: 0.092062741
F41: -0.05 | G41: 0.14242528 | H41: 0.13686422 | I41: 0.13142963 | J41: 0.12611755 | K41: 0.12092421 | L41: 0.11584594 | M41: 0.11087925 | N41: 0.10602076 | O41: 0.10126724 | P41: 0.096615566 | Q41: 0.092062741
F42: 0 | G42: 0.14242528 | H42: 0.13686422 | I42: 0.13142963 | J42: 0.12611755 | K42: 0.12092421 | L42: 0.11584594 | M42: 0.11087925 | N42: 0.10602076 | O42: 0.10126724 | P42: 0.096615566 | Q42: 0.092062741
F43: 0.05 | G43: 0.14242528 | H43: 0.13686422 | I43: 0.13142963 | J43: 0.12611755 | K43: 0.12092421 | L43: 0.11584594 | M43: 0.11087925 | N43: 0.10602076 | O43: 0.10126724 | P43: 0.096615566 | Q43: 0.092062741
F44: 0.1 | G44: 0.14242528 | H44: 0.13686422 | I44: 0.13142963 | J44: 0.12611755 | K44: 0.12092421 | L44: 0.11584594 | M44: 0.11087925 | N44: 0.10602076 | O44: 0.10126724 | P44: 0.096615566 | Q44: 0.092062741
F45: 0.15 | G45: 0.14242528 | H45: 0.13686422 | I45: 0.13142963 | J45: 0.12611755 | K45: 0.12092421 | L45: 0.11584594 | M45: 0.11087925 | N45: 0.10602076 | O45: 0.10126724 | P45: 0.096615566 | Q45: 0.092062741
F46: 0.2 | G46: 0.14242528 | H46: 0.13686422 | I46: 0.13142963 | J46: 0.12611755 | K46: 0.12092421 | L46: 0.11584594 | M46: 0.11087925 | N46: 0.10602076 | O46: 0.10126724 | P46: 0.096615566 | Q46: 0.092062741
F48: IRR chủ đầu tư
G49: Tỷ lệ thay đổi TMĐT
E50: Tỷ lệ thay đổi giá bán | F50: =D7 -> 0.17607408 | G50: -0.05 | H50: -0.04 | I50: -0.03 | J50: -0.02 | K50: -0.01 | L50: 0 | M50: 0.01 | N50: 0.02 | O50: 0.03 | P50: 0.04 | Q50: 0.05
F51: -0.2 | G51: 0.23693705 | H51: 0.22401896 | I51: 0.21148662 | J51: 0.1993268 | K51: 0.18752672 | L51: 0.17607408 | M51: 0.164957 | N51: 0.15416402 | O51: 0.14368411 | P51: 0.1335066 | Q51: 0.12362121
F52: -0.15 | G52: 0.23693705 | H52: 0.22401896 | I52: 0.21148662 | J52: 0.1993268 | K52: 0.18752672 | L52: 0.17607408 | M52: 0.164957 | N52: 0.15416402 | O52: 0.14368411 | P52: 0.1335066 | Q52: 0.12362121
F53: -0.1 | G53: 0.23693705 | H53: 0.22401896 | I53: 0.21148662 | J53: 0.1993268 | K53: 0.18752672 | L53: 0.17607408 | M53: 0.164957 | N53: 0.15416402 | O53: 0.14368411 | P53: 0.1335066 | Q53: 0.12362121
F54: -0.05 | G54: 0.23693705 | H54: 0.22401896 | I54: 0.21148662 | J54: 0.1993268 | K54: 0.18752672 | L54: 0.17607408 | M54: 0.164957 | N54: 0.15416402 | O54: 0.14368411 | P54: 0.1335066 | Q54: 0.12362121
F55: 0 | G55: 0.23693705 | H55: 0.22401896 | I55: 0.21148662 | J55: 0.1993268 | K55: 0.18752672 | L55: 0.17607408 | M55: 0.164957 | N55: 0.15416402 | O55: 0.14368411 | P55: 0.1335066 | Q55: 0.12362121
F56: 0.05 | G56: 0.23693705 | H56: 0.22401896 | I56: 0.21148662 | J56: 0.1993268 | K56: 0.18752672 | L56: 0.17607408 | M56: 0.164957 | N56: 0.15416402 | O56: 0.14368411 | P56: 0.1335066 | Q56: 0.12362121
F57: 0.1 | G57: 0.23693705 | H57: 0.22401896 | I57: 0.21148662 | J57: 0.1993268 | K57: 0.18752672 | L57: 0.17607408 | M57: 0.164957 | N57: 0.15416402 | O57: 0.14368411 | P57: 0.1335066 | Q57: 0.12362121
F58: 0.15 | G58: 0.23693705 | H58: 0.22401896 | I58: 0.21148662 | J58: 0.1993268 | K58: 0.18752672 | L58: 0.17607408 | M58: 0.164957 | N58: 0.15416402 | O58: 0.14368411 | P58: 0.1335066 | Q58: 0.12362121
F59: 0.2 | G59: 0.23693705 | H59: 0.22401896 | I59: 0.21148662 | J59: 0.1993268 | K59: 0.18752672 | L59: 0.17607408 | M59: 0.164957 | N59: 0.15416402 | O59: 0.14368411 | P59: 0.1335066 | Q59: 0.12362121

Sheet 2. CPxaydung
A1: BẢNG 2: TỔNG HỢP CÁC CHI PHÍ XÂY DỰNG
H4: Đơn vị: vnđ
A5: STT | B5: Khoản mục chi phí | C5: Ký hiệu | D5: Diễn giải tính toán | G5: Thành tiền trước thuế | H5: Thuế GTGT | I5: Thành tiền sau thuế | J5: Ghi chú | L5: Tổng | M5: 45291 | N5: =EOMONTH(M5,3) -> 45382 | O5: =EOMONTH(N5,3) -> 45473 | P5: =EOMONTH(O5,3) -> 45565 | Q5: =EOMONTH(P5,3) -> 45657 | R5: =EOMONTH(Q5,3) -> 45747 | S5: =EOMONTH(R5,3) -> 45838 | T5: =EOMONTH(S5,3) -> 45930 | U5: =EOMONTH(T5,3) -> 46022 | ... BA5: =EOMONTH(AZ5,3) -> 48944
A6: A | B6: Chi phí xây dựng, thiết bị | C6: Gxd | G6: =SUM(G7:G9) -> 8.6824028e+11 | H6: =SUM(H7:H9) -> 8.6824028e+10 | I6: =SUM(I7:I9) -> 955064310000 | K6: =I6-L6 -> 0 | L6: =SUM(L7:L9) -> 955064310000 | M6: =SUM(M7:M9) -> 0 | N6: =SUM(N7:N9) -> 0 | O6: =SUM(O7:O9) -> 0 | P6: =SUM(P7:P9) -> 0 | Q6: =SUM(Q7:Q9) -> 0 | R6: =SUM(R7:R9) -> 0 | S6: =SUM(S7:S9) -> 0 | ... BA6: =SUM(BA7:BA9) -> 0
A7: 1 | B7: Chi phí xây dựng và thiết bị phần hạ tầng kỹ thuật | G7: =I7/(1+'1. Tổng hợp'!$D$24) -> 2.8275455e+10 | H7: =+G7*0.1 -> 2.8275455e+09 | I7: =31103000000*(1+'1. Tổng hợp'!$C$38) -> 31103000000 | K7: =I7-L7 -> 0 | L7: =SUM(M7:BA7) -> 31103000000 | M7: 0 | V7: =I7/8 -> 3887875000 | W7: =V7 -> 3887875000 | X7: =W7 -> 3887875000 | Y7: =X7 -> 3887875000 | Z7: =Y7 -> 3887875000 | AA7: =Z7 -> 3887875000 | AB7: =AA7 -> 3887875000 | AC7: =AB7 -> 3887875000
A8: 2 | B8: Chi phí xây dựng và thiết bị phần nhà ở, thương mại dịch vụ, công trình công cộng và y tế, giáo dục | G8: =I8/(1+'1. Tổng hợp'!$D$24) -> 7.8697364e+11 | H8: =+G8*0.1 -> 7.8697364e+10 | I8: =865671000000*(1+'1. Tổng hợp'!$C$38) -> 865671000000 | K8: =I8-L8 -> 0 | L8: =SUM(M8:AC8) -> 865671000000 | V8: =I8/8 -> 108208875000 | W8: =V8 -> 108208875000 | X8: =W8 -> 108208875000 | Y8: =X8 -> 108208875000 | Z8: =Y8 -> 108208875000 | AA8: =Z8 -> 108208875000 | AB8: =AA8 -> 108208875000 | AC8: =AB8 -> 108208875000
A9: 3 | B9: Chi phí quản lý dự án, chi phí tư vấn và chi phí khác | G9: =I9/(1+'1. Tổng hợp'!$D$24) -> 5.2991191e+10 | H9: =+G9*0.1 -> 5.2991191e+09 | I9: =58290310000*(1+'1. Tổng hợp'!$C$38) -> 58290310000 | K9: =I9-L9 -> 0 | L9: =SUM(M9:AC9) -> 58290310000 | V9: =I9/8 -> 7286288750 | W9: =V9 -> 7286288750 | X9: =W9 -> 7286288750 | Y9: =X9 -> 7286288750 | Z9: =Y9 -> 7286288750 | AA9: =Z9 -> 7286288750 | AB9: =AA9 -> 7286288750 | AC9: =AB9 -> 7286288750
A10: B | B10: Chi phí quản lý dự án + tư vấn + khác | C10: Gqlda | G10: =I10/(1+'1. Tổng hợp'!$D$24) -> 0 | H10: =+G10*0.1 -> 0 | I10: =0*(1+'1. Tổng hợp'!$C$38) -> 0 | K10: =I10-L10 -> 0 | L10: =SUM(M10:AC10) -> 0
A11: C | B11: Chi phí dự phòng | C11: Gdp | D11: 0.05 | E11: x(A+B+C+D+E) | G11: =I11/(1+'1. Tổng hợp'!$D$24) -> 1.3093411e+11 | H11: =+G11*0.1 -> 1.3093411e+10 | I11: =144027518205.24*(1+'1. Tổng hợp'!$C$38) -> 1.4402752e+11 | K11: =I11-L11 -> 0 | L11: =SUM(M11:AC11) -> 1.4402752e+11 | V11: =I11/8 -> 1.800344e+10 | W11: =V11 -> 1.800344e+10 | X11: =W11 -> 1.800344e+10 | Y11: =X11 -> 1.800344e+10 | Z11: =Y11 -> 1.800344e+10 | AA11: =Z11 -> 1.800344e+10 | AB11: =AA11 -> 1.800344e+10 | AC11: =AB11 -> 1.800344e+10
A12: D | B12: Tổng chi phí đầu tư | G12: =G6+G10+G11 -> 9.9917439e+11 | H12: =H6+H10+H11 -> 9.9917439e+10 | I12: =I6+I10+I11 -> 1.0990918e+12 | K12: =I12-L12 -> 0 | L12: =L6+L10+L11 -> 1.0990918e+12 | M12: =M6+M10+M11 -> 0 | N12: =N6+N10+N11 -> 0 | O12: =O6+O10+O11 -> 0 | P12: =P6+P10+P11 -> 0 | Q12: =Q6+Q10+Q11 -> 0 | R12: =R6+R10+R11 -> 0 | S12: =S6+S10+S11 -> 0 | ... BA12: =BA6+BA10+BA11 -> 0
A13: E | B13: LÀM TRÒN | D13: A+B+C+D+E+F | I13: =ROUND(I12,-3) -> 1099091828000

Sheet 3. TMDT
A1: BẢNG 3: TỔNG MỨC ĐẦU TƯ DỰ ÁN
G4: =SUM(G8:G8) -> 0 | H4: Đơn vị: vnđ
A5: STT | B5: Khoản mục chi phí | C5: Ký hiệu | D5: Cách tính | E5: Thành tiền trước thuế | F5: Thuế GTGT | G5: Thành tiền sau thuế | H5: Ghi chú | J5: Tổng | K5: ='2. CPxaydung'!M5 -> 45291 | L5: ='2. CPxaydung'!N5 -> 45382 | M5: ='2. CPxaydung'!O5 -> 45473 | N5: ='2. CPxaydung'!P5 -> 45565 | O5: ='2. CPxaydung'!Q5 -> 45657 | P5: ='2. CPxaydung'!R5 -> 45747 | Q5: ='2. CPxaydung'!S5 -> 45838 | R5: ='2. CPxaydung'!T5 -> 45930 | ... AY5: ='2. CPxaydung'!BA5 -> 48944
A6: A | B6: Tổng chi phí đầu tư xây dựng dự án | E6: =SUBTOTAL(9,E7:E9) -> 9.9917439e+11 | F6: =SUBTOTAL(9,F7:F9) -> 9.9917439e+10 | G6: =SUBTOTAL(9,G7:G9) -> 1.0990918e+12 | J6: =SUBTOTAL(9,J7:J9) -> 1.0990918e+12 | K6: =SUBTOTAL(9,K7:K9) -> 0 | L6: =SUBTOTAL(9,L7:L9) -> 0 | M6: =SUBTOTAL(9,M7:M9) -> 0 | N6: =SUBTOTAL(9,N7:N9) -> 0 | O6: =SUBTOTAL(9,O7:O9) -> 0 | P6: =SUBTOTAL(9,P7:P9) -> 0 | Q6: =SUBTOTAL(9,Q7:Q9) -> 0 | ... AY6: =SUBTOTAL(9,AY7:AY9) -> 0
A7: 1 | B7: ='2. CPxaydung'!B6 -> Chi phí xây dựng, thiết bị | C7: Gxd | E7: =SUMIFS('2. CPxaydung'!$G$5:$G$14,'2. CPxaydung'!$C$5:$C$14,'3. TMDT'!C7) -> 8.6824028e+11 | F7: =+E7*'1. Tổng hợp'!$D$24 -> 8.6824028e+10 | G7: =E7+F7 -> 9.5506431e+11 | I7: =G7-J7 -> 0 | J7: =SUM(K7:AY7) -> 955064310000 | K7: ='2. CPxaydung'!M6 -> 0 | L7: ='2. CPxaydung'!N6 -> 0 | M7: ='2. CPxaydung'!O6 -> 0 | N7: ='2. CPxaydung'!P6 -> 0 | O7: ='2. CPxaydung'!Q6 -> 0 | P7: ='2. CPxaydung'!R6 -> 0 | Q7: ='2. CPxaydung'!S6 -> 0 | R7: ='2. CPxaydung'!T6 -> 0 | ... AY7: ='2. CPxaydung'!BA6 -> 0
A8: 2 | B8: ='2. CPxaydung'!B10 -> Chi phí quản lý dự án + tư vấn + khác | C8: Gqlda | E8: =SUMIFS('2. CPxaydung'!$G$5:$G$14,'2. CPxaydung'!$C$5:$C$14,'3. TMDT'!C8) -> 0 | F8: =+E8*'1. Tổng hợp'!$D$24 -> 0 | G8: =E8+F8 -> 0 | I8: =G8-J8 -> 0 | J8: =SUM(K8:AY8) -> 0 | K8: ='2. CPxaydung'!M10 -> 0 | L8: ='2. CPxaydung'!N10 -> 0 | M8: ='2. CPxaydung'!O10 -> 0 | N8: ='2. CPxaydung'!P10 -> 0 | O8: ='2. CPxaydung'!Q10 -> 0 | P8: ='2. CPxaydung'!R10 -> 0 | Q8: ='2. CPxaydung'!S10 -> 0 | R8: ='2. CPxaydung'!T10 -> 0 | ... AE8: ='2. CPxaydung'!AG10 -> 0 | AF8: ='2. CPxaydung'!AD10 -> 0 | AG8: ='2. CPxaydung'!AE10 -> 0 | AH8: ='2. CPxaydung'!AF10 -> 0 | AI8: ='2. CPxaydung'!AG10 -> 0 | AJ8: ='2. CPxaydung'!AL10 -> 0 | AK8: ='2. CPxaydung'!AM10 -> 0 | AL8: ='2. CPxaydung'!AN10 -> 0 | AM8: ='2. CPxaydung'!AO10 -> 0 | AN8: ='2. CPxaydung'!AP10 -> 0 | AO8: ='2. CPxaydung'!AQ10 -> 0 | AP8: ='2. CPxaydung'!AR10 -> 0 | AQ8: ='2. CPxaydung'!AS10 -> 0 | ... AY8: ='2. CPxaydung'!BA10 -> 0
A9: 3 | B9: ='2. CPxaydung'!B11 -> Chi phí dự phòng | C9: Gdp | E9: =SUMIFS('2. CPxaydung'!$G$5:$G$14,'2. CPxaydung'!$C$5:$C$14,'3. TMDT'!C9) -> 1.3093411e+11 | F9: =+E9*'1. Tổng hợp'!$D$24 -> 1.3093411e+10 | G9: =E9+F9 -> 1.4402752e+11 | I9: =G9-J9 -> 0 | J9: =SUM(K9:AY9) -> 1.4402752e+11 | K9: ='2. CPxaydung'!M11 -> 0 | L9: ='2. CPxaydung'!N11 -> 0 | M9: ='2. CPxaydung'!O11 -> 0 | N9: ='2. CPxaydung'!P11 -> 0 | O9: ='2. CPxaydung'!Q11 -> 0 | P9: ='2. CPxaydung'!R11 -> 0 | Q9: ='2. CPxaydung'!S11 -> 0 | R9: ='2. CPxaydung'!T11 -> 0 | ... AE9: ='2. CPxaydung'!AG11 -> 0 | AF9: ='2. CPxaydung'!AD11 -> 0 | AG9: ='2. CPxaydung'!AE11 -> 0 | AH9: ='2. CPxaydung'!AF11 -> 0 | AI9: ='2. CPxaydung'!AG11 -> 0 | AJ9: ='2. CPxaydung'!AL11 -> 0 | AK9: ='2. CPxaydung'!AM11 -> 0 | AL9: ='2. CPxaydung'!AN11 -> 0 | AM9: ='2. CPxaydung'!AO11 -> 0 | AN9: ='2. CPxaydung'!AP11 -> 0 | AO9: ='2. CPxaydung'!AQ11 -> 0 | AP9: ='2. CPxaydung'!AR11 -> 0 | AQ9: ='2. CPxaydung'!AS11 -> 0 | ... AY9: ='2. CPxaydung'!BA11 -> 0
A10: B | B10: Chi phí GPMB và tiền sử dụng đất | E10: =G10 -> 43014372094 | F10: 0 | G10: =43014372094*(1+'1. Tổng hợp'!$C$38) -> 43014372094 | I10: =G10-J10 -> 0 | J10: =SUM(K10:AY10) -> 43014372094 | T10: =G10 -> 43014372094
A11: C | B11: Chi phí M&A | E11: 0 | G11: 0 | J11: =SUM(K11:AY11) -> 0
A12: D | B12: Chi phí PTDA | C12: PTDA | E12: 0 | G12: =+E12 -> 0 | J12: =SUM(K12:AY12) -> 0
A13: H | B13: Tổng cộng (A+B+C+D) | E13: =E6+E10+E11+E12 -> 1.0421888e+12 | F13: =F6+F10+F11+F12 -> 9.9917439e+10 | G13: =G6+G10+G11+G12 -> 1.1421062e+12 | I13: =G13-J13 -> 0 | J13: =J6+J10+J11+J12 -> 1.1421062e+12 | K13: =K6+K10+K11+K12 -> 0 | L13: =L6+L10+L11+L12 -> 0 | M13: =M6+M10+M11+M12 -> 0 | N13: =N6+N10+N11+N12 -> 0 | O13: =O6+O10+O11+O12 -> 0 | P13: =P6+P10+P11+P12 -> 0 | Q13: =Q6+Q10+Q11+Q12 -> 0 | ... AY13: =AY6+AY10+AY11+AY12 -> 0
A14: I | B14: Lãi vay trong giai đoạn xây dựng | C14: Lv | E14: =J14 -> 4.501737e+10 | G14: =E14 -> 4.501737e+10 | I14: =G14-J14 -> 0 | J14: =SUM(K14:AY14) -> 4.501737e+10 | K14: =+'4. Vay'!E22 -> 0 | L14: =+'4. Vay'!F22 -> 0 | M14: =+'4. Vay'!G22 -> 0 | N14: =+'4. Vay'!H22 -> 0 | O14: =+'4. Vay'!I22 -> 0 | P14: =+'4. Vay'!J22 -> 0 | Q14: =+'4. Vay'!K22 -> 0 | R14: =+'4. Vay'!L22 -> 0 | ... AY14: =+'4. Vay'!AS22 -> 0
B15: TỔNG VỐN ĐẦU TƯ (H+I+G) | C15: TVĐT | E15: =E13+E14 -> 1.0872061e+12 | F15: =F13+F14 -> 9.9917439e+10 | G15: =G13+G14 -> 1.1871236e+12 | I15: =G15-J15 -> 0 | J15: =J13+J14 -> 1.1871236e+12 | K15: =K13+K14 -> 0 | L15: =L13+L14 -> 0 | M15: =M13+M14 -> 0 | N15: =N13+N14 -> 0 | O15: =O13+O14 -> 0 | P15: =P13+P14 -> 0 | Q15: =Q13+Q14 -> 0 | ... AY15: =AY13+AY14 -> 0
B16: LÀM TRÒN | G16: =ROUND(G15,-6) -> 1187124000000 | J16: =SUM(K16:T16) -> 0

Sheet 4. Vay
A1: BẢNG 4: KẾ HOẠCH VAY VỐN
I4: 1 | J4: =I4+1 -> 2 | K4: =J4+1 -> 3 | L4: =K4+1 -> 4 | M4: =L4+1 -> 5 | N4: =M4+1 -> 6 | O4: =N4+1 -> 7 | P4: =O4+1 -> 8 | Q4: =P4+1 -> 9 | ... AS4: =AR4+1 -> 37
A5: STT | B5: CÁC YẾU TỐ | C5: TỔNG CỘNG | D5: Đơn vị | E5: KỲ VAY VỐN
E6: =+'5. KHBH'!FK4 -> 45291 | F6: =+'5. KHBH'!FL4 -> 45382 | G6: =+'5. KHBH'!FM4 -> 45473 | H6: =+'5. KHBH'!FN4 -> 45565 | I6: =+'5. KHBH'!FO4 -> 45657 | J6: =+'5. KHBH'!FP4 -> 45747 | K6: =+'5. KHBH'!FQ4 -> 45838 | L6: =+'5. KHBH'!FR4 -> 45930 | ... AS6: =+'5. KHBH'!GY4 -> 48944
B7: Lãi suất | D7: %/năm | E7: 0.065 | F7: =E7 -> 0.065 | G7: =+F7 -> 0.065 | H7: =+G7 -> 0.065 | I7: =+H7 -> 0.065 | J7: =E7 -> 0.065 | K7: =+J7 -> 0.065 | L7: =+K7 -> 0.065 | M7: =+L7 -> 0.065 | N7: =+M7 -> 0.065 | O7: =+N7 -> 0.065 | P7: =+O7 -> 0.065 | Q7: =P7 -> 0.065 | R7: =Q7 -> 0.065 | S7: =+R7 -> 0.065 | T7: =+S7 -> 0.065 | U7: =T7 -> 0.065 | V7: =+U7 -> 0.065 | W7: =+V7 -> 0.065 | X7: =+W7 -> 0.065 | Y7: =+X7 -> 0.065 | Z7: =+Y7 -> 0.065 | AA7: =+Z7 -> 0.065 | AB7: =+AA7 -> 0.065 | AC7: =+I7 -> 0.065 | AD7: =+J7 -> 0.065 | AE7: =+K7 -> 0.065 | AF7: =+L7 -> 0.065 | AG7: =+M7 -> 0.065 | AH7: =+N7 -> 0.065 | AI7: =+O7 -> 0.065 | AJ7: =+P7 -> 0.065 | ... AS7: =+Y7 -> 0.065
B8: Dư nợ đầu kỳ | D8: vnđ | I8: =+H11 -> 0 | J8: =+I11 -> 0 | K8: =+J11 -> 0 | L8: =+K11 -> 0 | M8: =+L11 -> 0 | N8: =+M11 -> 0 | O8: =+N11 -> 1.262806e+11 | P8: =+O11 -> 2.2245113e+11 | ... AS8: =+AR11 -> 0
B9: Giải ngân trong kỳ | C9: =SUM(E9:AS9) -> 7.9947434e+11 | D9: vnđ | E9: 0 | F9: 0 | G9: 0 | H9: 0 | M9: =('3. TMDT'!S6+'3. TMDT'!S10)*60% -> 0 | N9: =('3. TMDT'!T6+'3. TMDT'!T10)*70% -> 1.262806e+11 | O9: =('3. TMDT'!U6+'3. TMDT'!U10)*70% -> 9.6170535e+10 | P9: =('3. TMDT'!V6+'3. TMDT'!V10)*70% -> 9.6170535e+10 | Q9: =('3. TMDT'!W6+'3. TMDT'!W10)*70% -> 9.6170535e+10 | R9: =('3. TMDT'!X6+'3. TMDT'!X10)*70% -> 9.6170535e+10 | S9: =('3. TMDT'!Y6+'3. TMDT'!Y10)*70% -> 9.6170535e+10 | T9: =('3. TMDT'!Z6+'3. TMDT'!Z10)*70% -> 9.6170535e+10 | U9: =('3. TMDT'!AA6+'3. TMDT'!AA10)*70% -> 9.6170535e+10
B10: Trả nợ trong kỳ | C10: =SUM(E10:AS10) -> 7.9947434e+11 | D10: vnđ | R10: =C9/12 -> 6.6622862e+10 | S10: =R10 -> 6.6622862e+10 | T10: =S10 -> 6.6622862e+10 | U10: =T10 -> 6.6622862e+10 | V10: =U10 -> 6.6622862e+10 | W10: =V10 -> 6.6622862e+10 | X10: =W10 -> 6.6622862e+10 | Y10: =X10 -> 6.6622862e+10 | Z10: =Y10 -> 6.6622862e+10 | ... AB10: =AA10 -> 6.6622862e+10 | AC10: 6.6622862e+10
B11: Dư nợ cuối kỳ | D11: vnđ | E11: =+E8+E9-E10 -> 0 | F11: =+F8+F9-F10 -> 0 | G11: =+G8+G9-G10 -> 0 | H11: =+H8+H9-H10 -> 0 | I11: =+I8+I9-I10 -> 0 | J11: =+J8+J9-J10 -> 0 | K11: =+K8+K9-K10 -> 0 | L11: =+L8+L9-L10 -> 0 | ... AS11: =+AS8+AS9-AS10 -> 0
B12: Lãi vay trong kỳ | C12: =SUM(E12:AS12) -> 7.9661258e+10 | D12: vnđ | E12: 0 | F12: =+(F8+F11)*F7/(2*4) -> 0 | G12: =+(G8+G11)*G7/(2*4) -> 0 | H12: =+(H8+H11)*H7/(2*4) -> 0 | I12: =+(I8+I11)*I7/(2*4) -> 0 | J12: =+(J8+J11)*J7/(2*4) -> 0 | K12: =+(K8+K11)*K7/(2*4) -> 0 | L12: =+(L8+L11)*L7/(2*4) -> 0 | M12: =+(M8+M11)*M7/(2*4) -> 0 | ... AS12: =+(AS8+AS11)*AS7/(2*4) -> 0
B13: Kế hoạch trả lãi trong kỳ | C13: =SUM(E13:AS13) -> 7.9661258e+10 | D13: vnđ | E13: =+E12 -> 0 | F13: =+F12 -> 0 | G13: =+G12 -> 0 | H13: =+H12 -> 0 | I13: =+I12 -> 0 | J13: =+J12 -> 0 | K13: =+K12 -> 0 | L13: =+L12 -> 0 | ... AS13: =+AS12 -> 0
A15: TỔNG CẢ GỐC VÀ LÃI | C15: =+C10+C13 -> 8.791356e+11 | J15: =J10+J12 -> 0 | K15: =K10+K12 -> 0 | L15: =L10+L12 -> 0 | M15: =M10+M12 -> 0 | N15: =N10+N12 -> 1.0260298e+09 | O15: =O10+O12 -> 2.8334453e+09 | P15: =P10+P12 -> 4.3962165e+09 | Q15: =Q10+Q12 -> 5.9589877e+09 | ... AS15: =AS10+AS12 -> 0
J17: =+#REF!*J7/(2*4) -> #REF!
C18: =INDEX(F6:AS6,1,MATCH(C20,F20:AS20,0)) -> 46752
B19: Lãi vay
B20: Lũy kế chi phí xây dựng, thiết bị | C20: ='2. CPxaydung'!I6 -> 955064310000 | F20: =SUM('2. CPxaydung'!$N$6:'2. CPxaydung'!N6) -> 0 | G20: =SUM('2. CPxaydung'!$N$6:'2. CPxaydung'!O6) -> 0 | H20: =SUM('2. CPxaydung'!$N$6:'2. CPxaydung'!P6) -> 0 | I20: =SUM('2. CPxaydung'!$N$6:'2. CPxaydung'!Q6) -> 0 | J20: =SUM('2. CPxaydung'!$N$6:'2. CPxaydung'!R6) -> 0 | K20: =SUM('2. CPxaydung'!$N$6:'2. CPxaydung'!S6) -> 0 | L20: =SUM('2. CPxaydung'!$N$6:'2. CPxaydung'!T6) -> 0 | M20: =SUM('2. CPxaydung'!$N$6:'2. CPxaydung'!U6) -> 0 | ... AS20: =SUM('2. CPxaydung'!$N$6:'2. CPxaydung'!BA6) -> 955064310000
B21: Thời điểm kết thúc XD | C21: 46752
B22: Lãi vay trong giai đoạn xây dựng | C22: =SUM(E22:AS22) -> 4.501737e+10 | F22: =IF(F6<=$C$21,F12,0) -> 0 | G22: =IF(G6<=$C$21,G12,0) -> 0 | H22: =IF(H6<=$C$21,H12,0) -> 0 | I22: =IF(I6<=$C$21,I12,0) -> 0 | J22: =IF(J6<=$C$21,J12,0) -> 0 | K22: =IF(K6<=$C$21,K12,0) -> 0 | L22: =IF(L6<=$C$21,L12,0) -> 0 | M22: =IF(M6<=$C$21,M12,0) -> 0 | ... AS22: =IF(AS6<=$C$21,AS12,0) -> 0
B23: Lãi vay trong kỳ | C23: =SUM(E23:AS23) -> 3.4643888e+10 | F23: =IF(F6>$C$21,F12,0) -> 0 | G23: =IF(G6>$C$21,G12,0) -> 0 | H23: =IF(H6>$C$21,H12,0) -> 0 | I23: =IF(I6>$C$21,I12,0) -> 0 | J23: =IF(J6>$C$21,J12,0) -> 0 | K23: =IF(K6>$C$21,K12,0) -> 0 | L23: =IF(L6>$C$21,L12,0) -> 0 | M23: =IF(M6>$C$21,M12,0) -> 0 | ... AS23: =IF(AS6>$C$21,AS12,0) -> 0

Sheet 5. KHBH
B1: BẢNG 5: KẾ HOẠCH BÁN HÀNG | P1: =SUBTOTAL(9,P8:P11) -> 1535939420000
P2: =SUBTOTAL(9,P8:P11) -> 1535939420000 | Z2: =SUBTOTAL(9,Z8:Z11) -> 0 | AA2: =SUBTOTAL(9,AA8:AA11) -> 1535939420000 | AB2: 44742 | AC2: 44834 | AD2: =AC2 -> 44834 | AE2: =AD2 -> 44834 | AF2: =EOMONTH(AC2,3) -> 44926 | AG2: =EOMONTH(AD2,3) -> 44926 | AH2: =EOMONTH(AE2,3) -> 44926 | AI2: =EOMONTH(AF2,3) -> 45016 | AJ2: =EOMONTH(AG2,3) -> 45016 | AK2: =EOMONTH(AH2,3) -> 45016 | AL2: =EOMONTH(AI2,3) -> 45107 | AM2: =EOMONTH(AJ2,3) -> 45107 | ... FJ2: =EOMONTH(FG2,3) -> 48944
B3: STT | C3: SẢN PHẨM | I3: LOẠI SẢN PHẦM | J3: THỜI GIAN BÁN | K3: KẾ HOẠCH BÁN HÀNG | R3: TIẾN ĐỘ THU TIỀN THÔNG THƯỜNG | AB3: KẾ HOẠCH THU TIỀN THEO THÁNG | FK3: KẾ HOẠCH THU TIỀN THEO QUÝ
B4: STT | D4: MÃ CĂN | E4: NOTE 1 | F4: NOTE 2 | G4: NOTE 3 | H4: KHU VỰC | K4: Số căn | L4: Diện tích xây dựng | M4: Diện tích thương phẩm | N4: DG đất + xây (gồm VAT) | O4: DG đất + xây có tăng giá (gồm VAT) | P4: Tổng giá trị hợp đồng | Q4: Thời điểm ghi nhận doanh thu | R4: Đợt 1 | S4: Đợt 2 | T4: Đợt 3 | U4: Đợt 4 | V4: Đợt 5 | W4: Đợt 6 | X4: Đợt 7 | Y4: Đợt 8 | AB4: 44713 | AC4: =+EDATE(AB4,1) -> 44743 | AD4: =+EDATE(AC4,1) -> 44774 | AE4: =+EDATE(AD4,1) -> 44805 | AF4: =+EDATE(AE4,1) -> 44835 | AG4: =+EDATE(AF4,1) -> 44866 | AH4: =+EDATE(AG4,1) -> 44896 | AI4: =+EDATE(AH4,1) -> 44927 | AJ4: =+EDATE(AI4,1) -> 44958 | ... FJ4: =+EDATE(FI4,1) -> 48914 | FK4: =+'3. TMDT'!K5 -> 45291 | FL4: =+'3. TMDT'!L5 -> 45382 | FM4: =+'3. TMDT'!M5 -> 45473 | FN4: =+'3. TMDT'!N5 -> 45565 | FO4: =+'3. TMDT'!O5 -> 45657 | FP4: =+'3. TMDT'!P5 -> 45747 | FQ4: =+'3. TMDT'!Q5 -> 45838 | FR4: =+'3. TMDT'!R5 -> 45930 | ... GY4: =+'3. TMDT'!AY5 -> 48944
C5: Tiến độ thu tiền nhà ở xã hội | R5: 0.3 | S5: 0.1 | T5: 0.1 | U5: 0.1 | V5: 0.1 | W5: 0.25 | X5: 0 | Y5: 0.05
C6: Tiến độ thu tiền nhà liền kề | R6: 0.3 | S6: 0.15 | T6: 0.15 | U6: 0.1 | V6: 0.25 | W6: 0 | X6: 0 | Y6: 0.05
B8: 1 | C8: Nhà ở xã hội 1 | I8: =C8 -> Nhà ở xã hội 1 | J8: 46388 | K8: 429.23496 | L8: 2787.24 | M8: 21461.748 | N8: 22500000 | O8: {=_xlfn.IFS( YEAR(R8)=2027,N8,YEAR(R8)=2028,N8*(1+'1. Tổng hợp'!$C$16),YEAR(R8)=2029,N8*(1+'1. Tổng hợp'!$C$16)^2, YEAR(R8)=2030,N8*(1+'1. Tổng hợp'!$C$16)^3,YEAR(R8)=2031,N8*(1+'1. Tổng hợp'!$C$16)^3)} -> 22500000 | P8: =M8*O8 -> 4.8288933e+11 | Q8: =+X8 -> 47119 | R8: =J8 -> 46388 | S8: =EDATE(R8,2) -> 46447 | T8: =EDATE(S8,2) -> 46508 | U8: =EDATE(T8,2) -> 46569 | V8: =EDATE(U8,2) -> 46631 | W8: =EDATE(V8,16) -> 47119 | X8: =W8 -> 47119 | Y8: =EDATE(X8,1) -> 47150 | Z8: =+P8-AA8 -> 0 | AA8: =SUM(AB8:FJ8) -> 482889330000 | AB8: =SUMIF($R8:$Y8,AB$4,$R$5:$Y$5)*$P8 -> 0 | AC8: =SUMIF($R8:$Y8,AC$4,$R$5:$Y$5)*$P8 -> 0 | AD8: =SUMIF($R8:$Y8,AD$4,$R$5:$Y$5)*$P8 -> 0 | AE8: =SUMIF($R8:$Y8,AE$4,$R$5:$Y$5)*$P8 -> 0 | AF8: =SUMIF($R8:$Y8,AF$4,$R$5:$Y$5)*$P8 -> 0 | AG8: =SUMIF($R8:$Y8,AG$4,$R$5:$Y$5)*$P8 -> 0 | AH8: =SUMIF($R8:$Y8,AH$4,$R$5:$Y$5)*$P8 -> 0 | AI8: =SUMIF($R8:$Y8,AI$4,$R$5:$Y$5)*$P8 -> 0 | ... FJ8: =SUMIF($R8:$Y8,FJ$4,$R$5:$Y$5)*$P8 -> 0 | FL8: =SUMIFS($AB8:$FF8,$AB$2:$FF$2,FL$4) -> 0 | FM8: =SUMIFS($AB8:$FF8,$AB$2:$FF$2,FM$4) -> 0 | FN8: =SUMIFS($AB8:$FF8,$AB$2:$FF$2,FN$4) -> 0 | FO8: =SUMIFS($AB8:$FF8,$AB$2:$FF$2,FO$4) -> 0 | FP8: =SUMIFS($AB8:$FF8,$AB$2:$FF$2,FP$4) -> 0 | FQ8: =SUMIFS($AB8:$FF8,$AB$2:$FF$2,FQ$4) -> 0 | FR8: =SUMIFS($AB8:$FF8,$AB$2:$FF$2,FR$4) -> 0 | FS8: =SUMIFS($AB8:$FF8,$AB$2:$FF$2,FS$4) -> 0 | ... GY8: =SUMIFS($AB8:$FF8,$AB$2:$FF$2,GY$4) -> 0
B9: 2 | C9: Nhà ở xã hội 2 | I9: =C9 -> Nhà ở xã hội 2 | J9: 46753 | K9: 349.12416 | L9: 2267.04 | M9: 17456.208 | N9: 22500000 | O9: {=_xlfn.IFS( YEAR(R9)=2027,N9,YEAR(R9)=2028,N9*(1+'1. Tổng hợp'!$C$16),YEAR(R9)=2029,N9*(1+'1. Tổng hợp'!$C$16)^2, YEAR(R9)=2030,N9*(1+'1. Tổng hợp'!$C$16)^3,YEAR(R9)=2031,N9*(1+'1. Tổng hợp'!$C$16)^3)} -> 22500000 | P9: =M9*O9 -> 392764680000 | Q9: =+X9 -> 47484 | R9: =J9 -> 46753 | S9: =EDATE(R9,2) -> 46813 | T9: =EDATE(S9,2) -> 46874 | U9: =EDATE(T9,2) -> 46935 | V9: =EDATE(U9,2) -> 46997 | W9: =EDATE(V9,16) -> 47484 | X9: =W9 -> 47484 | Y9: =EDATE(X9,1) -> 47515 | Z9: =+P9-AA9 -> 0 | AA9: =SUM(AB9:FJ9) -> 392764680000 | AB9: =SUMIF($R9:$Y9,AB$4,$R$5:$Y$5)*$P9 -> 0 | AC9: =SUMIF($R9:$Y9,AC$4,$R$5:$Y$5)*$P9 -> 0 | AD9: =SUMIF($R9:$Y9,AD$4,$R$5:$Y$5)*$P9 -> 0 | AE9: =SUMIF($R9:$Y9,AE$4,$R$5:$Y$5)*$P9 -> 0 | AF9: =SUMIF($R9:$Y9,AF$4,$R$5:$Y$5)*$P9 -> 0 | AG9: =SUMIF($R9:$Y9,AG$4,$R$5:$Y$5)*$P9 -> 0 | AH9: =SUMIF($R9:$Y9,AH$4,$R$5:$Y$5)*$P9 -> 0 | AI9: =SUMIF($R9:$Y9,AI$4,$R$5:$Y$5)*$P9 -> 0 | ... FJ9: =SUMIF($R9:$Y9,FJ$4,$R$5:$Y$5)*$P9 -> 0 | FL9: =SUMIFS($AB9:$FF9,$AB$2:$FF$2,FL$4) -> 0 | FM9: =SUMIFS($AB9:$FF9,$AB$2:$FF$2,FM$4) -> 0 | FN9: =SUMIFS($AB9:$FF9,$AB$2:$FF$2,FN$4) -> 0 | FO9: =SUMIFS($AB9:$FF9,$AB$2:$FF$2,FO$4) -> 0 | FP9: =SUMIFS($AB9:$FF9,$AB$2:$FF$2,FP$4) -> 0 | FQ9: =SUMIFS($AB9:$FF9,$AB$2:$FF$2,FQ$4) -> 0 | FR9: =SUMIFS($AB9:$FF9,$AB$2:$FF$2,FR$4) -> 0 | FS9: =SUMIFS($AB9:$FF9,$AB$2:$FF$2,FS$4) -> 0 | ... GY9: =SUMIFS($AB9:$FF9,$AB$2:$FF$2,GY$4) -> 0
B10: 3 | C10: Nhà ở xã hội 3 | I10: =C10 -> Nhà ở xã hội 3 | J10: 47119 | K10: 289.28592 | L10: 1878.48 | M10: 14464.296 | N10: 22500000 | O10: {=_xlfn.IFS( YEAR(R10)=2027,N10,YEAR(R10)=2028,N10*(1+'1. Tổng hợp'!$C$16),YEAR(R10)=2029,N10*(1+'1. Tổng hợp'!$C$16)^2, YEAR(R10)=2030,N10*(1+'1. Tổng hợp'!$C$16)^3,YEAR(R10)=2031,N10*(1+'1. Tổng hợp'!$C$16)^3)} -> 22500000 | P10: =M10*O10 -> 3.2544666e+11 | Q10: =+X10 -> 47849 | R10: =J10 -> 47119 | S10: =EDATE(R10,2) -> 47178 | T10: =EDATE(S10,2) -> 47239 | U10: =EDATE(T10,2) -> 47300 | V10: =EDATE(U10,2) -> 47362 | W10: =EDATE(V10,16) -> 47849 | X10: =W10 -> 47849 | Y10: =EDATE(X10,1) -> 47880 | Z10: =+P10-AA10 -> 0 | AA10: =SUM(AB10:FJ10) -> 3.2544666e+11 | AB10: =SUMIF($R10:$Y10,AB$4,$R$5:$Y$5)*$P10 -> 0 | AC10: =SUMIF($R10:$Y10,AC$4,$R$5:$Y$5)*$P10 -> 0 | AD10: =SUMIF($R10:$Y10,AD$4,$R$5:$Y$5)*$P10 -> 0 | AE10: =SUMIF($R10:$Y10,AE$4,$R$5:$Y$5)*$P10 -> 0 | AF10: =SUMIF($R10:$Y10,AF$4,$R$5:$Y$5)*$P10 -> 0 | AG10: =SUMIF($R10:$Y10,AG$4,$R$5:$Y$5)*$P10 -> 0 | AH10: =SUMIF($R10:$Y10,AH$4,$R$5:$Y$5)*$P10 -> 0 | AI10: =SUMIF($R10:$Y10,AI$4,$R$5:$Y$5)*$P10 -> 0 | ... FJ10: =SUMIF($R10:$Y10,FJ$4,$R$5:$Y$5)*$P10 -> 0 | FL10: =SUMIFS($AB10:$FF10,$AB$2:$FF$2,FL$4) -> 0 | FM10: =SUMIFS($AB10:$FF10,$AB$2:$FF$2,FM$4) -> 0 | FN10: =SUMIFS($AB10:$FF10,$AB$2:$FF$2,FN$4) -> 0 | FO10: =SUMIFS($AB10:$FF10,$AB$2:$FF$2,FO$4) -> 0 | FP10: =SUMIFS($AB10:$FF10,$AB$2:$FF$2,FP$4) -> 0 | FQ10: =SUMIFS($AB10:$FF10,$AB$2:$FF$2,FQ$4) -> 0 | FR10: =SUMIFS($AB10:$FF10,$AB$2:$FF$2,FR$4) -> 0 | FS10: =SUMIFS($AB10:$FF10,$AB$2:$FF$2,FS$4) -> 0 | ... GY10: =SUMIFS($AB10:$FF10,$AB$2:$FF$2,GY$4) -> 0
B11: 4 | C11: Liền kề 1 | I11: =C11 -> Liền kề 1 | J11: 46753 | K11: 51 | L11: 4320.5 | M11: 4320.5 | N11: 77500000 | O11: {=_xlfn.IFS( YEAR(R11)=2027,N11,YEAR(R11)=2028,N11*(1+'1. Tổng hợp'!$C$16),YEAR(R11)=2029,N11*(1+'1. Tổng hợp'!$C$16)^2, YEAR(R11)=2030,N11*(1+'1. Tổng hợp'!$C$16)^3,YEAR(R11)=2031,N11*(1+'1. Tổng hợp'!$C$16)^3)} -> 77500000 | P11: =M11*O11 -> 334838750000 | Q11: =+X11 -> 47119 | R11: =J11 -> 46753 | S11: =EDATE(R11,3) -> 46844 | T11: =EDATE(S11,3) -> 46935 | U11: =EDATE(T11,3) -> 47027 | V11: =EDATE(U11,3) -> 47119 | W11: =V11 -> 47119 | X11: =W11 -> 47119 | Y11: =EDATE(X11,1) -> 47150 | Z11: =+P11-AA11 -> 0 | AA11: =SUM(AB11:FJ11) -> 334838750000 | AB11: =SUMIF($R11:$Y11,AB$4,$R$5:$Y$5)*$P11 -> 0 | AC11: =SUMIF($R11:$Y11,AC$4,$R$5:$Y$5)*$P11 -> 0 | AD11: =SUMIF($R11:$Y11,AD$4,$R$5:$Y$5)*$P11 -> 0 | AE11: =SUMIF($R11:$Y11,AE$4,$R$5:$Y$5)*$P11 -> 0 | AF11: =SUMIF($R11:$Y11,AF$4,$R$5:$Y$5)*$P11 -> 0 | AG11: =SUMIF($R11:$Y11,AG$4,$R$5:$Y$5)*$P11 -> 0 | AH11: =SUMIF($R11:$Y11,AH$4,$R$5:$Y$5)*$P11 -> 0 | AI11: =SUMIF($R11:$Y11,AI$4,$R$5:$Y$5)*$P11 -> 0 | ... FJ11: =SUMIF($R11:$Y11,FJ$4,$R$5:$Y$5)*$P11 -> 0 | FL11: =SUMIFS($AB11:$FF11,$AB$2:$FF$2,FL$4) -> 0 | FM11: =SUMIFS($AB11:$FF11,$AB$2:$FF$2,FM$4) -> 0 | FN11: =SUMIFS($AB11:$FF11,$AB$2:$FF$2,FN$4) -> 0 | FO11: =SUMIFS($AB11:$FF11,$AB$2:$FF$2,FO$4) -> 0 | FP11: =SUMIFS($AB11:$FF11,$AB$2:$FF$2,FP$4) -> 0 | FQ11: =SUMIFS($AB11:$FF11,$AB$2:$FF$2,FQ$4) -> 0 | FR11: =SUMIFS($AB11:$FF11,$AB$2:$FF$2,FR$4) -> 0 | FS11: =SUMIFS($AB11:$FF11,$AB$2:$FF$2,FS$4) -> 0 | ... GY11: =SUMIFS($AB11:$FF11,$AB$2:$FF$2,GY$4) -> 0
B12: =P12=SUM(BE12:FJ12) -> TRUE | L12: =SUBTOTAL(9,L8:L11) -> 11253.26 | M12: =SUBTOTAL(9,M8:M11) -> 57702.752 | P12: =SUM(P8:P11) -> 1535939420000 | AB12: =SUM(AB8:AB11) -> 0 | AC12: =SUM(AC8:AC11) -> 0 | AD12: =SUM(AD8:AD11) -> 0 | AE12: =SUM(AE8:AE11) -> 0 | AF12: =SUM(AF8:AF11) -> 0 | AG12: =SUM(AG8:AG11) -> 0 | AH12: =SUM(AH8:AH11) -> 0 | AI12: =SUM(AI8:AI11) -> 0 | ... FJ12: =SUM(FJ8:FJ11) -> 0 | FL12: =SUM(FL8:FL11) -> 0 | FM12: =SUM(FM8:FM11) -> 0 | FN12: =SUM(FN8:FN11) -> 0 | FO12: =SUM(FO8:FO11) -> 0 | FP12: =SUM(FP8:FP11) -> 0 | FQ12: =SUM(FQ8:FQ11) -> 0 | FR12: =SUM(FR8:FR11) -> 0 | FS12: =SUM(FS8:FS11) -> 0 | ... GY12: =SUM(GY8:GY11) -> 0

Sheet 6. PBChiPhi
A1: BẢNG 6: PHÂN BỔ CHI PHÍ ĐẦU TƯ DỰ ÁN
A5: STT | B5: Nội dung | C5: Tỷ lệ phân bổ | D5: Tổng | E5: ='5. KHBH'!C8 -> Nhà ở xã hội 1 | F5: ='5. KHBH'!C9 -> Nhà ở xã hội 2 | G5: ='5. KHBH'!C10 -> Nhà ở xã hội 3 | H5: ='5. KHBH'!C11 -> Liền kề 1
A6: I | B6: Tiêu thức phân bổ
B7: Phân bổ các loại chi phí | D7: =SUM(E7:H7) -> 11253.26 | E7: ='5. KHBH'!L8 -> 2787.24 | F7: ='5. KHBH'!L9 -> 2267.04 | G7: ='5. KHBH'!L10 -> 1878.48 | H7: ='5. KHBH'!L11 -> 4320.5
B8: - Phân bổ theo diện tích ô đất | D8: =SUM(E8:H8) -> 1 | E8: =E7/$D$7 -> 0.24768289 | F8: =F7/$D$7 -> 0.20145629 | G8: =G7/$D$7 -> 0.16692763 | H8: =H7/$D$7 -> 0.38393319
A9: II | B9: Phân bổ chi phí | C9: Ghi chú | D9: Tổng
A10: 1 | B10: ='2. CPxaydung'!B6 -> Chi phí xây dựng, thiết bị | D10: =SUM(D11:D13) -> 8.6824028e+11 | E10: =SUM(E11:E13) -> 3.1283242e+11 | F10: =SUM(F11:F13) -> 2.5444655e+11 | G10: =SUM(G11:G13) -> 2.1083561e+11 | H10: =SUM(H11:H13) -> 9.0125701e+10 | I10: =D10-'3. TMDT'!E7 -> 0
B11: Chi phí xây dựng và thiết bị phần hạ tầng kỹ thuật | D11: ='2. CPxaydung'!G7 -> 2.8275455e+10 | E11: =$D$11*E8 -> 7.0033464e+09 | F11: =$D$11*F8 -> 5.6962681e+09 | G11: =$D$11*G8 -> 4.7199546e+09 | H11: =$D$11*H8 -> 1.0855885e+10
B12: Chi phí xây dựng và thiết bị phần nhà ở, thương mại dịch vụ, công trình công cộng và y tế, giáo dục | D12: ='2. CPxaydung'!G8 -> 7.8697364e+11 | E12: =$D$12*E20/SUM($E$20:$H$20) -> 2.9270406e+11 | F12: =$D$12*F20/SUM($E$20:$H$20) -> 2.3807488e+11 | G12: =$D$12*G20/SUM($E$20:$H$20) -> 1.9726996e+11 | H12: =$D$12*H20/SUM($E$20:$H$20) -> 5.8924739e+10
B13: Chi phí quản lý dự án, chi phí tư vấn và chi phí khác | D13: ='2. CPxaydung'!G9 -> 5.2991191e+10 | E13: =$D$13*E8 -> 1.3125012e+10 | F13: =$D$13*F8 -> 1.0675409e+10 | G13: =$D$13*G8 -> 8.8456938e+09 | H13: =$D$13*H8 -> 2.0345077e+10
A14: 2 | B14: ='2. CPxaydung'!B10 -> Chi phí quản lý dự án + tư vấn + khác | D14: ='2. CPxaydung'!G10 -> 0 | E14: =$D14*E$8 -> 0 | F14: =$D14*F$8 -> 0 | G14: =$D14*G$8 -> 0 | H14: =$D14*H$8 -> 0 | I14: ='3. TMDT'!E8-'6. PBChiPhi'!D14 -> 0
A15: 3 | B15: ='2. CPxaydung'!B11 -> Chi phí dự phòng | D15: ='2. CPxaydung'!G11 -> 1.3093411e+11 | E15: =$D15*E$8 -> 3.2430139e+10 | F15: =$D15*F$8 -> 2.6377499e+10 | G15: =$D15*G$8 -> 2.185652e+10 | H15: =$D15*H$8 -> 5.0269949e+10 | I15: =D15-'3. TMDT'!E9 -> 0
A16: 4 | B16: ='3. TMDT'!B10 -> Chi phí GPMB và tiền sử dụng đất | D16: ='3. TMDT'!E10 -> 43014372094 | E16: =$D16*E$8 -> 1.0653924e+10 | F16: =$D16*F$8 -> 8.6655158e+09 | G16: =$D16*G$8 -> 7.1802871e+09 | H16: =$D16*H$8 -> 1.6514645e+10 | I16: =D16-'3. TMDT'!E10 -> 0
A17: 5 | B17: ='3. TMDT'!B14 -> Lãi vay trong giai đoạn xây dựng | D17: ='3. TMDT'!E14 -> 4.501737e+10 | E17: =$D17*E$8 -> 1.1150032e+10 | F17: =$D17*F$8 -> 9.0690323e+09 | G17: =$D17*G$8 -> 7.5146428e+09 | H17: =$D17*H$8 -> 1.7283662e+10 | I17: =D17-'3. TMDT'!E14 -> 0
B19: Giá vốn bao gồm lãi vay | D19: =SUM(E19:H19) -> 1.0872061e+12 | E19: =E10+SUM(E14:E17) -> 3.6706651e+11 | F19: =F10+SUM(F14:F17) -> 2.985586e+11 | G19: =G10+SUM(G14:G17) -> 2.4738706e+11 | H19: =H10+SUM(H14:H17) -> 1.7419396e+11
B20: Diện tích thương phẩm | E20: ='5. KHBH'!M8 -> 21461.748 | F20: ='5. KHBH'!M9 -> 17456.208 | G20: ='5. KHBH'!M10 -> 14464.296 | H20: ='5. KHBH'!M11 -> 4320.5
B21: Giá vốn/m2 đất thương phẩm | E21: =E19/E20 -> 17103291 | F21: =F19/F20 -> 17103291 | G21: =G19/G20 -> 17103291 | H21: =H19/H20 -> 40318009
B22: Phân bổ chi phí bán hàng | D22: ='7. P&L TOÀN DỰ ÁN'!C19 -> 2.7926171e+10 | E22: =$D$22*'5. KHBH'!P8/'5. KHBH'!$P$12 -> 8.779806e+09 | F22: =$D$22*'5. KHBH'!P9/'5. KHBH'!$P$12 -> 7141176000 | G22: =$D$22*'5. KHBH'!P10/'5. KHBH'!$P$12 -> 5.917212e+09 | H22: =$D$22*'5. KHBH'!P11/'5. KHBH'!$P$12 -> 6.0879773e+09
B23: Chi phí bán hàng/m2 đất thương phẩm | E23: =E22/E20 -> 409090.91 | F23: =F22/F20 -> 409090.91 | G23: =G22/G20 -> 409090.91 | H23: =H22/H20 -> 1409090.9
B24: Phân bổ chi phí lãi vay | D24: ='7. P&L TOÀN DỰ ÁN'!C21 -> 3.4643888e+10 | E24: =$D$24*'5. KHBH'!P8/'5. KHBH'!$P$12 -> 1.0891812e+10 | F24: =$D$24*'5. KHBH'!P9/'5. KHBH'!$P$12 -> 8.8590054e+09 | G24: =$D$24*'5. KHBH'!P10/'5. KHBH'!$P$12 -> 7.3406135e+09 | H24: =$D$24*'5. KHBH'!P11/'5. KHBH'!$P$12 -> 7.5524568e+09
B25: Chi phí lãi vay/m2 đất thương phẩm | E25: =E24/E20 -> 507498.85 | F25: =F24/F20 -> 507498.85 | G25: =G24/G20 -> 507498.85 | H25: =H24/H20 -> 1748051.6
B26: Phân bổ chi phí quản lý | D26: ='7. P&L TOÀN DỰ ÁN'!C20 -> 2.7926171e+10 | E26: =$D$26*'5. KHBH'!P8/'5. KHBH'!$P$12 -> 8.779806e+09 | F26: =$D$26*'5. KHBH'!P9/'5. KHBH'!$P$12 -> 7141176000 | G26: =$D$26*'5. KHBH'!P10/'5. KHBH'!$P$12 -> 5.917212e+09 | H26: =$D$26*'5. KHBH'!P11/'5. KHBH'!$P$12 -> 6.0879773e+09
E27: =E26/E20 -> 409090.91 | F27: =F26/F20 -> 409090.91 | G27: =G26/G20 -> 409090.91 | H27: =H26/H20 -> 1409090.9
B28: Tổng giá vốn phân bổ (chưa bao gồm VAT) | E28: =E21+E23+E25+E27 -> 18428971 | F28: =F21+F23+F25+F27 -> 18428971 | G28: =G21+G23+G25+G27 -> 18428971 | H28: =H21+H23+H25+H27 -> 44884242
F29: =F28*1.1 -> 20271868
E30: =+E21+E23+E25+E27 -> 18428971 | F30: =F29*1.1 -> 22299055
E31: =+E30*1.1 -> 20271868
E32: =+E31*1.1 -> 22299055

Sheet 7. P&L TOÀN DỰ ÁN
A1: KẾT QUẢ KINH DOANH TOÀN DỰ ÁN
C2: ĐVT: VNĐ | E2: =+'5. KHBH'!AB2 -> 44742 | F2: =+'5. KHBH'!AC2 -> 44834 | G2: =+'5. KHBH'!AD2 -> 44834 | H2: =+'5. KHBH'!AE2 -> 44834 | I2: =+'5. KHBH'!AF2 -> 44926 | J2: =+'5. KHBH'!AG2 -> 44926 | K2: =+'5. KHBH'!AH2 -> 44926 | L2: =+'5. KHBH'!AI2 -> 45016 | ... EM2: =+'5. KHBH'!FJ2 -> 48944
A3: TT | B3: Nội dung | C3: Tổng | D3: Diện tích bán sản phẩm | E3: =+'5. KHBH'!AB4 -> 44713 | F3: =+'5. KHBH'!AC4 -> 44743 | G3: =+'5. KHBH'!AD4 -> 44774 | H3: =+'5. KHBH'!AE4 -> 44805 | I3: =+'5. KHBH'!AF4 -> 44835 | J3: =+'5. KHBH'!AG4 -> 44866 | K3: =+'5. KHBH'!AH4 -> 44896 | L3: =+'5. KHBH'!AI4 -> 44927 | ... GB3: =+'5. KHBH'!GY4 -> 48944
A4: I | B4: Doanh thu từ bán và chuyển nhượng bất động sản | C4: =SUM(C5:C8) -> 1.3963086e+12 | D4: =SUM(D5:D8) -> 57702.752 | E4: =SUM(#REF!) -> #REF! | F4: =SUM(#REF!) -> #REF! | G4: =SUM(#REF!) -> #REF! | H4: =SUM(#REF!) -> #REF! | I4: =SUM(#REF!) -> #REF! | J4: =SUM(#REF!) -> #REF! | K4: =SUM(#REF!) -> #REF! | L4: =SUM(#REF!) -> #REF! | ... EM4: =SUM(#REF!) -> #REF! | EN4: =SUM(EN5:EN8) -> 0 | EO4: =SUM(EO5:EO8) -> 0 | EP4: =SUM(EP5:EP8) -> 0 | EQ4: =SUM(EQ5:EQ8) -> 0 | ER4: =SUM(ER5:ER8) -> 0 | ES4: =SUM(ES5:ES8) -> 0 | ET4: =SUM(ET5:ET8) -> 0 | EU4: =SUM(EU5:EU8) -> 0 | ... GB4: =SUM(GB5:GB8) -> 0
A5: 1 | B5: ='5. KHBH'!C8 -> Nhà ở xã hội 1 | C5: =SUM(EN5:GB5) -> 4.389903e+11 | D5: =SUMIF('5. KHBH'!$I$8:$I$11,B5,'5. KHBH'!$M$8:$M$11) -> 21461.748 | E5: =SUMIFS('5. KHBH'!$P$8:$P$11,'5. KHBH'!$Q$8:$Q$11,'7. P&L TOÀN DỰ ÁN'!E$3,'5. KHBH'!$I$8:$I$11,'7. P&L TOÀN DỰ ÁN'!$B5)/1.1 -> 0 | F5: =SUMIFS('5. KHBH'!$P$8:$P$11,'5. KHBH'!$Q$8:$Q$11,'7. P&L TOÀN DỰ ÁN'!F$3,'5. KHBH'!$I$8:$I$11,'7. P&L TOÀN DỰ ÁN'!$B5)/1.1 -> 0 | G5: =SUMIFS('5. KHBH'!$P$8:$P$11,'5. KHBH'!$Q$8:$Q$11,'7. P&L TOÀN DỰ ÁN'!G$3,'5. KHBH'!$I$8:$I$11,'7. P&L TOÀN DỰ ÁN'!$B5)/1.1 -> 0 | H5: =SUMIFS('5. KHBH'!$P$8:$P$11,'5. KHBH'!$Q$8:$Q$11,'7. P&L TOÀN DỰ ÁN'!H$3,'5. KHBH'!$I$8:$I$11,'7. P&L TOÀN DỰ ÁN'!$B5)/1.1 -> 0 | I5: =SUMIFS('5. KHBH'!$P$8:$P$11,'5. KHBH'!$Q$8:$Q$11,'7. P&L TOÀN DỰ ÁN'!I$3,'5. KHBH'!$I$8:$I$11,'7. P&L TOÀN DỰ ÁN'!$B5)/1.1 -> 0 | J5: =SUMIFS('5. KHBH'!$P$8:$P$11,'5. KHBH'!$Q$8:$Q$11,'7. P&L TOÀN DỰ ÁN'!J$3,'5. KHBH'!$I$8:$I$11,'7. P&L TOÀN DỰ ÁN'!$B5)/1.1 -> 0 | K5: =SUMIFS('5. KHBH'!$P$8:$P$11,'5. KHBH'!$Q$8:$Q$11,'7. P&L TOÀN DỰ ÁN'!K$3,'5. KHBH'!$I$8:$I$11,'7. P&L TOÀN DỰ ÁN'!$B5)/1.1 -> 0 | L5: =SUMIFS('5. KHBH'!$P$8:$P$11,'5. KHBH'!$Q$8:$Q$11,'7. P&L TOÀN DỰ ÁN'!L$3,'5. KHBH'!$I$8:$I$11,'7. P&L TOÀN DỰ ÁN'!$B5)/1.1 -> 0 | ... EM5: =SUMIFS('5. KHBH'!$P$8:$P$11,'5. KHBH'!$Q$8:$Q$11,'7. P&L TOÀN DỰ ÁN'!EM$3,'5. KHBH'!$I$8:$I$11,'7. P&L TOÀN DỰ ÁN'!$B5)/1.1 -> 0 | EN5: =SUMIFS($E5:$EM5,$E$2:$EM$2,EN$3) -> 0 | EO5: =SUMIFS($E5:$EM5,$E$2:$EM$2,EO$3) -> 0 | EP5: =SUMIFS($E5:$EM5,$E$2:$EM$2,EP$3) -> 0 | EQ5: =SUMIFS($E5:$EM5,$E$2:$EM$2,EQ$3) -> 0 | ER5: =SUMIFS($E5:$EM5,$E$2:$EM$2,ER$3) -> 0 | ES5: =SUMIFS($E5:$EM5,$E$2:$EM$2,ES$3) -> 0 | ET5: =SUMIFS($E5:$EM5,$E$2:$EM$2,ET$3) -> 0 | EU5: =SUMIFS($E5:$EM5,$E$2:$EM$2,EU$3) -> 0 | ... GB5: =SUMIFS($E5:$EM5,$E$2:$EM$2,GB$3) -> 0
A6: =A5+1 -> 2 | B6: ='5. KHBH'!C9 -> Nhà ở xã hội 2 | C6: =SUM(EN6:GB6) -> 357058800000 | D6: =SUMIF('5. KHBH'!$I$8:$I$11,B6,'5. KHBH'!$M$8:$M$11) -> 17456.208 | E6: =SUMIFS('5. KHBH'!$P$8:$P$11,'5. KHBH'!$Q$8:$Q$11,'7. P&L TOÀN DỰ ÁN'!E$3,'5. KHBH'!$I$8:$I$11,'7. P&L TOÀN DỰ ÁN'!$B6)/1.1 -> 0 | F6: =SUMIFS('5. KHBH'!$P$8:$P$11,'5. KHBH'!$Q$8:$Q$11,'7. P&L TOÀN DỰ ÁN'!F$3,'5. KHBH'!$I$8:$I$11,'7. P&L TOÀN DỰ ÁN'!$B6)/1.1 -> 0 | G6: =SUMIFS('5. KHBH'!$P$8:$P$11,'5. KHBH'!$Q$8:$Q$11,'7. P&L TOÀN DỰ ÁN'!G$3,'5. KHBH'!$I$8:$I$11,'7. P&L TOÀN DỰ ÁN'!$B6)/1.1 -> 0 | H6: =SUMIFS('5. KHBH'!$P$8:$P$11,'5. KHBH'!$Q$8:$Q$11,'7. P&L TOÀN DỰ ÁN'!H$3,'5. KHBH'!$I$8:$I$11,'7. P&L TOÀN DỰ ÁN'!$B6)/1.1 -> 0 | I6: =SUMIFS('5. KHBH'!$P$8:$P$11,'5. KHBH'!$Q$8:$Q$11,'7. P&L TOÀN DỰ ÁN'!I$3,'5. KHBH'!$I$8:$I$11,'7. P&L TOÀN DỰ ÁN'!$B6)/1.1 -> 0 | J6: =SUMIFS('5. KHBH'!$P$8:$P$11,'5. KHBH'!$Q$8:$Q$11,'7. P&L TOÀN DỰ ÁN'!J$3,'5. KHBH'!$I$8:$I$11,'7. P&L TOÀN DỰ ÁN'!$B6)/1.1 -> 0 | K6: =SUMIFS('5. KHBH'!$P$8:$P$11,'5. KHBH'!$Q$8:$Q$11,'7. P&L TOÀN DỰ ÁN'!K$3,'5. KHBH'!$I$8:$I$11,'7. P&L TOÀN DỰ ÁN'!$B6)/1.1 -> 0 | L6: =SUMIFS('5. KHBH'!$P$8:$P$11,'5. KHBH'!$Q$8:$Q$11,'7. P&L TOÀN DỰ ÁN'!L$3,'5. KHBH'!$I$8:$I$11,'7. P&L TOÀN DỰ ÁN'!$B6)/1.1 -> 0 | ... EM6: =SUMIFS('5. KHBH'!$P$8:$P$11,'5. KHBH'!$Q$8:$Q$11,'7. P&L TOÀN DỰ ÁN'!EM$3,'5. KHBH'!$I$8:$I$11,'7. P&L TOÀN DỰ ÁN'!$B6)/1.1 -> 0 | EN6: =SUMIFS($E6:$EM6,$E$2:$EM$2,EN$3) -> 0 | EO6: =SUMIFS($E6:$EM6,$E$2:$EM$2,EO$3) -> 0 | EP6: =SUMIFS($E6:$EM6,$E$2:$EM$2,EP$3) -> 0 | EQ6: =SUMIFS($E6:$EM6,$E$2:$EM$2,EQ$3) -> 0 | ER6: =SUMIFS($E6:$EM6,$E$2:$EM$2,ER$3) -> 0 | ES6: =SUMIFS($E6:$EM6,$E$2:$EM$2,ES$3) -> 0 | ET6: =SUMIFS($E6:$EM6,$E$2:$EM$2,ET$3) -> 0 | EU6: =SUMIFS($E6:$EM6,$E$2:$EM$2,EU$3) -> 0 | ... GB6: =SUMIFS($E6:$EM6,$E$2:$EM$2,GB$3) -> 0
A7: 3 | B7: ='5. KHBH'!C10 -> Nhà ở xã hội 3 | C7: =SUM(EN7:GB7) -> 2.958606e+11 | D7: =SUMIF('5. KHBH'!$I$8:$I$11,B7,'5. KHBH'!$M$8:$M$11) -> 14464.296 | E7: =SUMIFS('5. KHBH'!$P$8:$P$11,'5. KHBH'!$Q$8:$Q$11,'7. P&L TOÀN DỰ ÁN'!E$3,'5. KHBH'!$I$8:$I$11,'7. P&L TOÀN DỰ ÁN'!$B7)/1.1 -> 0 | F7: =SUMIFS('5. KHBH'!$P$8:$P$11,'5. KHBH'!$Q$8:$Q$11,'7. P&L TOÀN DỰ ÁN'!F$3,'5. KHBH'!$I$8:$I$11,'7. P&L TOÀN DỰ ÁN'!$B7)/1.1 -> 0 | G7: =SUMIFS('5. KHBH'!$P$8:$P$11,'5. KHBH'!$Q$8:$Q$11,'7. P&L TOÀN DỰ ÁN'!G$3,'5. KHBH'!$I$8:$I$11,'7. P&L TOÀN DỰ ÁN'!$B7)/1.1 -> 0 | H7: =SUMIFS('5. KHBH'!$P$8:$P$11,'5. KHBH'!$Q$8:$Q$11,'7. P&L TOÀN DỰ ÁN'!H$3,'5. KHBH'!$I$8:$I$11,'7. P&L TOÀN DỰ ÁN'!$B7)/1.1 -> 0 | I7: =SUMIFS('5. KHBH'!$P$8:$P$11,'5. KHBH'!$Q$8:$Q$11,'7. P&L TOÀN DỰ ÁN'!I$3,'5. KHBH'!$I$8:$I$11,'7. P&L TOÀN DỰ ÁN'!$B7)/1.1 -> 0 | J7: =SUMIFS('5. KHBH'!$P$8:$P$11,'5. KHBH'!$Q$8:$Q$11,'7. P&L TOÀN DỰ ÁN'!J$3,'5. KHBH'!$I$8:$I$11,'7. P&L TOÀN DỰ ÁN'!$B7)/1.1 -> 0 | K7: =SUMIFS('5. KHBH'!$P$8:$P$11,'5. KHBH'!$Q$8:$Q$11,'7. P&L TOÀN DỰ ÁN'!K$3,'5. KHBH'!$I$8:$I$11,'7. P&L TOÀN DỰ ÁN'!$B7)/1.1 -> 0 | L7: =SUMIFS('5. KHBH'!$P$8:$P$11,'5. KHBH'!$Q$8:$Q$11,'7. P&L TOÀN DỰ ÁN'!L$3,'5. KHBH'!$I$8:$I$11,'7. P&L TOÀN DỰ ÁN'!$B7)/1.1 -> 0 | ... EM7: =SUMIFS('5. KHBH'!$P$8:$P$11,'5. KHBH'!$Q$8:$Q$11,'7. P&L TOÀN DỰ ÁN'!EM$3,'5. KHBH'!$I$8:$I$11,'7. P&L TOÀN DỰ ÁN'!$B7)/1.1 -> 0 | EN7: =SUMIFS($E7:$EM7,$E$2:$EM$2,EN$3) -> 0 | EO7: =SUMIFS($E7:$EM7,$E$2:$EM$2,EO$3) -> 0 | EP7: =SUMIFS($E7:$EM7,$E$2:$EM$2,EP$3) -> 0 | EQ7: =SUMIFS($E7:$EM7,$E$2:$EM$2,EQ$3) -> 0 | ER7: =SUMIFS($E7:$EM7,$E$2:$EM$2,ER$3) -> 0 | ES7: =SUMIFS($E7:$EM7,$E$2:$EM$2,ES$3) -> 0 | ET7: =SUMIFS($E7:$EM7,$E$2:$EM$2,ET$3) -> 0 | EU7: =SUMIFS($E7:$EM7,$E$2:$EM$2,EU$3) -> 0 | ... GB7: =SUMIFS($E7:$EM7,$E$2:$EM$2,GB$3) -> 0
A8: 4 | B8: ='5. KHBH'!C11 -> Liền kề 1 | C8: =SUM(EN8:GB8) -> 3.0439886e+11 | D8: =SUMIF('5. KHBH'!$I$8:$I$11,B8,'5. KHBH'!$M$8:$M$11) -> 4320.5 | E8: =SUMIFS('5. KHBH'!$P$8:$P$11,'5. KHBH'!$Q$8:$Q$11,'7. P&L TOÀN DỰ ÁN'!E$3,'5. KHBH'!$I$8:$I$11,'7. P&L TOÀN DỰ ÁN'!$B8)/1.1 -> 0 | F8: =SUMIFS('5. KHBH'!$P$8:$P$11,'5. KHBH'!$Q$8:$Q$11,'7. P&L TOÀN DỰ ÁN'!F$3,'5. KHBH'!$I$8:$I$11,'7. P&L TOÀN DỰ ÁN'!$B8)/1.1 -> 0 | G8: =SUMIFS('5. KHBH'!$P$8:$P$11,'5. KHBH'!$Q$8:$Q$11,'7. P&L TOÀN DỰ ÁN'!G$3,'5. KHBH'!$I$8:$I$11,'7. P&L TOÀN DỰ ÁN'!$B8)/1.1 -> 0 | H8: =SUMIFS('5. KHBH'!$P$8:$P$11,'5. KHBH'!$Q$8:$Q$11,'7. P&L TOÀN DỰ ÁN'!H$3,'5. KHBH'!$I$8:$I$11,'7. P&L TOÀN DỰ ÁN'!$B8)/1.1 -> 0 | I8: =SUMIFS('5. KHBH'!$P$8:$P$11,'5. KHBH'!$Q$8:$Q$11,'7. P&L TOÀN DỰ ÁN'!I$3,'5. KHBH'!$I$8:$I$11,'7. P&L TOÀN DỰ ÁN'!$B8)/1.1 -> 0 | J8: =SUMIFS('5. KHBH'!$P$8:$P$11,'5. KHBH'!$Q$8:$Q$11,'7. P&L TOÀN DỰ ÁN'!J$3,'5. KHBH'!$I$8:$I$11,'7. P&L TOÀN DỰ ÁN'!$B8)/1.1 -> 0 | K8: =SUMIFS('5. KHBH'!$P$8:$P$11,'5. KHBH'!$Q$8:$Q$11,'7. P&L TOÀN DỰ ÁN'!K$3,'5. KHBH'!$I$8:$I$11,'7. P&L TOÀN DỰ ÁN'!$B8)/1.1 -> 0 | L8: =SUMIFS('5. KHBH'!$P$8:$P$11,'5. KHBH'!$Q$8:$Q$11,'7. P&L TOÀN DỰ ÁN'!L$3,'5. KHBH'!$I$8:$I$11,'7. P&L TOÀN DỰ ÁN'!$B8)/1.1 -> 0 | ... EM8: =SUMIFS('5. KHBH'!$P$8:$P$11,'5. KHBH'!$Q$8:$Q$11,'7. P&L TOÀN DỰ ÁN'!EM$3,'5. KHBH'!$I$8:$I$11,'7. P&L TOÀN DỰ ÁN'!$B8)/1.1 -> 0 | EN8: =SUMIFS($E8:$EM8,$E$2:$EM$2,EN$3) -> 0 | EO8: =SUMIFS($E8:$EM8,$E$2:$EM$2,EO$3) -> 0 | EP8: =SUMIFS($E8:$EM8,$E$2:$EM$2,EP$3) -> 0 | EQ8: =SUMIFS($E8:$EM8,$E$2:$EM$2,EQ$3) -> 0 | ER8: =SUMIFS($E8:$EM8,$E$2:$EM$2,ER$3) -> 0 | ES8: =SUMIFS($E8:$EM8,$E$2:$EM$2,ES$3) -> 0 | ET8: =SUMIFS($E8:$EM8,$E$2:$EM$2,ET$3) -> 0 | EU8: =SUMIFS($E8:$EM8,$E$2:$EM$2,EU$3) -> 0 | ... GB8: =SUMIFS($E8:$EM8,$E$2:$EM$2,GB$3) -> 0
A9: II | B9: Giá vốn bán hàng | C9: =SUM(C10:C13) -> 1.0872061e+12 | D9: =SUM(D10:D13) -> 57702.752 | EN9: =SUM(EN10:EN13) -> 0 | EO9: =SUM(EO10:EO13) -> 0 | EP9: =SUM(EP10:EP13) -> 0 | EQ9: =SUM(EQ10:EQ13) -> 0 | ER9: =SUM(ER10:ER13) -> 0 | ES9: =SUM(ES10:ES13) -> 0 | ET9: =SUM(ET10:ET13) -> 0 | EU9: =SUM(EU10:EU13) -> 0 | ... GB9: =SUM(GB10:GB13) -> 0
A10: =A5 -> 1 | B10: =B5 -> Nhà ở xã hội 1 | C10: =SUMIFS('6. PBChiPhi'!$E$19:$H$19,'6. PBChiPhi'!$E$5:$H$5,'7. P&L TOÀN DỰ ÁN'!$B10) -> 3.6706651e+11 | D10: =SUMIF('5. KHBH'!$I$8:$I$11,B5,'5. KHBH'!$M$8:$M$11) -> 21461.748 | EN10: =+EN5*$C10/$C5 -> 0 | EO10: =+EO5*$C10/$C5 -> 0 | EP10: =+EP5*$C10/$C5 -> 0 | EQ10: =+EQ5*$C10/$C5 -> 0 | ER10: =+ER5*$C10/$C5 -> 0 | ES10: =+ES5*$C10/$C5 -> 0 | ET10: =+ET5*$C10/$C5 -> 0 | EU10: =+EU5*$C10/$C5 -> 0 | ... GB10: =+GB5*$C10/$C5 -> 0
A11: =A6 -> 2 | B11: =B6 -> Nhà ở xã hội 2 | C11: =SUMIFS('6. PBChiPhi'!$E$19:$H$19,'6. PBChiPhi'!$E$5:$H$5,'7. P&L TOÀN DỰ ÁN'!$B11) -> 2.985586e+11 | D11: =SUMIF('5. KHBH'!$I$8:$I$11,B6,'5. KHBH'!$M$8:$M$11) -> 17456.208 | EN11: =+EN6*$C11/$C6 -> 0 | EO11: =+EO6*$C11/$C6 -> 0 | EP11: =+EP6*$C11/$C6 -> 0 | EQ11: =+EQ6*$C11/$C6 -> 0 | ER11: =+ER6*$C11/$C6 -> 0 | ES11: =+ES6*$C11/$C6 -> 0 | ET11: =+ET6*$C11/$C6 -> 0 | EU11: =+EU6*$C11/$C6 -> 0 | ... GB11: =+GB6*$C11/$C6 -> 0
A12: =A7 -> 3 | B12: =B7 -> Nhà ở xã hội 3 | C12: =SUMIFS('6. PBChiPhi'!$E$19:$H$19,'6. PBChiPhi'!$E$5:$H$5,'7. P&L TOÀN DỰ ÁN'!$B12) -> 2.4738706e+11 | D12: =SUMIF('5. KHBH'!$I$8:$I$11,B7,'5. KHBH'!$M$8:$M$11) -> 14464.296 | EN12: =+EN7*$C12/$C7 -> 0 | EO12: =+EO7*$C12/$C7 -> 0 | EP12: =+EP7*$C12/$C7 -> 0 | EQ12: =+EQ7*$C12/$C7 -> 0 | ER12: =+ER7*$C12/$C7 -> 0 | ES12: =+ES7*$C12/$C7 -> 0 | ET12: =+ET7*$C12/$C7 -> 0 | EU12: =+EU7*$C12/$C7 -> 0 | ... GB12: =+GB7*$C12/$C7 -> 0
A13: =A8 -> 4 | B13: =B8 -> Liền kề 1 | C13: =SUMIFS('6. PBChiPhi'!$E$19:$H$19,'6. PBChiPhi'!$E$5:$H$5,'7. P&L TOÀN DỰ ÁN'!$B13) -> 1.7419396e+11 | D13: =SUMIF('5. KHBH'!$I$8:$I$11,B8,'5. KHBH'!$M$8:$M$11) -> 4320.5 | EN13: =+EN8*$C13/$C8 -> 0 | EO13: =+EO8*$C13/$C8 -> 0 | EP13: =+EP8*$C13/$C8 -> 0 | EQ13: =+EQ8*$C13/$C8 -> 0 | ER13: =+ER8*$C13/$C8 -> 0 | ES13: =+ES8*$C13/$C8 -> 0 | ET13: =+ET8*$C13/$C8 -> 0 | EU13: =+EU8*$C13/$C8 -> 0 | ... GB13: =+GB8*$C13/$C8 -> 0
A14: III | B14: Lợi nhuận gộp | C14: =SUM(C15:C18) -> 3.0910243e+11 | D14: =SUM(D15:D18) -> 57702.752 | EN14: =SUM(EN15:EN18) -> 0 | EO14: =SUM(EO15:EO18) -> 0 | EP14: =SUM(EP15:EP18) -> 0 | EQ14: =SUM(EQ15:EQ18) -> 0 | ER14: =SUM(ER15:ER18) -> 0 | ES14: =SUM(ES15:ES18) -> 0 | ET14: =SUM(ET15:ET18) -> 0 | EU14: =SUM(EU15:EU18) -> 0 | ... GB14: =SUM(GB15:GB18) -> 0
A15: =A10 -> 1 | B15: =B5 -> Nhà ở xã hội 1 | C15: =SUM(EN15:GB15) -> 7.1923785e+10 | D15: =SUMIF('5. KHBH'!$I$8:$I$11,B5,'5. KHBH'!$M$8:$M$11) -> 21461.748 | EN15: =+EN5-EN10 -> 0 | EO15: =+EO5-EO10 -> 0 | EP15: =+EP5-EP10 -> 0 | EQ15: =+EQ5-EQ10 -> 0 | ER15: =+ER5-ER10 -> 0 | ES15: =+ES5-ES10 -> 0 | ET15: =+ET5-ET10 -> 0 | EU15: =+EU5-EU10 -> 0 | ... GB15: =+GB5-GB10 -> 0
A16: =A11 -> 2 | B16: =B6 -> Nhà ở xã hội 2 | C16: =SUM(EN16:GB16) -> 5.85002e+10 | D16: =SUMIF('5. KHBH'!$I$8:$I$11,B6,'5. KHBH'!$M$8:$M$11) -> 17456.208 | EN16: =+EN6-EN11 -> 0 | EO16: =+EO6-EO11 -> 0 | EP16: =+EP6-EP11 -> 0 | EQ16: =+EQ6-EQ11 -> 0 | ER16: =+ER6-ER11 -> 0 | ES16: =+ES6-ES11 -> 0 | ET16: =+ET6-ET11 -> 0 | EU16: =+EU6-EU11 -> 0 | ... GB16: =+GB6-GB11 -> 0
A17: =A12 -> 3 | B17: =B7 -> Nhà ở xã hội 3 | C17: =SUM(EN17:GB17) -> 4.8473541e+10 | D17: =SUMIF('5. KHBH'!$I$8:$I$11,B7,'5. KHBH'!$M$8:$M$11) -> 14464.296 | EN17: =+EN7-EN12 -> 0 | EO17: =+EO7-EO12 -> 0 | EP17: =+EP7-EP12 -> 0 | EQ17: =+EQ7-EQ12 -> 0 | ER17: =+ER7-ER12 -> 0 | ES17: =+ES7-ES12 -> 0 | ET17: =+ET7-ET12 -> 0 | EU17: =+EU7-EU12 -> 0 | ... GB17: =+GB7-GB12 -> 0
A18: =A13 -> 4 | B18: =B8 -> Liền kề 1 | C18: =SUM(EN18:GB18) -> 1.3020491e+11 | D18: =SUMIF('5. KHBH'!$I$8:$I$11,B8,'5. KHBH'!$M$8:$M$11) -> 4320.5 | EN18: =+EN8-EN13 -> 0 | EO18: =+EO8-EO13 -> 0 | EP18: =+EP8-EP13 -> 0 | EQ18: =+EQ8-EQ13 -> 0 | ER18: =+ER8-ER13 -> 0 | ES18: =+ES8-ES13 -> 0 | ET18: =+ET8-ET13 -> 0 | EU18: =+EU8-EU13 -> 0 | ... GB18: =+GB8-GB13 -> 0
A19: IV | B19: ='8. Hiệu quả dự án và CĐT'!B10 -> Chi phí bán hàng | C19: =(C4)*'1. Tổng hợp'!$D$19 -> 2.7926171e+10 | EN19: =+EN4*$C$19/$C$4 -> 0 | EO19: =+EO4*$C$19/$C$4 -> 0 | EP19: =+EP4*$C$19/$C$4 -> 0 | EQ19: =+EQ4*$C$19/$C$4 -> 0 | ER19: =+ER4*$C$19/$C$4 -> 0 | ES19: =+ES4*$C$19/$C$4 -> 0 | ET19: =+ET4*$C$19/$C$4 -> 0 | EU19: =+EU4*$C$19/$C$4 -> 0 | ... GB19: =+GB4*$C$19/$C$4 -> 0
A20: V | B20: ='1. Tổng hợp'!B23 -> Chi phí quản lý doanh nghiệp | C20: =C4*'1. Tổng hợp'!$D$23 -> 2.7926171e+10 | EN20: =+EN4*$C$20/$C$4 -> 0 | EO20: =+EO4*$C$20/$C$4 -> 0 | EP20: =+EP4*$C$20/$C$4 -> 0 | EQ20: =+EQ4*$C$20/$C$4 -> 0 | ER20: =+ER4*$C$20/$C$4 -> 0 | ES20: =+ES4*$C$20/$C$4 -> 0 | ET20: =+ET4*$C$20/$C$4 -> 0 | EU20: =+EU4*$C$20/$C$4 -> 0 | ... GB20: =+GB4*$C$20/$C$4 -> 0
A21: VI | B21: Chí phí tài chính: - Trong đó lãi vay | C21: ='4. Vay'!C23 -> 3.4643888e+10 | EN21: =+EN4*$C$21/$C$4 -> 0 | EO21: =+EO4*$C$21/$C$4 -> 0 | EP21: =+EP4*$C$21/$C$4 -> 0 | EQ21: =+EQ4*$C$21/$C$4 -> 0 | ER21: =+ER4*$C$21/$C$4 -> 0 | ES21: =+ES4*$C$21/$C$4 -> 0 | ET21: =+ET4*$C$21/$C$4 -> 0 | EU21: =+EU4*$C$21/$C$4 -> 0 | ... GB21: =+GB4*$C$21/$C$4 -> 0
A22: VII | B22: Lợi nhuận thuần từ hoạt động kinh doanh | C22: =SUM(EN22:GB22) -> 2.186062e+11 | EN22: =+EN14-EN19-EN20-EN21 -> 0 | EO22: =+EO14-EO19-EO20-EO21 -> 0 | EP22: =+EP14-EP19-EP20-EP21 -> 0 | EQ22: =+EQ14-EQ19-EQ20-EQ21 -> 0 | ER22: =+ER14-ER19-ER20-ER21 -> 0 | ES22: =+ES14-ES19-ES20-ES21 -> 0 | ET22: =+ET14-ET19-ET20-ET21 -> 0 | EU22: =+EU14-EU19-EU20-EU21 -> 0 | ... GB22: =+GB14-GB19-GB20-GB21 -> 0
A23: VIII | B23: Chi phí thuế thu nhập doanh nghiệp | C23: =SUM(EN23:GB23) -> 4.372124e+10 | EN23: =+EN22*'1. Tổng hợp'!$D$25 -> 0 | EO23: =+EO22*'1. Tổng hợp'!$D$25 -> 0 | EP23: =+EP22*'1. Tổng hợp'!$D$25 -> 0 | EQ23: =+EQ22*'1. Tổng hợp'!$D$25 -> 0 | ER23: =+ER22*'1. Tổng hợp'!$D$25 -> 0 | ES23: =+ES22*'1. Tổng hợp'!$D$25 -> 0 | ET23: =+ET22*'1. Tổng hợp'!$D$25 -> 0 | EU23: =+EU22*'1. Tổng hợp'!$D$25 -> 0 | ... GB23: =+GB22*'1. Tổng hợp'!$D$25 -> 0
A24: IX | B24: Lợi nhuận sau thuế thu nhập doanh nghiệp | C24: =SUM(EN24:GB24) -> 1.7488496e+11 | EN24: =+EN22-EN23 -> 0 | EO24: =+EO22-EO23 -> 0 | EP24: =+EP22-EP23 -> 0 | EQ24: =+EQ22-EQ23 -> 0 | ER24: =+ER22-ER23 -> 0 | ES24: =+ES22-ES23 -> 0 | ET24: =+ET22-ET23 -> 0 | EU24: =+EU22-EU23 -> 0 | ... GB24: =+GB22-GB23 -> 0
B26: ROS | C26: =C24/C4 -> 0.12524808
B27: Hiệu quả dự án | ER27: 2024 | ES27: 2025 | ET27: 2026 | EU27: 2027 | EV27: 2028 | EW27: 2029
A28: NPV | C28: ='8. Hiệu quả dự án và CĐT'!C20 -> 7.6848969e+10 | ER28: =ER4 -> 0 | ES28: =SUM(ES4:EV4) -> 0 | ET28: =SUM(EW4:EZ4) -> 0 | EU28: =SUM(FA4:FD4) -> 0 | EV28: =SUM(FE4:FH4) -> 0
A29: IRR | C29: ='8. Hiệu quả dự án và CĐT'!C21 -> 0.11584594
A30: Thời gian hoàn vốn | C30: ='8. Hiệu quả dự án và CĐT'!C22 -> 3 | D30: ='8. Hiệu quả dự án và CĐT'!D22 -> 3.5220057
B31: Hiệu quả CĐT
A32: NPV | C32: ='8. Hiệu quả dự án và CĐT'!C48 -> 1.6125998e+10
A33: IRR | C33: ='8. Hiệu quả dự án và CĐT'!C49 -> 0.17607408
A34: Thời gian hoàn vốn | C34: ='8. Hiệu quả dự án và CĐT'!C50 -> 3 | D34: ='8. Hiệu quả dự án và CĐT'!D50 -> 0.92859742

Sheet 8. Hiệu quả dự án và CĐT
A1: BẢNG 8: HIỆU QUẢ ĐẦU TƯ DỰ ÁN
D4: =YEAR(D5) -> 2023 | E4: =YEAR(E5) -> 2024 | F4: =YEAR(F5) -> 2024 | G4: =YEAR(G5) -> 2024 | H4: =YEAR(H5) -> 2024 | I4: =YEAR(I5) -> 2025 | J4: =YEAR(J5) -> 2025 | K4: =YEAR(K5) -> 2025 | ... AR4: =YEAR(AR5) -> 2033
A5: STT | B5: Dòng tiền dự án | C5: TỔNG | D5: =+'4. Vay'!E6 -> 45291 | E5: =+'4. Vay'!F6 -> 45382 | F5: =+'4. Vay'!G6 -> 45473 | G5: =+'4. Vay'!H6 -> 45565 | H5: =+'4. Vay'!I6 -> 45657 | I5: =+'4. Vay'!J6 -> 45747 | J5: =+'4. Vay'!K6 -> 45838 | K5: =+'4. Vay'!L6 -> 45930 | ... AR5: =+'4. Vay'!AS6 -> 48944
A6: I | B6: Dòng tiền thu từ dự án (cả VAT) | C6: =SUM(D6:AR6) -> 1535939420000 | D6: =+'5. KHBH'!FK12 -> 0 | E6: =+'5. KHBH'!FL12 -> 0 | F6: =+'5. KHBH'!FM12 -> 0 | G6: =+'5. KHBH'!FN12 -> 0 | H6: =+'5. KHBH'!FO12 -> 0 | I6: =+'5. KHBH'!FP12 -> 0 | J6: =+'5. KHBH'!FQ12 -> 0 | K6: =+'5. KHBH'!FR12 -> 0 | ... AR6: =+'5. KHBH'!GY12 -> 0
A7: II | B7: Dòng tiền chi cho dự án (ko lãi vay) | C7: =SUM(D7:AR7) -> 1.2813932e+12 | D7: =SUM(D8:D13) -> 0 | E7: =SUM(E8:E13) -> 0 | F7: =SUM(F8:F13) -> 0 | G7: =SUM(G8:G13) -> 0 | H7: =SUM(H8:H13) -> 0 | I7: =SUM(I8:I13) -> 0 | J7: =SUM(J8:J13) -> 0 | K7: =SUM(K8:K13) -> 0 | ... AR7: =SUM(AR8:AR13) -> 0
A8: 1 | B8: =+'3. TMDT'!B6 -> Tổng chi phí đầu tư xây dựng dự án | C8: =SUM(D8:AR8) -> 1.0990918e+12 | D8: =+'3. TMDT'!K6 -> 0 | E8: =+'3. TMDT'!L6 -> 0 | F8: =+'3. TMDT'!M6 -> 0 | G8: =+'3. TMDT'!N6 -> 0 | H8: =+'3. TMDT'!O6 -> 0 | I8: =+'3. TMDT'!P6 -> 0 | J8: =+'3. TMDT'!Q6 -> 0 | K8: =+'3. TMDT'!R6 -> 0 | ... AR8: =+'3. TMDT'!AY6 -> 0
A9: 2 | B9: =+'3. TMDT'!B10 -> Chi phí GPMB và tiền sử dụng đất | C9: =SUM(D9:AR9) -> 43014372094 | D9: =+'3. TMDT'!K10 -> 0 | E9: =+'3. TMDT'!L10 -> 0 | F9: =+'3. TMDT'!M10 -> 0 | G9: =+'3. TMDT'!N10 -> 0 | H9: =+'3. TMDT'!O10 -> 0 | I9: =+'3. TMDT'!P10 -> 0 | J9: =+'3. TMDT'!Q10 -> 0 | K9: =+'3. TMDT'!R10 -> 0 | ... AR9: =+'3. TMDT'!AY10 -> 0
A10: 3 | B10: Chi phí bán hàng | C10: =SUM(D10:AR10) -> 30718788400 | D10: =+'5. KHBH'!FK12*'1. Tổng hợp'!$D$19 -> 0 | E10: =+'5. KHBH'!FL12*'1. Tổng hợp'!$D$19 -> 0 | F10: =+'5. KHBH'!FM12*'1. Tổng hợp'!$D$19 -> 0 | G10: =+'5. KHBH'!FN12*'1. Tổng hợp'!$D$19 -> 0 | H10: =+'5. KHBH'!FO12*'1. Tổng hợp'!$D$19 -> 0 | I10: =+'5. KHBH'!FP12*'1. Tổng hợp'!$D$19 -> 0 | J10: =+'5. KHBH'!FQ12*'1. Tổng hợp'!$D$19 -> 0 | K10: =+'5. KHBH'!FR12*'1. Tổng hợp'!$D$19 -> 0 | ... AR10: =+'5. KHBH'!GY12*'1. Tổng hợp'!$D$19 -> 0
A11: 4 | B11: ='1. Tổng hợp'!B23 -> Chi phí quản lý doanh nghiệp | C11: =SUM(D11:AR11) -> 30718788400 | D11: =+D6*'1. Tổng hợp'!$D$23 -> 0 | E11: =+E6*'1. Tổng hợp'!$D$23 -> 0 | F11: =+F6*'1. Tổng hợp'!$D$23 -> 0 | G11: =+G6*'1. Tổng hợp'!$D$23 -> 0 | H11: =+H6*'1. Tổng hợp'!$D$23 -> 0 | I11: =+I6*'1. Tổng hợp'!$D$23 -> 0 | J11: =+J6*'1. Tổng hợp'!$D$23 -> 0 | K11: =+K6*'1. Tổng hợp'!$D$23 -> 0 | ... AR11: =+AR6*'1. Tổng hợp'!$D$23 -> 0
A12: 5 | B12: Thuế thu nhập doanh nghiệp | C12: =SUM(D12:AR12) -> 4.372124e+10 | D12: =+'7. P&L TOÀN DỰ ÁN'!EN23 -> 0 | E12: =+'7. P&L TOÀN DỰ ÁN'!EO23 -> 0 | F12: =+'7. P&L TOÀN DỰ ÁN'!EP23 -> 0 | G12: =+'7. P&L TOÀN DỰ ÁN'!EQ23 -> 0 | H12: =+'7. P&L TOÀN DỰ ÁN'!ER23 -> 0 | I12: =+'7. P&L TOÀN DỰ ÁN'!ES23 -> 0 | J12: =+'7. P&L TOÀN DỰ ÁN'!ET23 -> 0 | K12: =+'7. P&L TOÀN DỰ ÁN'!EU23 -> 0 | ... AR12: =+'7. P&L TOÀN DỰ ÁN'!GB23 -> 0
A13: 6 | B13: Thuế VAT phải nộp nhà nước | C13: =SUM(D13:AR13) -> 3.4128183e+10 | D13: 0 | E13: 0 | F13: 0 | G13: 0 | H13: =SUM(D16:H16) -> 0 | I13: =I16 -> 0 | J13: 0 | K13: 0 | L13: 0 | M13: 0 | N13: 0 | O13: 0 | P13: 0 | Q13: 0 | R13: 0 | S13: 0 | T13: 0 | U13: 0 | V13: 0 | W13: 0 | X13: 0 | Y13: 0 | Z13: 0 | AA13: 0 | AB13: 0 | AC13: 0 | AD13: 0 | AE13: 0 | AF13: 0 | AG13: 0 | AH13: =SUM(D16:AH16) -> 3.4128183e+10 | AI13: =AI16 -> 0 | AJ13: =AJ16 -> 0 | AK13: =AK16 -> 0 | AL13: =AL16 -> 0 | AM13: =AM16 -> 0 | AN13: =AN16 -> 0 | AO13: =AO16 -> 0 | AP13: =AP16 -> 0 | ... AR13: =AR16 -> 0
B14: Thuế VAT đầu ra | C14: =SUM(D14:AR14) -> 1.3963086e+11 | D14: =+(D6/(1+'1. Tổng hợp'!$D$24))*'1. Tổng hợp'!$D$24 -> 0 | E14: =+(E6/(1+'1. Tổng hợp'!$D$24))*'1. Tổng hợp'!$D$24 -> 0 | F14: =+(F6/(1+'1. Tổng hợp'!$D$24))*'1. Tổng hợp'!$D$24 -> 0 | G14: =+(G6/(1+'1. Tổng hợp'!$D$24))*'1. Tổng hợp'!$D$24 -> 0 | H14: =+(H6/(1+'1. Tổng hợp'!$D$24))*'1. Tổng hợp'!$D$24 -> 0 | I14: =+(I6/(1+'1. Tổng hợp'!$D$24))*'1. Tổng hợp'!$D$24 -> 0 | J14: =+(J6/(1+'1. Tổng hợp'!$D$24))*'1. Tổng hợp'!$D$24 -> 0 | K14: =+(K6/(1+'1. Tổng hợp'!$D$24))*'1. Tổng hợp'!$D$24 -> 0 | ... AR14: =+(AR6/(1+'1. Tổng hợp'!$D$24))*'1. Tổng hợp'!$D$24 -> 0
B15: Thuế VAT đầu vào | C15: =SUM(D15:AR15) -> 1.0550267e+11 | D15: =+((D8+D10+D11)/(1+'1. Tổng hợp'!$D$24))*'1. Tổng hợp'!$D$24 -> 0 | E15: =+((E8+E10+E11)/(1+'1. Tổng hợp'!$D$24))*'1. Tổng hợp'!$D$24 -> 0 | F15: =+((F8+F10+F11)/(1+'1. Tổng hợp'!$D$24))*'1. Tổng hợp'!$D$24 -> 0 | G15: =+((G8+G10+G11)/(1+'1. Tổng hợp'!$D$24))*'1. Tổng hợp'!$D$24 -> 0 | H15: =+((H8+H10+H11)/(1+'1. Tổng hợp'!$D$24))*'1. Tổng hợp'!$D$24 -> 0 | I15: =+((I8+I10+I11)/(1+'1. Tổng hợp'!$D$24))*'1. Tổng hợp'!$D$24 -> 0 | J15: =+((J8+J10+J11)/(1+'1. Tổng hợp'!$D$24))*'1. Tổng hợp'!$D$24 -> 0 | K15: =+((K8+K10+K11)/(1+'1. Tổng hợp'!$D$24))*'1. Tổng hợp'!$D$24 -> 0 | ... AR15: =+((AR8+AR10+AR11)/(1+'1. Tổng hợp'!$D$24))*'1. Tổng hợp'!$D$24 -> 0
B16: VAT đầu ra - đầu vào | C16: =SUM(D16:AR16) -> 3.4128183e+10 | D16: =D14-D15 -> 0 | E16: =E14-E15 -> 0 | F16: =F14-F15 -> 0 | G16: =G14-G15 -> 0 | H16: =H14-H15 -> 0 | I16: =I14-I15 -> 0 | J16: =J14-J15 -> 0 | K16: =K14-K15 -> 0 | ... AR16: =AR14-AR15 -> 0
A17: III | B17: Dòng Tiền Thuần | C17: =SUM(D17:AR17) -> 2.5454622e+11 | D17: =D6-D7 -> 0 | E17: =E6-E7 -> 0 | F17: =F6-F7 -> 0 | G17: =G6-G7 -> 0 | H17: =H6-H7 -> 0 | I17: =I6-I7 -> 0 | J17: =J6-J7 -> 0 | K17: =K6-K7 -> 0 | ... AR17: =AR6-AR7 -> 0
A18: IV | B18: Luỹ kế dòng tiền thuần | C18: =AR18 -> 2.5454622e+11 | D18: =D17 -> 0 | E18: =D18+E17 -> 0 | F18: =E18+F17 -> 0 | G18: =F18+G17 -> 0 | H18: =G18+H17 -> 0 | I18: =H18+I17 -> 0 | J18: =I18+J17 -> 0 | K18: =J18+K17 -> 0 | L18: =K18+L17 -> 0 | ... AR18: =AQ18+AR17 -> 2.5454622e+11
A20: NPV | C20: =I21+NPV('1. Tổng hợp'!E33,J21:Q21) -> 7.6848969e+10 | F20: Year | G20: 2023 | H20: 2024 | I20: =H20+1 -> 2025 | J20: =I20+1 -> 2026 | K20: =J20+1 -> 2027 | L20: =K20+1 -> 2028 | M20: =L20+1 -> 2029 | N20: =M20+1 -> 2030 | O20: =N20+1 -> 2031 | P20: =O20+1 -> 2032 | Q20: =P20+1 -> 2033
A21: MIRR | C21: =IRR(I22:Q22) -> 0.11584594 | F21: Cash Flow | G21: =SUMIFS($D$17:$AR$17,$D$4:$AR$4,G20) -> 0 | H21: =SUMIFS($D$17:$AR$17,$D$4:$AR$4,H20) -> 0 | I21: =SUMIFS($D$17:$AR$17,$D$4:$AR$4,I20) -> 0 | J21: =SUMIFS($D$17:$AR$17,$D$4:$AR$4,J20) -> -5.9256029e+11 | K21: =SUMIFS($D$17:$AR$17,$D$4:$AR$4,K20) -> -2.2504428e+11 | L21: =SUMIFS($D$17:$AR$17,$D$4:$AR$4,L20) -> 456804984960 | M21: =SUMIFS($D$17:$AR$17,$D$4:$AR$4,M20) -> 4.5556059e+11 | N21: =SUMIFS($D$17:$AR$17,$D$4:$AR$4,N20) -> 1.0604446e+11 | ... Q21: =SUMIFS($D$17:$AR$17,$D$4:$AR$4,Q20) -> 0
A22: Thời gian hoàn vốn | C22: =COUNTIFS(I23:Q23,"<0") -> 3 | D22: {=12-ABS(INDEX($I$22:$Q$23,2,C22+1)/INDEX($I$22:$Q$23,1,C22+1))*12+1} -> 3.5220057 | F22: Quy đổi (triệu VNĐ) | G22: =G21/10^6 -> 0 | H22: =H21/10^6 -> 0 | I22: =I21/10^6 -> 0 | J22: =J21/10^6 -> -592560.29 | K22: =K21/10^6 -> -225044.28 | L22: =L21/10^6 -> 456804.98 | M22: =M21/10^6 -> 455560.59 | N22: =N21/10^6 -> 106044.46 | ... Q22: =Q21/10^6 -> 0
A23: XNPV | B23: XNPV | C23: =XNPV('1. Tổng hợp'!$E$33,L17:AR17,L5:AR5)+SUM(D17:K17) -> 9.6698192e+10 | F23: Lũy kế | G23: =SUM($G$22:G22) -> 0 | H23: =SUM($G$22:H22) -> 0 | I23: =SUM($G$22:I22) -> 0 | J23: =SUM($G$22:J22) -> -592560.29 | K23: =SUM($G$22:K22) -> -817604.57 | L23: =SUM($G$22:L22) -> -360799.59 | M23: =SUM($G$22:M22) -> 94761.006 | N23: =SUM($G$22:N22) -> 200805.47 | ... Q23: =SUM($G$22:Q22) -> 254546.22
A24: XIRR | B24: XIRR | C24: =XIRR(E17:AR17,E5:AR5) -> 2.9802322e-09
A26: CHECK | C26: =+C18-'4. Vay'!C22-'4. Vay'!C23 -> 1.7488496e+11
D27: =YEAR(D28) -> 2023 | E27: =YEAR(E28) -> 2024 | F27: =YEAR(F28) -> 2024 | G27: =YEAR(G28) -> 2024 | H27: =YEAR(H28) -> 2024 | I27: =YEAR(I28) -> 2025 | J27: =YEAR(J28) -> 2025 | K27: =YEAR(K28) -> 2025 | ... AR27: =YEAR(AR28) -> 2033
A28: STT | B28: Dòng tiền chủ đầu tư | C28: TỔNG | D28: =D5 -> 45291 | E28: =E5 -> 45382 | F28: =F5 -> 45473 | G28: =G5 -> 45565 | H28: =H5 -> 45657 | I28: =I5 -> 45747 | J28: =J5 -> 45838 | K28: =K5 -> 45930 | ... AR28: =AR5 -> 48944
A29: I | B29: Dòng vào | C29: =SUM(C30:C31) -> 2.3354138e+12 | D29: =D30+D31 -> 0 | E29: =E30+E31 -> 0 | F29: =F30+F31 -> 0 | G29: =G30+G31 -> 0 | H29: =H30+H31 -> 0 | I29: =I30+I31 -> 0 | J29: =J30+J31 -> 0 | K29: =K30+K31 -> 0 | ... AR29: =AR30+AR31 -> 0
A30: 1 | B30: Dòng tiền thu từ dự án (cả VAT) | C30: =SUM(D30:AR30) -> 1535939420000 | D30: =+'5. KHBH'!FK12 -> 0 | E30: =+'5. KHBH'!FL12 -> 0 | F30: =+'5. KHBH'!FM12 -> 0 | G30: =+'5. KHBH'!FN12 -> 0 | H30: =+'5. KHBH'!FO12 -> 0 | I30: =+'5. KHBH'!FP12 -> 0 | J30: =+'5. KHBH'!FQ12 -> 0 | K30: =+'5. KHBH'!FR12 -> 0 | ... AR30: =+'5. KHBH'!GY12 -> 0
A31: 2 | B31: Vốn vay | C31: =SUM(D31:AR31) -> 7.9947434e+11 | D31: =+'4. Vay'!E9 -> 0 | E31: =+'4. Vay'!F9 -> 0 | F31: =+'4. Vay'!G9 -> 0 | G31: =+'4. Vay'!H9 -> 0 | H31: =+'4. Vay'!I9 -> 0 | I31: =+'4. Vay'!J9 -> 0 | J31: =+'4. Vay'!K9 -> 0 | K31: =+'4. Vay'!L9 -> 0 | ... AR31: =+'4. Vay'!AS9 -> 0
A32: II | B32: Dòng tiền chi cho dự án (ko lãi vay) | C32: =SUM(D32:AR32) -> 2.1605288e+12 | D32: =SUM(D33:D41) -> 0 | E32: =SUM(E33:E41) -> 0 | F32: =SUM(F33:F41) -> 0 | G32: =SUM(G33:G41) -> 0 | H32: =SUM(H33:H41) -> 0 | I32: =SUM(I33:I41) -> 0 | J32: =SUM(J33:J41) -> 0 | K32: =SUM(K33:K41) -> 0 | ... AR32: =SUM(AR33:AR41) -> 0
A33: 1 | B33: Tổng chi phí đầu tư xây dựng dự án không bao gồm lãi vay | C33: =SUM(D33:AR33) -> 1.0990918e+12 | D33: =+'3. TMDT'!K6 -> 0 | E33: =+'3. TMDT'!L6 -> 0 | F33: =+'3. TMDT'!M6 -> 0 | G33: =+'3. TMDT'!N6 -> 0 | H33: =+'3. TMDT'!O6 -> 0 | I33: =+'3. TMDT'!P6 -> 0 | J33: =+'3. TMDT'!Q6 -> 0 | K33: =+'3. TMDT'!R6 -> 0 | ... AR33: =+'3. TMDT'!AY6 -> 0
A34: 2 | B34: Lãi vay trong giai đoạn xây dựng | C34: =SUM(D34:AR34) -> 4.501737e+10 | D34: =+'4. Vay'!E22 -> 0 | E34: =+'4. Vay'!F22 -> 0 | F34: =+'4. Vay'!G22 -> 0 | G34: =+'4. Vay'!H22 -> 0 | H34: =+'4. Vay'!I22 -> 0 | I34: =+'4. Vay'!J22 -> 0 | J34: =+'4. Vay'!K22 -> 0 | K34: =+'4. Vay'!L22 -> 0 | ... AR34: =+'4. Vay'!AS22 -> 0
A35: 3 | B35: Lãi vay trong kỳ | C35: =SUM(D35:AR35) -> 3.4643888e+10 | D35: =+'4. Vay'!E23 -> 0 | E35: =+'4. Vay'!F23 -> 0 | F35: =+'4. Vay'!G23 -> 0 | G35: =+'4. Vay'!H23 -> 0 | H35: =+'4. Vay'!I23 -> 0 | I35: =+'4. Vay'!J23 -> 0 | J35: =+'4. Vay'!K23 -> 0 | K35: =+'4. Vay'!L23 -> 0 | ... AR35: =+'4. Vay'!AS23 -> 0
A36: 4 | B36: Chi phí GPMB và tiền sử dụng đất | C36: =SUM(D36:AR36) -> 43014372094 | D36: =+'3. TMDT'!K10 -> 0 | E36: =+'3. TMDT'!L10 -> 0 | F36: =+'3. TMDT'!M10 -> 0 | G36: =+'3. TMDT'!N10 -> 0 | H36: =+'3. TMDT'!O10 -> 0 | I36: =+'3. TMDT'!P10 -> 0 | J36: =+'3. TMDT'!Q10 -> 0 | K36: =+'3. TMDT'!R10 -> 0 | ... AR36: =+'3. TMDT'!AY10 -> 0
A37: 5 | B37: =B10 -> Chi phí bán hàng | C37: =SUM(D37:AR37) -> 30718788400 | D37: =D10 -> 0 | E37: =E10 -> 0 | F37: =F10 -> 0 | G37: =G10 -> 0 | H37: =H10 -> 0 | I37: =I10 -> 0 | J37: =J10 -> 0 | K37: =K10 -> 0 | ... AR37: =AR10 -> 0
A38: 6 | B38: =B11 -> Chi phí quản lý doanh nghiệp | C38: =SUM(D38:AR38) -> 30718788400 | D38: =D11 -> 0 | E38: =E11 -> 0 | F38: =F11 -> 0 | G38: =G11 -> 0 | H38: =H11 -> 0 | I38: =I11 -> 0 | J38: =J11 -> 0 | K38: =K11 -> 0 | ... AR38: =AR11 -> 0
A39: 7 | B39: Trả gốc vay | C39: =SUM(D39:AR39) -> 7.9947434e+11 | D39: ='4. Vay'!E10 -> 0 | E39: ='4. Vay'!F10 -> 0 | F39: ='4. Vay'!G10 -> 0 | G39: ='4. Vay'!H10 -> 0 | H39: ='4. Vay'!I10 -> 0 | I39: ='4. Vay'!J10 -> 0 | J39: ='4. Vay'!K10 -> 0 | K39: ='4. Vay'!L10 -> 0 | ... AR39: ='4. Vay'!AS10 -> 0
A40: 8 | B40: Thuế thu nhập doanh nghiệp | C40: =SUM(D40:AR40) -> 4.372124e+10 | D40: =+'7. P&L TOÀN DỰ ÁN'!EN23 -> 0 | E40: =+'7. P&L TOÀN DỰ ÁN'!EO23 -> 0 | F40: =+'7. P&L TOÀN DỰ ÁN'!EP23 -> 0 | G40: =+'7. P&L TOÀN DỰ ÁN'!EQ23 -> 0 | H40: =+'7. P&L TOÀN DỰ ÁN'!ER23 -> 0 | I40: =+'7. P&L TOÀN DỰ ÁN'!ES23 -> 0 | J40: =+'7. P&L TOÀN DỰ ÁN'!ET23 -> 0 | K40: =+'7. P&L TOÀN DỰ ÁN'!EU23 -> 0 | ... AR40: =+'7. P&L TOÀN DỰ ÁN'!GB23 -> 0
A41: 9 | B41: Thuế VAT phải nộp nhà nước | C41: =SUM(D41:AR41) -> 3.4128183e+10 | D41: =D13 -> 0 | E41: =E13 -> 0 | F41: =F13 -> 0 | G41: =G13 -> 0 | H41: =H13 -> 0 | I41: =I13 -> 0 | J41: =J13 -> 0 | K41: =K13 -> 0 | ... AR41: =AR13 -> 0
B42: Thuế VAT đầu ra | C42: =SUM(D42:AR42) -> 1.3963086e+11 | D42: =D14 -> 0 | E42: =E14 -> 0 | F42: =F14 -> 0 | G42: =G14 -> 0 | H42: =H14 -> 0 | I42: =I14 -> 0 | J42: =J14 -> 0 | K42: =K14 -> 0 | ... AR42: =AR14 -> 0
B43: Thuế VAT đầu vào | C43: =SUM(D43:AR43) -> 1.0550267e+11 | D43: =D15 -> 0 | E43: =E15 -> 0 | F43: =F15 -> 0 | G43: =G15 -> 0 | H43: =H15 -> 0 | I43: =I15 -> 0 | J43: =J15 -> 0 | K43: =K15 -> 0 | ... AR43: =AR15 -> 0
B44: VAT đầu ra - đầu vào | C44: =SUM(D44:AR44) -> 3.4128183e+10 | D44: =D16 -> 0 | E44: =E16 -> 0 | F44: =F16 -> 0 | G44: =G16 -> 0 | H44: =H16 -> 0 | I44: =I16 -> 0 | J44: =J16 -> 0 | K44: =K16 -> 0 | ... AR44: =AR16 -> 0
A45: III | B45: Dòng Tiền Thuần | C45: =C29-C32 -> 1.7488496e+11 | D45: =D29-D32 -> 0 | E45: =E29-E32 -> 0 | F45: =F29-F32 -> 0 | G45: =G29-G32 -> 0 | H45: =H29-H32 -> 0 | I45: =I29-I32 -> 0 | J45: =J29-J32 -> 0 | ... AR45: =AR29-AR32 -> 0
A46: IV | B46: Luỹ kế dòng tiền thuần | C46: =AR46 -> 1.7488496e+11 | D46: =D45 -> 0 | E46: =D46+E45 -> 0 | F46: =E46+F45 -> 0 | G46: =F46+G45 -> 0 | H46: =G46+H45 -> 0 | I46: =H46+I45 -> 0 | J46: =I46+J45 -> 0 | K46: =J46+K45 -> 0 | L46: =K46+L45 -> 0 | ... AR46: =AQ46+AR45 -> 1.7488496e+11
A48: NPV | C48: =I49+NPV('1. Tổng hợp'!E30,J49:Q49) -> 1.6125998e+10 | F48: Year | G48: 2023 | H48: 2024 | I48: =H48+1 -> 2025 | J48: =I48+1 -> 2026 | K48: =J48+1 -> 2027 | L48: =K48+1 -> 2028 | M48: =L48+1 -> 2029 | N48: =M48+1 -> 2030 | O48: =N48+1 -> 2031 | P48: =O48+1 -> 2032 | Q48: =P48+1 -> 2033
A49: IRR | C49: =IRR(I50:Q50) -> 0.17607408 | F49: Cash Flow | G49: =SUMIFS($D$45:$AR$45,$D$27:$AR$27,G48) -> 0 | H49: =SUMIFS($D$45:$AR$45,$D$27:$AR$27,H48) -> 0 | I49: =SUMIFS($D$45:$AR$45,$D$27:$AR$27,I48) -> 0 | J49: =SUMIFS($D$45:$AR$45,$D$27:$AR$27,J48) -> -1.9198277e+11 | K49: =SUMIFS($D$45:$AR$45,$D$27:$AR$27,K48) -> -1.3765628e+11 | L49: =SUMIFS($D$45:$AR$45,$D$27:$AR$27,L48) -> 1.6433062e+11 | M49: =SUMIFS($D$45:$AR$45,$D$27:$AR$27,M48) -> 1.8040817e+11 | N49: =SUMIFS($D$45:$AR$45,$D$27:$AR$27,N48) -> 1.0604446e+11 | ... Q49: =SUMIFS($D$45:$AR$45,$D$27:$AR$27,Q48) -> 0
A50: Thời gian hoàn vốn | C50: =COUNTIFS(I51:Q51,"<0") -> 3 | D50: {=12-ABS(INDEX($I$50:$Q$51,2,C50+1)/INDEX($I$50:$Q$51,1,C50+1))*12+1} -> 0.92859742 | F50: Quy đổi (triệu VNĐ) | G50: =G49/10^6 -> 0 | H50: =H49/10^6 -> 0 | I50: =I49/10^6 -> 0 | J50: =J49/10^6 -> -191982.77 | K50: =K49/10^6 -> -137656.28 | L50: =L49/10^6 -> 164330.62 | M50: =M49/10^6 -> 180408.17 | N50: =N49/10^6 -> 106044.46 | ... Q50: =Q49/10^6 -> 0
F51: Lũy kế | G51: =SUM($G$50:G50) -> 0 | H51: =SUM($G$50:H50) -> 0 | I51: =SUM($G$50:I50) -> 0 | J51: =SUM($G$50:J50) -> -191982.77 | K51: =SUM($G$50:K50) -> -329639.05 | L51: =SUM($G$50:L50) -> -165308.42 | M51: =SUM($G$50:M50) -> 15099.748 | N51: =SUM($G$50:N50) -> 121144.21 | ... Q51: =SUM($G$50:Q50) -> 174884.96

Sheet 9. Cân đối dòng tiền (VCSH)
A1: BẢNG 9: DÒNG TIỀN CHỦ ĐẦU TƯ
A5: STT | B5: Dòng tiền chủ đầu tư | C5: TỔNG | D5: ='4. Vay'!E6 -> 45291 | E5: ='4. Vay'!F6 -> 45382 | F5: ='4. Vay'!G6 -> 45473 | G5: ='4. Vay'!H6 -> 45565 | H5: ='4. Vay'!I6 -> 45657 | I5: ='4. Vay'!J6 -> 45747 | J5: ='4. Vay'!K6 -> 45838 | K5: ='4. Vay'!L6 -> 45930 | ... AR5: ='4. Vay'!AS6 -> 48944
A6: I | B6: Dòng vào | C6: =SUM(C7:C9) -> 2.5844138e+12 | D6: =SUM(D7:D9) -> 0 | E6: =SUM(E7:E9) -> 0 | F6: =SUM(F7:F9) -> 0 | G6: =SUM(G7:G9) -> 0 | H6: =SUM(H7:H9) -> 0 | I6: =SUM(I7:I9) -> 0 | J6: =SUM(J7:J9) -> 0 | ... AR6: =SUM(AR7:AR9) -> 0
A7: 1 | B7: Dòng tiền thu từ dự án (cả VAT) | C7: =SUM(D7:AR7) -> 1535939420000 | D7: =+'5. KHBH'!FK12 -> 0 | E7: =+'5. KHBH'!FL12 -> 0 | F7: =+'5. KHBH'!FM12 -> 0 | G7: =+'5. KHBH'!FN12 -> 0 | H7: =+'5. KHBH'!FO12 -> 0 | I7: =+'5. KHBH'!FP12 -> 0 | J7: =+'5. KHBH'!FQ12 -> 0 | K7: =+'5. KHBH'!FR12 -> 0 | ... AR7: =+'5. KHBH'!GY12 -> 0
A8: 2 | B8: Vốn vay | C8: =SUM(D8:AR8) -> 7.9947434e+11 | D8: ='4. Vay'!E9 -> 0 | E8: ='4. Vay'!F9 -> 0 | F8: ='4. Vay'!G9 -> 0 | G8: ='4. Vay'!H9 -> 0 | H8: ='4. Vay'!I9 -> 0 | I8: ='4. Vay'!J9 -> 0 | J8: ='4. Vay'!K9 -> 0 | K8: ='4. Vay'!L9 -> 0 | ... AR8: ='4. Vay'!AS9 -> 0
A9: 3 | B9: Dòng vốn CSH (thực chi) | C9: =SUM(D9:AR9) -> 249000000000 | D9: 0 | F9: 0 | M9: =56*10^9 -> 56000000000 | N9: =45*10^9 -> 45000000000 | O9: =47*10^9 -> 47000000000 | P9: =50*10^9 -> 50000000000 | R9: =18*10^9 -> 18000000000 | S9: =33*10^9 -> 33000000000
A10: II | B10: Dòng tiền chi cho dự án (ko lãi vay) | C10: =SUM(D10:AR10) -> 2.2662953e+12 | D10: =SUM(D11:D19) -> 0 | E10: =SUM(E11:E19) -> 0 | F10: =SUM(F11:F19) -> 0 | G10: =SUM(G11:G19) -> 0 | H10: =SUM(H11:H19) -> 0 | I10: =SUM(I11:I19) -> 0 | J10: =SUM(J11:J19) -> 0 | K10: =SUM(K11:K19) -> 0 | ... AR10: =SUM(AR11:AR19) -> 3.7891753e+09
A11: 1 | B11: Tổng chi phí đầu tư xây dựng dự án không bao gồm lãi vay | C11: =SUM(D11:AR11) -> 1.0990918e+12 | D11: =+'3. TMDT'!K6 -> 0 | E11: =+'3. TMDT'!L6 -> 0 | F11: =+'3. TMDT'!M6 -> 0 | G11: =+'3. TMDT'!N6 -> 0 | H11: =+'3. TMDT'!O6 -> 0 | I11: =+'3. TMDT'!P6 -> 0 | J11: =+'3. TMDT'!Q6 -> 0 | K11: =+'3. TMDT'!R6 -> 0 | ... AR11: =+'3. TMDT'!AY6 -> 0
A12: 2 | B12: ='[1]4. Vay'!B22 -> Lãi vay trong giai đoạn xây dựng | C12: =SUM(D12:AR12) -> 8.7991819e+10 | D12: =+'4. Vay'!E22 -> 0 | E12: =+'4. Vay'!F22 -> 0 | F12: =+'4. Vay'!G22 -> 0 | G12: =+'4. Vay'!H22 -> 0 | H12: =+'4. Vay'!I22 -> 0 | I12: =+'4. Vay'!J22 -> 0 | J12: =+'4. Vay'!K22 -> 0 | K12: =+'4. Vay'!L22 -> 0 | ... X12: =+'4. Vay'!Y22 -> 0 | Y12: =+'4. Vay'!W22 -> 0 | Z12: =+'4. Vay'!X22 -> 0 | AA12: =+'4. Vay'!Y22 -> 0 | AB12: =+'4. Vay'!V22 -> 0 | AC12: =+'4. Vay'!W22 -> 0 | AD12: =+'4. Vay'!X22 -> 0 | AE12: =+'4. Vay'!P22 -> 4.3962165e+09 | AF12: =+'4. Vay'!N22 -> 1.0260298e+09 | AG12: =+'4. Vay'!O22 -> 2.8334453e+09 | AH12: =+'4. Vay'!P22 -> 4.3962165e+09 | AI12: =+'4. Vay'!T22 -> 7.9407475e+09 | AJ12: =+'4. Vay'!R22 -> 6.9804481e+09 | AK12: =+'4. Vay'!S22 -> 7.4605978e+09 | AL12: =+'4. Vay'!T22 -> 7.9407475e+09 | AM12: =+'4. Vay'!X22 -> 0 | AN12: =+'4. Vay'!V22 -> 0 | AO12: =+'4. Vay'!W22 -> 0 | AP12: =+'4. Vay'!X22 -> 0 | AQ12: =+'4. Vay'!AB22 -> 0 | AR12: =+'4. Vay'!Z22 -> 0
A13: 3 | B13: ='[1]4. Vay'!B23 -> Lãi vay trong kỳ | C13: =SUM(D13:AR13) -> 9.7435935e+10 | D13: =+'4. Vay'!E23 -> 0 | E13: =+'4. Vay'!F23 -> 0 | F13: =+'4. Vay'!G23 -> 0 | G13: =+'4. Vay'!H23 -> 0 | H13: =+'4. Vay'!I23 -> 0 | I13: =+'4. Vay'!J23 -> 0 | J13: =+'4. Vay'!K23 -> 0 | K13: =+'4. Vay'!L23 -> 0 | ... X13: =+'4. Vay'!Y23 -> 4.8717968e+09 | Y13: =+'4. Vay'!W23 -> 7.0370398e+09 | Z13: =+'4. Vay'!X23 -> 5.9544183e+09 | AA13: =+'4. Vay'!Y23 -> 4.8717968e+09 | AB13: =+'4. Vay'!V23 -> 8.1196613e+09 | AC13: =+'4. Vay'!W23 -> 7.0370398e+09 | AD13: =+'4. Vay'!X23 -> 5.9544183e+09 | AE13: =+'4. Vay'!P23 -> 0 | AF13: =+'4. Vay'!N23 -> 0 | AG13: =+'4. Vay'!O23 -> 0 | AH13: =+'4. Vay'!P23 -> 0 | AI13: =+'4. Vay'!T23 -> 0 | AJ13: =+'4. Vay'!R23 -> 0 | AK13: =+'4. Vay'!S23 -> 0 | AL13: =+'4. Vay'!T23 -> 0 | AM13: =+'4. Vay'!X23 -> 5.9544183e+09 | AN13: =+'4. Vay'!V23 -> 8.1196613e+09 | AO13: =+'4. Vay'!W23 -> 7.0370398e+09 | AP13: =+'4. Vay'!X23 -> 5.9544183e+09 | AQ13: =+'4. Vay'!AB23 -> 1.6239323e+09 | AR13: =+'4. Vay'!Z23 -> 3.7891753e+09
A14: 4 | B14: =+'[1]3. TMDT'!B12 -> Chi phí GPMB và tiền sử dụng đất | C14: =SUM(D14:AR14) -> 43014372094 | D14: =+'3. TMDT'!K10 -> 0 | E14: =+'3. TMDT'!L10 -> 0 | F14: =+'3. TMDT'!M10 -> 0 | G14: =+'3. TMDT'!N10 -> 0 | H14: =+'3. TMDT'!O10 -> 0 | I14: =+'3. TMDT'!P10 -> 0 | J14: =+'3. TMDT'!Q10 -> 0 | K14: =+'3. TMDT'!R10 -> 0 | ... X14: =+'3. TMDT'!AE10 -> 0 | Y14: =+'3. TMDT'!AG10 -> 0 | Z14: =+'3. TMDT'!AH10 -> 0 | AA14: =+'3. TMDT'!AI10 -> 0 | AB14: =+'3. TMDT'!AF10 -> 0 | AC14: =+'3. TMDT'!AG10 -> 0 | AD14: =+'3. TMDT'!AH10 -> 0 | AE14: =+'3. TMDT'!W10 -> 0 | AF14: =+'3. TMDT'!AJ10 -> 0 | AG14: =+'3. TMDT'!AK10 -> 0 | AH14: =+'3. TMDT'!AL10 -> 0 | AI14: =+'3. TMDT'!AA10 -> 0 | AJ14: =+'3. TMDT'!AN10 -> 0 | AK14: =+'3. TMDT'!AO10 -> 0 | AL14: =+'3. TMDT'!AP10 -> 0 | AM14: =+'3. TMDT'!AE10 -> 0 | AN14: =+'3. TMDT'!AR10 -> 0 | AO14: =+'3. TMDT'!AS10 -> 0 | AP14: =+'3. TMDT'!AT10 -> 0 | AQ14: =+'3. TMDT'!AI10 -> 0 | AR14: =+'3. TMDT'!AV10 -> 0
A15: 5 | B15: =+'[1]8. Hiệu quả dự án và CĐT'!B10 -> Chi phí bán hàng | C15: =SUM(D15:AR15) -> 30718788400 | D15: ='8. Hiệu quả dự án và CĐT'!D10 -> 0 | E15: ='8. Hiệu quả dự án và CĐT'!E10 -> 0 | F15: ='8. Hiệu quả dự án và CĐT'!F10 -> 0 | G15: ='8. Hiệu quả dự án và CĐT'!G10 -> 0 | H15: ='8. Hiệu quả dự án và CĐT'!H10 -> 0 | I15: ='8. Hiệu quả dự án và CĐT'!I10 -> 0 | J15: ='8. Hiệu quả dự án và CĐT'!J10 -> 0 | K15: ='8. Hiệu quả dự án và CĐT'!K10 -> 0 | ... AR15: ='8. Hiệu quả dự án và CĐT'!AR10 -> 0
A16: 6 | B16: ='[1]8. Hiệu quả dự án và CĐT'!B11 -> Chi phí quản lý doanh nghiệp | C16: =SUM(D16:AR16) -> 30718788400 | D16: ='8. Hiệu quả dự án và CĐT'!D11 -> 0 | E16: ='8. Hiệu quả dự án và CĐT'!E11 -> 0 | F16: ='8. Hiệu quả dự án và CĐT'!F11 -> 0 | G16: ='8. Hiệu quả dự án và CĐT'!G11 -> 0 | H16: ='8. Hiệu quả dự án và CĐT'!H11 -> 0 | I16: ='8. Hiệu quả dự án và CĐT'!I11 -> 0 | J16: ='8. Hiệu quả dự án và CĐT'!J11 -> 0 | K16: ='8. Hiệu quả dự án và CĐT'!K11 -> 0 | ... AR16: ='8. Hiệu quả dự án và CĐT'!AR11 -> 0
A17: 7 | B17: Trả gốc vay | C17: =SUM(D17:AR17) -> 7.9947434e+11 | D17: ='4. Vay'!E10 -> 0 | E17: ='4. Vay'!F10 -> 0 | F17: ='4. Vay'!G10 -> 0 | G17: ='4. Vay'!H10 -> 0 | H17: ='4. Vay'!I10 -> 0 | I17: ='4. Vay'!J10 -> 0 | J17: ='4. Vay'!K10 -> 0 | K17: ='4. Vay'!L10 -> 0 | ... AR17: ='4. Vay'!AS10 -> 0
A18: 8 | B18: ='[1]8. Hiệu quả dự án và CĐT'!B12 -> Thuế thu nhập doanh nghiệp | C18: =SUM(D18:AR18) -> 4.372124e+10 | D18: ='7. P&L TOÀN DỰ ÁN'!EN23 -> 0 | E18: ='7. P&L TOÀN DỰ ÁN'!EO23 -> 0 | F18: ='7. P&L TOÀN DỰ ÁN'!EP23 -> 0 | G18: ='7. P&L TOÀN DỰ ÁN'!EQ23 -> 0 | H18: ='7. P&L TOÀN DỰ ÁN'!ER23 -> 0 | I18: ='7. P&L TOÀN DỰ ÁN'!ES23 -> 0 | J18: ='7. P&L TOÀN DỰ ÁN'!ET23 -> 0 | K18: ='7. P&L TOÀN DỰ ÁN'!EU23 -> 0 | ... AR18: ='7. P&L TOÀN DỰ ÁN'!GB23 -> 0
A19: 9 | B19: ='[1]8. Hiệu quả dự án và CĐT'!B13 -> Thuế VAT phải nộp nhà nước | C19: =SUM(D19:AR19) -> 3.4128183e+10 | D19: ='8. Hiệu quả dự án và CĐT'!D13 -> 0 | E19: ='8. Hiệu quả dự án và CĐT'!E13 -> 0 | F19: ='8. Hiệu quả dự án và CĐT'!F13 -> 0 | G19: ='8. Hiệu quả dự án và CĐT'!G13 -> 0 | H19: ='8. Hiệu quả dự án và CĐT'!H13 -> 0 | I19: ='8. Hiệu quả dự án và CĐT'!I13 -> 0 | J19: ='8. Hiệu quả dự án và CĐT'!J13 -> 0 | K19: ='8. Hiệu quả dự án và CĐT'!K13 -> 0 | ... AR19: ='8. Hiệu quả dự án và CĐT'!AR13 -> 0
B20: Thuế VAT đầu ra | C20: =SUM(D20:AR20) -> 1.3963086e+11 | D20: ='8. Hiệu quả dự án và CĐT'!D14 -> 0 | E20: ='8. Hiệu quả dự án và CĐT'!E14 -> 0 | F20: ='8. Hiệu quả dự án và CĐT'!F14 -> 0 | G20: ='8. Hiệu quả dự án và CĐT'!G14 -> 0 | H20: ='8. Hiệu quả dự án và CĐT'!H14 -> 0 | I20: ='8. Hiệu quả dự án và CĐT'!I14 -> 0 | J20: ='8. Hiệu quả dự án và CĐT'!J14 -> 0 | K20: ='8. Hiệu quả dự án và CĐT'!K14 -> 0 | ... AR20: ='8. Hiệu quả dự án và CĐT'!AR14 -> 0
B21: Thuế VAT đầu vào | C21: =SUM(D21:AR21) -> 1.0550267e+11 | D21: ='8. Hiệu quả dự án và CĐT'!D15 -> 0 | E21: ='8. Hiệu quả dự án và CĐT'!E15 -> 0 | F21: ='8. Hiệu quả dự án và CĐT'!F15 -> 0 | G21: ='8. Hiệu quả dự án và CĐT'!G15 -> 0 | H21: ='8. Hiệu quả dự án và CĐT'!H15 -> 0 | I21: ='8. Hiệu quả dự án và CĐT'!I15 -> 0 | J21: ='8. Hiệu quả dự án và CĐT'!J15 -> 0 | K21: ='8. Hiệu quả dự án và CĐT'!K15 -> 0 | ... AR21: ='8. Hiệu quả dự án và CĐT'!AR15 -> 0
B22: VAT đầu ra - đầu vào | C22: =SUM(D22:AR22) -> 3.4128183e+10 | D22: =D20-D21 -> 0 | E22: =E20-E21 -> 0 | F22: =F20-F21 -> 0 | G22: =G20-G21 -> 0 | H22: =H20-H21 -> 0 | I22: =I20-I21 -> 0 | J22: =J20-J21 -> 0 | K22: =K20-K21 -> 0 | ... AR22: =AR20-AR21 -> 0
A23: III | B23: Dòng Tiền Thuần | C23: =C6-C10 -> 3.1811847e+11 | D23: =D6-D10 -> 0 | E23: =E6-E10 -> 0 | F23: =F6-F10 -> 0 | G23: =G6-G10 -> 0 | H23: =H6-H10 -> 0 | I23: =I6-I10 -> 0 | J23: =J6-J10 -> 0 | ... AR23: =AR6-AR10 -> -3.7891753e+09
A24: IV | B24: Luỹ kế dòng tiền thuần | C24: =AR24 -> 3.1811847e+11 | D24: =D23 -> 0 | E24: =D24+E23 -> 0 | F24: =E24+F23 -> 0 | G24: =F24+G23 -> 0 | H24: =G24+H23 -> 0 | I24: =H24+I23 -> 0 | J24: =I24+J23 -> 0 | K24: =J24+K23 -> 0 | L24: =K24+L23 -> 0 | ... AR24: =AQ24+AR23 -> 3.1811847e+11
C25: =+C23-C9 -> 6.9118465e+10
C26: Vốn huy động khác | D26: =IF(D7>0,MAX(D10-D9-D8,0),0) -> 0 | E26: =IF(E7>0,MAX(E10-E9-E8,0),0) -> 0 | F26: =IF(F7>0,MAX(F10-F9-F8,0),0) -> 0 | G26: =IF(G7>0,MAX(G10-G9-G8,0),0) -> 0 | H26: =IF(H7>0,MAX(H10-H9-H8,0),0) -> 0 | I26: =IF(I7>0,MAX(I10-I9-I8,0),0) -> 0 | J26: =IF(J7>0,MAX(J10-J9-J8,0),0) -> 0 | K26: =IF(K7>0,MAX(K10-K9-K8,0),0) -> 0 | ... AR26: =IF(AR7>0,MAX(AR10-AR9-AR8,0),0) -> 0
D28: 2023 | E28: 2024 | F28: 2025 | G28: 2026 | H28: 2027 | I28: 2028 | J28: 2029
D29: =D23 -> 0 | E29: =SUM(E23:H23) -> 0 | F29: =SUM(I23:L23) -> 0 | G29: =SUM(M23:P23) -> 6.0172349e+09 | H29: =SUM(Q23:T23) -> -8.6656282e+10 | I29: =SUM(U23:X23) -> 1.6433062e+11 | J29: =SUM(AR23:AR23) -> -3.7891753e+09
D30: =D29/10^6 -> 0 | E30: =E29/10^6 -> 0 | F30: =F29/10^6 -> 0 | G30: =G29/10^6 -> 6017.2349 | H30: =H29/10^6 -> -86656.282 | I30: =I29/10^6 -> 164330.62 | J30: =J29/10^6 -> -3789.1753

Sheet 10. PA dự phòng
A1: Dòng tiền thực tế:
B2: 45688 | C2: =EOMONTH(B2,1) -> 45716 | D2: =EOMONTH(C2,1) -> 45747
A3: FCPY giải ngân | B3: ='4. Vay'!N9 -> 1.262806e+11
A4: VCSH cần nộp để giải ngân | B4: =#REF! -> #REF!
A5: VCSH hiện có | B5: 30000000000
A6: Vốn chiếm dụng KH (từ bán hàng) | B6: ='5. KHBH'!#REF! -> #REF! | C6: ='5. KHBH'!#REF! -> #REF! | D6: ='5. KHBH'!#REF! -> #REF!
A8: PA1:
A9: Tỷ lệ thanh toán cho nhà thầu phụ | B9: 0.9 | C9: 0.05 | D9: 0.05
A10: FCPY thanh toán cho FCI | B10: =#REF! -> #REF! | C10: 0 | D10: 0
A11: FCI thanh toán cho thầu phụ | B11: =$B$10*B9 -> #REF! | C11: =$B$10*C9 -> #REF! | D11: =$B$10*D9 -> #REF!
A12: Dư dòng tiền tại FCI | B12: =B3+B5+B6-B11 -> #REF! | C12: =C3+C5+C6-C11 -> #REF! | D12: =D3+D5+D6-D11 -> #REF!
A13: FCI cần chuyển về cho FCP và FCP thanh toán cho FCPY để đưa vào VCSH | B13: =B4-B5 -> #REF! | C13: =C4-C5 -> 0 | D13: =D4-D5 -> 0
A14: Dư dòng tiền cuối của FCI | B14: =B12-B13 -> #REF! | C14: =C12-C13 -> #REF! | D14: =D12-D13 -> #REF!
A16: PA2:
A17: Tỷ lệ giải ngân vay cá nhân (% VCSH/số tiền giải ngân) | B17: 0.3 | C17: 0.3 | D17: 0.3
A18: Số tiền cần giải ngân cá nhân để bù vào VCSH | B18: =IF(B14<0,-B14,0) -> #REF! | C18: =IF(C14<0,-C14,0) -> #REF! | D18: =IF(D14<0,-D14,0) -> #REF!
A19: Vốn tự có cần đưa vào để vay cá nhân | B19: =B18*B17 -> #REF! | C19: =C18*C17 -> #REF! | D19: =D18*D17 -> #REF!
A22: PA3:
A23: Giá nội bộ/giá bán ra bên ngoài | B23: 0.8 | C23: 0.8 | D23: 0.8
A24: Giá bán trung bình ra bên ngoài | B24: ='5. KHBH'!#REF! -> #REF! | C24: ='5. KHBH'!#REF! -> #REF! | D24: ='5. KHBH'!#REF! -> #REF!
A25: Giá bán trung bình nội bộ | B25: =B24*B23 -> #REF! | C25: =C24*C23 -> #REF! | D25: =D24*D23 -> #REF!
A26: Chênh giá | B26: =B24-B25 -> #REF! | C26: =C24-C25 -> #REF! | D26: =D24-D25 -> #REF!
A27: Số tiền cần giải ngân cá nhân để bù vào VCSH | B27: =IF(B14<0,-B14,0) -> #REF! | C27: =IF(C14<0,-C14,0) -> #REF! | D27: =IF(D14<0,-D14,0) -> #REF!
A28: Số căn cần bán | B28: =B27/B26 -> #REF! | C28: =C27/C26 -> #REF! | D28: =D27/D26 -> #REF!

Sheet 40 CĂN ĐỦ ĐK BH 
N1: Doanh thu đất sau CSBH | O1: Diện tích đất | P1: Đơn giá đất bình quân | S1: đặc biệt | T1: 1
M2: Mặt trước | N2: =SUMIFS($I$9:$I$48,$B$9:$B$48,"II",$G$9:$G$48,"42m") -> 8.2341032e+10 | O2: =SUMIFS($E$9:$E$48,B9:$B$48,"ii",$G$9:$G$48,"42m") -> 1080 | P2: =N2/O2 -> 76241697 | S2: sh | T2: 1
M3: Mặt sau | N3: =SUMIFS($I$9:$I$48,$B$9:$B$48,"ii")-N2 -> 1.9358767e+11 | O3: =SUMIFS($E$9:$E$48,$B$9:$B$48,"ii")-O2 -> 3947.83 | P3: =N3/O3 -> 49036477 | S3: lk | T3: 1
M4: TỔNG PK2 | N4: =SUM(N2:N3) -> 2.7592871e+11 | O4: =SUM(O2:O3) -> 5027.83 | P4: =N4/O4 -> 54880278
D5: 1 | E5: 2 | F5: 3 | G5: 4 | H5: 5 | I5: 6 | J5: 7 | K5: 8 | L5: 9 | M5: 10 | N5: 11 | O5: 12 | P5: 13 | Q5: 14 | R5: 15
K6: 0.9 | N6: 0.055 | O6: 0.1
E7: =SUBTOTAL(9,E9:E48) -> 5147.83 | I7: =SUBTOTAL(9,I9:I48) -> 2.8551808e+11 | J7: =I7/E7 -> 55463774 | K7: =J7*K6 -> 49917396 | N7: 0.1 | O7: 0.1 | Q7: =SUBTOTAL(9,Q9:Q48) -> 2.5256035e+11 | R7: =Q7/E7 -> 49061517 | U7: =SUBTOTAL(9,U9:U48) -> 2.5256035e+11 | Y7: =SUBTOTAL(9,Y9:Y48) -> #REF!
A8: STT | B8: PHÂN KHU | C8: BLOCK | D8: MÃ CĂN | E8: DIỆN TÍCH ĐẤT | F8: CÔNG NĂNG | G8: MẶT ĐƯỜNG | H8: TIỀN XD | I8: TIỀN ĐÂT SAU CSBH | J8: ĐƠN GIÁ ĐẤT SAU CSBH | K8: TIỀN ĐẤT SAU CSBH - DUYỆT CK 10% | M8: TỔNG TIỀN NHÀ SAU KHI TRỪ CSBH | N8: Tiền nhà gồm HTLS 0% 12 TH (LK) 24TH (SH) - Giá bán công bố | O8: Chiết kấu 8% LK. 10% SH | P8: TỔNG GIÁ BÁN SAU CK | Q8: TIỀN ĐẤT SAU CK | R8: ĐƠN GIÁ ĐẤT SAU CK | S8: ĐƠN GIÁ SAU CK 10%
A9: 1 | B9: II | C9: LK42.1 | D9: LK42.01 | E9: 169.75 | F9: SH | G9: 24m | H9: 4280100000 | I9: 7.7635459e+09 | J9: =I9/E9 -> 45735174 | K9: =I9*$K$6 -> 6.9871913e+09 | M9: =H9+K9 -> 1.1267291e+10 | N9: =M9/(1-$N$7) -> 1.2519213e+10 | O9: =N9*$O$7 -> 1.2519213e+09 | P9: =N9-O9 -> 1.1267291e+10 | Q9: 6.9871913e+09 | R9: 41161657 | S9: =K9/E9 -> 41161657 | T9: =S9*$T$2 -> 41161657 | U9: =R9*E9 -> 6.9871913e+09 | X9: =VLOOKUP(D9,'5. KHBH'!#REF!,11,0) -> #REF! | Y9: =X9*'5. KHBH'!#REF! -> #REF!
A10: 2 | B10: II | C10: LK42.1 | D10: LK42.02 | E10: 156.66 | F10: SH | G10: 24m | H10: 3560700000 | I10: 7.8124175e+09 | J10: =I10/E10 -> 49868616 | K10: =I10*$K$6 -> 7.0311757e+09 | M10: =H10+K10 -> 1.0591876e+10 | N10: =M10/(1-$N$7) -> 1.1768751e+10 | O10: =N10*$O$7 -> 1.1768751e+09 | P10: =N10-O10 -> 1.0591876e+10 | Q10: 7.0311757e+09 | R10: 44881755 | S10: =K10/E10 -> 44881755 | T10: =S10*$T$2 -> 44881755 | U10: =R10*E10 -> 7.0311757e+09 | X10: =VLOOKUP(D10,'5. KHBH'!#REF!,11,0) -> #REF! | Y10: =X10*'5. KHBH'!#REF! -> #REF!
A11: 3 | B11: II | C11: LK42.1 | D11: LK42.03 | E11: 143.56 | F11: SH | G11: 24m | H11: 3560700000 | I11: 7.5199316e+09 | J11: =I11/E11 -> 52381803 | K11: =I11*$K$6 -> 6.7679385e+09 | M11: =H11+K11 -> 1.0328638e+10 | N11: =M11/(1-$N$7) -> 1.1476265e+10 | O11: =N11*$O$7 -> 1.1476265e+09 | P11: =N11-O11 -> 1.0328638e+10 | Q11: 6.7679385e+09 | R11: 47143623 | S11: =K11/E11 -> 47143623 | T11: =S11*$T$2 -> 47143623 | U11: =R11*E11 -> 6.7679385e+09 | X11: =VLOOKUP(D11,'5. KHBH'!#REF!,11,0) -> #REF! | Y11: =X11*'5. KHBH'!#REF! -> #REF!
A12: 4 | B12: II | C12: LK42.1 | D12: LK42.04 | E12: 130.47 | F12: SH | G12: 24m | H12: 2838000000 | I12: 6.7931515e+09 | J12: =I12/E12 -> 52066770 | K12: =I12*$K$6 -> 6.1138364e+09 | M12: =H12+K12 -> 8.9518364e+09 | N12: =M12/(1-$N$7) -> 9.9464849e+09 | O12: =N12*$O$7 -> 9.9464849e+08 | P12: =N12-O12 -> 8.9518364e+09 | Q12: 6.1138364e+09 | R12: 46860093 | S12: =K12/E12 -> 46860093 | T12: =S12*$T$2 -> 46860093 | U12: =R12*E12 -> 6.1138364e+09 | X12: =VLOOKUP(D12,'5. KHBH'!#REF!,11,0) -> #REF! | Y12: =X12*'5. KHBH'!#REF! -> #REF!
A13: 5 | B13: II | C13: LK42.1 | D13: LK42.05 | E13: 117.37 | F13: SH | G13: 24m | H13: 2838000000 | I13: 5.8905166e+09 | J13: =I13/E13 -> 50187583 | K13: =I13*$K$6 -> 5.3014649e+09 | M13: =H13+K13 -> 8.1394649e+09 | N13: =M13/(1-$N$7) -> 9.0438499e+09 | O13: =N13*$O$7 -> 9.0438499e+08 | P13: =N13-O13 -> 8.1394649e+09 | Q13: 5.3014649e+09 | R13: 45168825 | S13: =K13/E13 -> 45168825 | T13: =S13*$T$2 -> 45168825 | U13: =R13*E13 -> 5.3014649e+09 | X13: =VLOOKUP(D13,'5. KHBH'!#REF!,11,0) -> #REF! | Y13: =X13*'5. KHBH'!#REF! -> #REF!
A14: 6 | B14: II | C14: LK42.1 | D14: LK42.06 | E14: 147.24 | F14: SH | G14: 24m | H14: 3300000000 | I14: 8.9838721e+09 | J14: =I14/E14 -> 61015159 | K14: =I14*$K$6 -> 8.0854849e+09 | M14: =H14+K14 -> 1.1385485e+10 | N14: =M14/(1-$N$7) -> 1.2650539e+10 | O14: =N14*$O$7 -> 1.2650539e+09 | P14: =N14-O14 -> 1.1385485e+10 | Q14: 8.0854849e+09 | R14: 54913643 | S14: =K14/E14 -> 54913643 | T14: =S14*$T$2 -> 54913643 | U14: =R14*E14 -> 8.0854849e+09 | X14: =VLOOKUP(D14,'5. KHBH'!#REF!,11,0) -> #REF! | Y14: =X14*'5. KHBH'!#REF! -> #REF!
A15: 7 | B15: II | C15: LK42.2 | D15: LK42.09 | E15: 188.68 | F15: LK | G15: 15m | H15: 0 | I15: 7.7994464e+09 | J15: =I15/E15 -> 41336901 | K15: =I15*$K$6 -> 7.0195018e+09 | M15: =H15+K15 -> 7.0195018e+09 | N15: =M15/(1-$N$6) -> 7.4280442e+09 | O15: =N15*$O$5 -> 8.9136531e+10 | P15: =N15-O15 -> -8.1708486e+10 | Q15: 7.056642e+09 | R15: 37400053 | S15: =K15/E15 -> 37203211 | T15: =S15*$T$1 -> 37203211 | U15: =R15*E15 -> 7.056642e+09 | X15: =VLOOKUP(D15,'5. KHBH'!#REF!,11,0) -> #REF! | Y15: =X15*'5. KHBH'!#REF! -> #REF!
A16: 8 | B16: II | C16: LK42.2 | D16: LK42.10 | E16: 175.74 | F16: LK | G16: 15m | H16: 0 | I16: 7.4224719e+09 | J16: =I16/E16 -> 42235529 | K16: =I16*$K$6 -> 6.6802247e+09 | M16: =H16+K16 -> 6.6802247e+09 | N16: =M16/(1-$N$6) -> 7.0690208e+09 | O16: =N16*$O$5 -> 8.482825e+10 | P16: =N16-O16 -> -7.7759229e+10 | Q16: 6.7155698e+09 | R16: 38213098 | S16: =K16/E16 -> 38011976 | T16: =S16*$T$1 -> 38011976 | U16: =R16*E16 -> 6.7155698e+09 | X16: =VLOOKUP(D16,'5. KHBH'!#REF!,11,0) -> #REF! | Y16: =X16*'5. KHBH'!#REF! -> #REF!
A17: 9 | B17: II | C17: LK42.2 | D17: LK42.11 | E17: 164.48 | F17: LK | G17: 15m | H17: 0 | I17: 6.4606168e+09 | J17: =I17/E17 -> 39279042 | K17: =I17*$K$6 -> 5.8145551e+09 | M17: =H17+K17 -> 5.8145551e+09 | N17: =M17/(1-$N$6) -> 6.1529684e+09 | O17: =N17*$O$5 -> 7.3835621e+10 | P17: =N17-O17 -> -6.7682652e+10 | Q17: 5.84532e+09 | R17: 35538181 | S17: =K17/E17 -> 35351138 | T17: =S17*$T$1 -> 35351138 | U17: =R17*E17 -> 5.84532e+09 | X17: =VLOOKUP(D17,'5. KHBH'!#REF!,11,0) -> #REF! | Y17: =X17*'5. KHBH'!#REF! -> #REF!
A18: 10 | B18: II | C18: LK42.2 | D18: LK42.12 | E18: 156.18 | F18: LK | G18: 15m | H18: 0 | I18: 6.2651242e+09 | J18: =I18/E18 -> 40114766 | K18: =I18*$K$6 -> 5.6386118e+09 | M18: =H18+K18 -> 5.6386118e+09 | N18: =M18/(1-$N$6) -> 5.9667849e+09 | O18: =N18*$O$5 -> 7.1601419e+10 | P18: =N18-O18 -> -6.5634634e+10 | Q18: 5.6684457e+09 | R18: 36294312 | S18: =K18/E18 -> 36103290 | T18: =S18*$T$1 -> 36103290 | U18: =R18*E18 -> 5.6684457e+09 | X18: =VLOOKUP(D18,'5. KHBH'!#REF!,11,0) -> #REF! | Y18: =X18*'5. KHBH'!#REF! -> #REF!
A19: 11 | B19: II | C19: LK42.2 | D19: LK42.14 | E19: 150.15 | F19: LK | G19: 15m | H19: 0 | I19: 6.7382743e+09 | J19: =I19/E19 -> 44876951 | K19: =I19*$K$6 -> 6.0644468e+09 | M19: =H19+K19 -> 6.0644468e+09 | N19: =M19/(1-$N$6) -> 6.4174041e+09 | O19: =N19*$O$5 -> 7.7008849e+10 | P19: =N19-O19 -> -7.0591445e+10 | Q19: 6.0965339e+09 | R19: 40602956 | S19: =K19/E19 -> 40389256 | T19: =S19*$T$1 -> 40389256 | U19: =R19*E19 -> 6.0965339e+09 | X19: =VLOOKUP(D19,'5. KHBH'!#REF!,11,0) -> #REF! | Y19: =X19*'5. KHBH'!#REF! -> #REF!
A20: 12 | B20: II | C20: LK42.2 | D20: LK42.15 | E20: 150 | F20: LK | G20: 15m | H20: 0 | I20: 6.7315427e+09 | J20: =I20/E20 -> 44876951 | K20: =I20*$K$6 -> 6.0583884e+09 | M20: =H20+K20 -> 6.0583884e+09 | N20: =M20/(1-$N$6) -> 6.4109931e+09 | O20: =N20*$O$5 -> 7.6931917e+10 | P20: =N20-O20 -> -7.0520924e+10 | Q20: 6.0904434e+09 | R20: 40602956 | S20: =K20/E20 -> 40389256 | T20: =S20*$T$1 -> 40389256 | U20: =R20*E20 -> 6.0904434e+09 | X20: =VLOOKUP(D20,'5. KHBH'!#REF!,11,0) -> #REF! | Y20: =X20*'5. KHBH'!#REF! -> #REF!
A21: 13 | B21: II | C21: LK42.2 | D21: LK42.24 | E21: 187.55 | F21: LK | G21: 15m | H21: 0 | I21: 9.7396679e+09 | J21: =I21/E21 -> 51931047 | K21: =I21*$K$6 -> 8.7657011e+09 | M21: =H21+K21 -> 8.7657011e+09 | N21: =M21/(1-$N$6) -> 9.2758742e+09 | O21: =N21*$O$6 -> 9.2758742e+08 | P21: =N21-O21 -> 8.3482868e+09 | Q21: 8.3482868e+09 | R21: 44512326 | S21: =K21/E21 -> 46737943 | T21: =S21*$T$3 -> 46737943 | U21: =R21*E21 -> 8.3482868e+09 | X21: =VLOOKUP(D21,'5. KHBH'!#REF!,11,0) -> #REF! | Y21: =X21*'5. KHBH'!#REF! -> #REF!
A22: 14 | B22: II | C22: LK41.1 | D22: LK41.05 | E22: 120 | F22: LK | G22: 15m | H22: 0 | I22: 5.9174494e+09 | J22: =I22/E22 -> 49312079 | K22: =I22*$K$6 -> 5.3257045e+09 | M22: =H22+K22 -> 5.3257045e+09 | N22: =M22/(1-$N$6) -> 5.6356661e+09 | O22: =N22*$O$6 -> 5.6356661e+08 | P22: =N22-O22 -> 5.0720995e+09 | Q22: 5.0720995e+09 | R22: 42267496 | S22: =K22/E22 -> 44380871 | T22: =S22*$T$3 -> 44380871 | U22: =R22*E22 -> 5.0720995e+09 | X22: =VLOOKUP(D22,'5. KHBH'!#REF!,11,0) -> #REF! | Y22: =X22*'5. KHBH'!#REF! -> #REF!
A23: 15 | B23: II | C23: LK41.1 | D23: LK41.06 | E23: 120 | F23: LK | G23: 15m | H23: 0 | I23: 5.9174494e+09 | J23: =I23/E23 -> 49312079 | K23: =I23*$K$6 -> 5.3257045e+09 | M23: =H23+K23 -> 5.3257045e+09 | N23: =M23/(1-$N$6) -> 5.6356661e+09 | O23: =N23*$O$6 -> 5.6356661e+08 | P23: =N23-O23 -> 5.0720995e+09 | Q23: 5.0720995e+09 | R23: 42267496 | S23: =K23/E23 -> 44380871 | T23: =S23*$T$3 -> 44380871 | U23: =R23*E23 -> 5.0720995e+09 | X23: =VLOOKUP(D23,'5. KHBH'!#REF!,11,0) -> #REF! | Y23: =X23*'5. KHBH'!#REF! -> #REF!
A24: 16 | B24: II | C24: LK41.1 | D24: LK41.07 | E24: 120 | F24: LK | G24: 15m | H24: 0 | I24: 5.9174494e+09 | J24: =I24/E24 -> 49312079 | K24: =I24*$K$6 -> 5.3257045e+09 | M24: =H24+K24 -> 5.3257045e+09 | N24: =M24/(1-$N$6) -> 5.6356661e+09 | O24: =N24*$O$6 -> 5.6356661e+08 | P24: =N24-O24 -> 5.0720995e+09 | Q24: 5.0720995e+09 | R24: 42267496 | S24: =K24/E24 -> 44380871 | T24: =S24*$T$3 -> 44380871 | U24: =R24*E24 -> 5.0720995e+09 | X24: =VLOOKUP(D24,'5. KHBH'!#REF!,11,0) -> #REF! | Y24: =X24*'5. KHBH'!#REF! -> #REF!
A25: 17 | B25: II | C25: LK41.1 | D25: LK41.08 | E25: 120 | F25: LK | G25: 15m | H25: 0 | I25: 5.9174494e+09 | J25: =I25/E25 -> 49312079 | K25: =I25*$K$6 -> 5.3257045e+09 | M25: =H25+K25 -> 5.3257045e+09 | N25: =M25/(1-$N$6) -> 5.6356661e+09 | O25: =N25*$O$6 -> 5.6356661e+08 | P25: =N25-O25 -> 5.0720995e+09 | Q25: 5.0720995e+09 | R25: 42267496 | S25: =K25/E25 -> 44380871 | T25: =S25*$T$3 -> 44380871 | U25: =R25*E25 -> 5.0720995e+09 | X25: =VLOOKUP(D25,'5. KHBH'!#REF!,11,0) -> #REF! | Y25: =X25*'5. KHBH'!#REF! -> #REF!
A26: 18 | B26: II | C26: LK41.1 | D26: LK41.09 | E26: 120 | F26: LK | G26: 15m | H26: 0 | I26: 5.9174494e+09 | J26: =I26/E26 -> 49312079 | K26: =I26*$K$6 -> 5.3257045e+09 | M26: =H26+K26 -> 5.3257045e+09 | N26: =M26/(1-$N$6) -> 5.6356661e+09 | O26: =N26*$O$6 -> 5.6356661e+08 | P26: =N26-O26 -> 5.0720995e+09 | Q26: 5.0720995e+09 | R26: 42267496 | S26: =K26/E26 -> 44380871 | T26: =S26*$T$3 -> 44380871 | U26: =R26*E26 -> 5.0720995e+09 | X26: =VLOOKUP(D26,'5. KHBH'!#REF!,11,0) -> #REF! | Y26: =X26*'5. KHBH'!#REF! -> #REF!
A27: 19 | B27: II | C27: LK41.1 | D27: LK41.10 | E27: 120 | F27: LK | G27: 15m | H27: 0 | I27: 5.9174494e+09 | J27: =I27/E27 -> 49312079 | K27: =I27*$K$6 -> 5.3257045e+09 | M27: =H27+K27 -> 5.3257045e+09 | N27: =M27/(1-$N$6) -> 5.6356661e+09 | O27: =N27*$O$6 -> 5.6356661e+08 | P27: =N27-O27 -> 5.0720995e+09 | Q27: 5.0720995e+09 | R27: 42267496 | S27: =K27/E27 -> 44380871 | T27: =S27*$T$3 -> 44380871 | U27: =R27*E27 -> 5.0720995e+09 | X27: =VLOOKUP(D27,'5. KHBH'!#REF!,11,0) -> #REF! | Y27: =X27*'5. KHBH'!#REF! -> #REF!
A28: 20 | B28: II | C28: LK41.1 | D28: LK41.11 | E28: 120 | F28: LK | G28: 15m | H28: 0 | I28: 5.9174494e+09 | J28: =I28/E28 -> 49312079 | K28: =I28*$K$6 -> 5.3257045e+09 | M28: =H28+K28 -> 5.3257045e+09 | N28: =M28/(1-$N$6) -> 5.6356661e+09 | O28: =N28*$O$6 -> 5.6356661e+08 | P28: =N28-O28 -> 5.0720995e+09 | Q28: 5.0720995e+09 | R28: 42267496 | S28: =K28/E28 -> 44380871 | T28: =S28*$T$3 -> 44380871 | U28: =R28*E28 -> 5.0720995e+09 | X28: =VLOOKUP(D28,'5. KHBH'!#REF!,11,0) -> #REF! | Y28: =X28*'5. KHBH'!#REF! -> #REF!
A29: 21 | B29: II | C29: LK41.1 | D29: LK41.12 | E29: 120 | F29: LK | G29: 15m | H29: 0 | I29: 5.9174494e+09 | J29: =I29/E29 -> 49312079 | K29: =I29*$K$6 -> 5.3257045e+09 | M29: =H29+K29 -> 5.3257045e+09 | N29: =M29/(1-$N$6) -> 5.6356661e+09 | O29: =N29*$O$6 -> 5.6356661e+08 | P29: =N29-O29 -> 5.0720995e+09 | Q29: 5.0720995e+09 | R29: 42267496 | S29: =K29/E29 -> 44380871 | T29: =S29*$T$3 -> 44380871 | U29: =R29*E29 -> 5.0720995e+09 | X29: =VLOOKUP(D29,'5. KHBH'!#REF!,11,0) -> #REF! | Y29: =X29*'5. KHBH'!#REF! -> #REF!
A30: 22 | B30: II | C30: LK41.2 | D30: LK41.13 | E30: 121.55 | F30: LK | G30: 15m | H30: 0 | I30: 6.0874484e+09 | J30: =I30/E30 -> 50081846 | K30: =I30*$K$6 -> 5.4787036e+09 | M30: =H30+K30 -> 5.4787036e+09 | N30: =M30/(1-$N$6) -> 5.7975699e+09 | O30: =N30*$O$6 -> 5.7975699e+08 | P30: =N30-O30 -> 5.2178129e+09 | Q30: 5.2178129e+09 | R30: 42927297 | S30: =K30/E30 -> 45073662 | T30: =S30*$T$3 -> 45073662 | U30: =R30*E30 -> 5.2178129e+09 | X30: =VLOOKUP(D30,'5. KHBH'!#REF!,11,0) -> #REF! | Y30: =X30*'5. KHBH'!#REF! -> #REF!
A31: 23 | B31: II | C31: LK41.2 | D31: LK41.14 | E31: 108.45 | F31: LK | G31: 15m | H31: 0 | I31: 5.4302335e+09 | J31: =I31/E31 -> 50071310 | K31: =I31*$K$6 -> 4.8872102e+09 | M31: =H31+K31 -> 4.8872102e+09 | N31: =M31/(1-$N$6) -> 5.171651e+09 | O31: =N31*$O$6 -> 5.171651e+08 | P31: =N31-O31 -> 4.6544859e+09 | Q31: 4.6544859e+09 | R31: 42918265 | S31: =K31/E31 -> 45064179 | T31: =S31*$T$3 -> 45064179 | U31: =R31*E31 -> 4.6544859e+09 | X31: =VLOOKUP(D31,'5. KHBH'!#REF!,11,0) -> #REF! | Y31: =X31*'5. KHBH'!#REF! -> #REF!
A32: 24 | B32: II | C32: LK21A.2 | D32: LK21A.12 | E32: 90 | F32: LK | G32: 15m | H32: 0 | I32: 4.7795341e+09 | J32: =I32/E32 -> 53105934 | K32: =I32*$K$6 -> 4.3015807e+09 | M32: =H32+K32 -> 4.3015807e+09 | N32: =M32/(1-$N$6) -> 4.5519372e+09 | O32: =N32*$O$6 -> 4.5519372e+08 | P32: =N32-O32 -> 4.0967435e+09 | Q32: 4.0967435e+09 | R32: 45519372 | S32: =K32/E32 -> 47795341 | T32: =S32*$T$3 -> 47795341 | U32: =R32*E32 -> 4.0967435e+09 | X32: =VLOOKUP(D32,'5. KHBH'!#REF!,11,0) -> #REF! | Y32: =X32*'5. KHBH'!#REF! -> #REF!
... A39: 31 | B39: II | C39: LK21B | D39: LK21B.08 | E39: 90 | F39: LK | G39: 15m | H39: 0 | I39: 4.7795341e+09 | J39: =I39/E39 -> 53105934 | K39: =I39*$K$6 -> 4.3015807e+09 | M39: =H39+K39 -> 4.3015807e+09 | N39: =M39/(1-$N$6) -> 4.5519372e+09 | O39: =N39*$O$6 -> 4.5519372e+08 | P39: =N39-O39 -> 4.0967435e+09 | Q39: 4.0967435e+09 | R39: 45519372 | S39: =K39/E39 -> 47795341 | T39: =S39*$T$3 -> 47795341 | U39: =R39*E39 -> 4.0967435e+09 | X39: =VLOOKUP(D39,'5. KHBH'!#REF!,11,0) -> #REF! | Y39: =X39*'5. KHBH'!#REF! -> #REF!
A40: 32 | B40: II | C40: HH9 | D40: HH9.13 | E40: 150 | F40: SH | G40: 42m | H40: 3.84318e+09 | I40: 1.0995886e+10 | J40: =I40/E40 -> 73305904 | K40: =I40*$K$6 -> 9.8962971e+09 | M40: =H40+K40 -> 1.3739477e+10 | N40: =M40/(1-$N$7) -> 1.5266086e+10 | O40: =N40*$O$7 -> 1.5266086e+09 | P40: =N40-O40 -> 1.3739477e+10 | Q40: 9.8962971e+09 | R40: 65975314 | S40: =K40/E40 -> 65975314 | T40: =S40*$T$2 -> 65975314 | U40: =R40*E40 -> 9.8962971e+09 | X40: =VLOOKUP(D40,'5. KHBH'!#REF!,11,0) -> #REF! | Y40: =X40*'5. KHBH'!#REF! -> #REF!
A41: 33 | B41: II | C41: HH9 | D41: HH9.14 | E41: 150 | F41: SH | G41: 42m | H41: 3.84318e+09 | I41: 1.0995886e+10 | J41: =I41/E41 -> 73305904 | K41: =I41*$K$6 -> 9.8962971e+09 | M41: =H41+K41 -> 1.3739477e+10 | N41: =M41/(1-$N$7) -> 1.5266086e+10 | O41: =N41*$O$7 -> 1.5266086e+09 | P41: =N41-O41 -> 1.3739477e+10 | Q41: 9.8962971e+09 | R41: 65975314 | S41: =K41/E41 -> 65975314 | T41: =S41*$T$2 -> 65975314 | U41: =R41*E41 -> 9.8962971e+09 | X41: =VLOOKUP(D41,'5. KHBH'!#REF!,11,0) -> #REF! | Y41: =X41*'5. KHBH'!#REF! -> #REF!
A42: 34 | B42: II | C42: HH9 | D42: HH9.15 | E42: 150 | F42: SH | G42: 42m | H42: 3.84318e+09 | I42: 1.0995886e+10 | J42: =I42/E42 -> 73305904 | K42: =I42*$K$6 -> 9.8962971e+09 | M42: =H42+K42 -> 1.3739477e+10 | N42: =M42/(1-$N$7) -> 1.5266086e+10 | O42: =N42*$O$7 -> 1.5266086e+09 | P42: =N42-O42 -> 1.3739477e+10 | Q42: 9.8962971e+09 | R42: 65975314 | S42: =K42/E42 -> 65975314 | T42: =S42*$T$2 -> 65975314 | U42: =R42*E42 -> 9.8962971e+09 | X42: =VLOOKUP(D42,'5. KHBH'!#REF!,11,0) -> #REF! | Y42: =X42*'5. KHBH'!#REF! -> #REF!
A43: 35 | B43: II | C43: HH9 | D43: HH9.16 | E43: 150 | F43: SH | G43: 42m | H43: 3.84318e+09 | I43: 1.0995886e+10 | J43: =I43/E43 -> 73305904 | K43: =I43*$K$6 -> 9.8962971e+09 | M43: =H43+K43 -> 1.3739477e+10 | N43: =M43/(1-$N$7) -> 1.5266086e+10 | O43: =N43*$O$7 -> 1.5266086e+09 | P43: =N43-O43 -> 1.3739477e+10 | Q43: 9.8962971e+09 | R43: 65975314 | S43: =K43/E43 -> 65975314 | T43: =S43*$T$2 -> 65975314 | U43: =R43*E43 -> 9.8962971e+09 | X43: =VLOOKUP(D43,'5. KHBH'!#REF!,11,0) -> #REF! | Y43: =X43*'5. KHBH'!#REF! -> #REF!
A44: 36 | B44: II | C44: HH8 | D44: HH8.04 | E44: 120 | F44: SH | G44: 42m | H44: 3053820000 | I44: 9.5893724e+09 | J44: =I44/E44 -> 79911437 | K44: =I44*$K$6 -> 8.6304352e+09 | M44: =H44+K44 -> 1.1684255e+10 | N44: =M44/(1-$N$7) -> 1.2982506e+10 | O44: =N44*$O$7 -> 1.2982506e+09 | P44: =N44-O44 -> 1.1684255e+10 | Q44: 8.6304352e+09 | R44: 71920293 | S44: =K44/E44 -> 71920293 | T44: =S44*$T$2 -> 71920293 | U44: =R44*E44 -> 8.6304352e+09 | X44: =VLOOKUP(D44,'5. KHBH'!#REF!,11,0) -> #REF! | Y44: =X44*'5. KHBH'!#REF! -> #REF!
A45: 37 | B45: II | C45: HH8 | D45: HH8.05 | E45: 120 | F45: SH | G45: 42m | H45: 3053820000 | I45: 9.5893724e+09 | J45: =I45/E45 -> 79911437 | K45: =I45*$K$6 -> 8.6304352e+09 | M45: =H45+K45 -> 1.1684255e+10 | N45: =M45/(1-$N$7) -> 1.2982506e+10 | O45: =N45*$O$7 -> 1.2982506e+09 | P45: =N45-O45 -> 1.1684255e+10 | Q45: 8.6304352e+09 | R45: 71920293 | S45: =K45/E45 -> 71920293 | T45: =S45*$T$2 -> 71920293 | U45: =R45*E45 -> 8.6304352e+09 | X45: =VLOOKUP(D45,'5. KHBH'!#REF!,11,0) -> #REF! | Y45: =X45*'5. KHBH'!#REF! -> #REF!
A46: 38 | B46: II | C46: HH8 | D46: HH8.07 | E46: 120 | F46: SH | G46: 42m | H46: 3053820000 | I46: 9.5893724e+09 | J46: =I46/E46 -> 79911437 | K46: =I46*$K$6 -> 8.6304352e+09 | M46: =H46+K46 -> 1.1684255e+10 | N46: =M46/(1-$N$7) -> 1.2982506e+10 | O46: =N46*$O$7 -> 1.2982506e+09 | P46: =N46-O46 -> 1.1684255e+10 | Q46: 8.6304352e+09 | R46: 71920293 | S46: =K46/E46 -> 71920293 | T46: =S46*$T$2 -> 71920293 | U46: =R46*E46 -> 8.6304352e+09 | X46: =VLOOKUP(D46,'5. KHBH'!#REF!,11,0) -> #REF! | Y46: =X46*'5. KHBH'!#REF! -> #REF!
A47: 39 | B47: II | C47: HH8 | D47: HH8.08 | E47: 120 | F47: SH | G47: 42m | H47: 3053820000 | I47: 9.5893724e+09 | J47: =I47/E47 -> 79911437 | K47: =I47*$K$6 -> 8.6304352e+09 | M47: =H47+K47 -> 1.1684255e+10 | N47: =M47/(1-$N$7) -> 1.2982506e+10 | O47: =N47*$O$7 -> 1.2982506e+09 | P47: =N47-O47 -> 1.1684255e+10 | Q47: 8.6304352e+09 | R47: 71920293 | S47: =K47/E47 -> 71920293 | T47: =S47*$T$2 -> 71920293 | U47: =R47*E47 -> 8.6304352e+09 | X47: =VLOOKUP(D47,'5. KHBH'!#REF!,11,0) -> #REF! | Y47: =X47*'5. KHBH'!#REF! -> #REF!
A48: 40 | B48: II` | C48: HH8 | D48: HH8.10 | E48: 120 | F48: SH | G48: 42m | H48: 3053820000 | I48: 9.5893724e+09 | J48: =I48/E48 -> 79911437 | K48: =I48*$K$6 -> 8.6304352e+09 | M48: =H48+K48 -> 1.1684255e+10 | N48: =M48/(1-$N$7) -> 1.2982506e+10 | O48: =N48*$O$7 -> 1.2982506e+09 | P48: =N48-O48 -> 1.1684255e+10 | Q48: 8.6304352e+09 | R48: 71920293 | S48: =K48/E48 -> 71920293 | T48: =S48*$T$2 -> 71920293 | U48: =R48*E48 -> 8.6304352e+09 | X48: =VLOOKUP(D48,'5. KHBH'!#REF!,11,0) -> #REF! | Y48: =X48*'5. KHBH'!#REF! -> #REF!

Sheet CF bán hàng 12.2024
B2: THANH TOÁN SỚM | E2: 0.5
D3: TỔN DOANH THU | E3: TỶ LỆ DOANH THU KH TTS | F3: T12.2024 | G3: Q1.2025 | H3: Q2.2025 | I3: Q3.2025 | J3: Q4.2025 | K3: Q1.2026 | L3: Q2.2026 | M3: Q3.2026 | N3: Q4.2026 | O3: Q1.2026 | P3: Q2.2026 | Q3: Q3.2026 | R3: Q4.2026 | S3: Q1.2027 | T3: Q2.2027 | U3: TỔNG
B4: T12/2024 | C4: LK | D4: =#REF! -> #REF! | E4: =D4*$E$2 -> #REF! | F4: 0.3 | G4: 0.65 | H4: 0.05 | U4: =SUM(F4:T4) -> 1
F5: =$E$4*F4 -> #REF! | G5: =$E$4*G4 -> #REF! | H5: =$E$4*H4 -> #REF! | U5: =SUM(F5:T5) -> #REF!
C6: SH | D6: =#REF! -> #REF! | E6: =D6*$E$2 -> #REF! | F6: 0.3 | G6: 0.4 | K6: 0.25 | L6: 0.05 | U6: =SUM(F6:T6) -> 1
F7: =$E$6*F6 -> #REF! | G7: =$E$6*G6 -> #REF! | H7: =$E$6*H6 -> #REF! | I7: =$E$6*I6 -> #REF! | J7: =$E$6*J6 -> #REF! | K7: =$E$6*K6 -> #REF! | L7: =$E$6*L6 -> #REF! | U7: =SUM(F7:T7) -> #REF!
B8: Q1.2025 | C8: LK | D8: =#REF! -> #REF! | E8: =D8*$E$2 -> #REF! | G8: 0.3 | H8: 0.65 | I8: 0.05 | U8: =SUM(F8:T8) -> 1
G9: =$E$8*G8 -> #REF! | H9: =$E$8*H8 -> #REF! | I9: =$E$8*I8 -> #REF! | U9: =SUM(F9:T9) -> #REF!
C10: SH | D10: =#REF! -> #REF! | E10: =D10*$E$2 -> #REF! | G10: 0.3 | H10: 0.4 | L10: 0.25 | M10: 0.05 | U10: =SUM(F10:T10) -> 1
G11: =$E$10*G10 -> #REF! | H11: =$E$10*H10 -> #REF! | I11: =$E$10*I10 -> #REF! | J11: =$E$10*J10 -> #REF! | K11: =$E$10*K10 -> #REF! | L11: =$E$10*L10 -> #REF! | M11: =$E$10*M10 -> #REF! | U11: =SUM(F11:T11) -> #REF!
B12: Q2.2025 | C12: LK | D12: =#REF! -> #REF! | E12: =D12*$E$2 -> #REF! | H12: 0.3 | I12: 0.65 | J12: 0.05 | U12: =SUM(F12:T12) -> 1
H13: =$E$12*H12 -> #REF! | I13: =$E$12*I12 -> #REF! | J13: =$E$12*J12 -> #REF! | U13: =SUM(F13:T13) -> #REF!
C14: SH | D14: =#REF! -> #REF! | E14: =D14*$E$2 -> #REF! | H14: 0.3 | I14: 0.4 | M14: 0.25 | N14: 0.05 | U14: =SUM(F14:T14) -> 1
H15: =$E$14*H14 -> #REF! | I15: =$E$14*I14 -> #REF! | J15: =$E$14*J14 -> #REF! | K15: =$E$14*K14 -> #REF! | L15: =$E$14*L14 -> #REF! | M15: =$E$14*M14 -> #REF! | N15: =$E$14*N14 -> #REF! | U15: =SUM(F15:T15) -> #REF!
B16: Q3.2025 | C16: LK | D16: =#REF! -> #REF! | E16: =D16*$E$2 -> #REF! | I16: 0.3 | J16: 0.65 | K16: 0.05 | U16: =SUM(F16:T16) -> 1
I17: =$E$16*I16 -> #REF! | J17: =$E$16*J16 -> #REF! | K17: =$E$16*K16 -> #REF! | U17: =SUM(F17:T17) -> #REF!
C18: SH | D18: =#REF! -> #REF! | E18: =D18*$E$2 -> #REF! | I18: 0.3 | J18: 0.4 | N18: 0.25 | O18: 0.05 | U18: =SUM(F18:T18) -> 1
I19: =$E$18*I18 -> #REF! | J19: =$E$18*J18 -> #REF! | K19: =$E$18*K18 -> #REF! | L19: =$E$18*L18 -> #REF! | M19: =$E$18*M18 -> #REF! | N19: =$E$18*N18 -> #REF! | O19: =$E$18*O18 -> #REF! | U19: =SUM(F19:T19) -> #REF!
B20: Q4.2025 | C20: LK | D20: =#REF! -> #REF! | E20: =D20*$E$2 -> #REF! | J20: 0.3 | K20: 0.65 | L20: 0.05 | U20: =SUM(F20:T20) -> 1
J21: =$E$20*J20 -> #REF! | K21: =$E$20*K20 -> #REF! | L21: =$E$20*L20 -> #REF! | U21: =SUM(F21:T21) -> #REF!
C22: SH | D22: =#REF! -> #REF! | E22: =D22*$E$2 -> #REF! | J22: 0.3 | K22: 0.4 | O22: 0.25 | P22: 0.05 | U22: =SUM(F22:T22) -> 1
J23: =$E$22*J22 -> #REF! | K23: =$E$22*K22 -> #REF! | L23: =$E$22*L22 -> #REF! | M23: =$E$22*M22 -> #REF! | N23: =$E$22*N22 -> #REF! | O23: =$E$22*O22 -> #REF! | P23: =$E$22*P22 -> #REF! | U23: =SUM(F23:T23) -> #REF!
B24: Q1.2026 | C24: LK | D24: =#REF! -> #REF! | E24: =D24*$E$2 -> #REF! | K24: 0.3 | L24: 0.65 | M24: 0.05 | U24: =SUM(F24:T24) -> 1
K25: =$E$24*K24 -> #REF! | L25: =$E$24*L24 -> #REF! | M25: =$E$24*M24 -> #REF! | U25: =SUM(F25:T25) -> #REF!
C26: SH | D26: =#REF! -> #REF! | E26: =D26*$E$2 -> #REF! | K26: 0.3 | L26: 0.4 | P26: 0.25 | Q26: 0.05 | U26: =SUM(F26:T26) -> 1
K27: =$E$26*K26 -> #REF! | L27: =$E$26*L26 -> #REF! | M27: =$E$26*M26 -> #REF! | N27: =$E$26*N26 -> #REF! | O27: =$E$26*O26 -> #REF! | P27: =$E$26*P26 -> #REF! | Q27: =$E$26*Q26 -> #REF! | U27: =SUM(F27:T27) -> #REF!
B28: Q2.2026 | C28: LK | D28: =#REF! -> #REF! | E28: =D28*$E$2 -> #REF! | L28: 0.3 | M28: 0.65 | N28: 0.05 | U28: =SUM(F28:T28) -> 1
L29: =$E$28*L28 -> #REF! | M29: =$E$28*M28 -> #REF! | N29: =$E$28*N28 -> #REF! | U29: =SUM(F29:T29) -> #REF!
C30: SH | D30: =#REF! -> #REF! | E30: =D30*$E$2 -> #REF! | L30: 0.3 | M30: 0.4 | Q30: 0.25 | R30: 0.05 | U30: =SUM(F30:T30) -> 1
L31: =$E$30*L30 -> #REF! | M31: =$E$30*M30 -> #REF! | N31: =$E$30*N30 -> #REF! | O31: =$E$30*O30 -> #REF! | P31: =$E$30*P30 -> #REF! | Q31: =$E$30*Q30 -> #REF! | R31: =$E$30*R30 -> #REF! | U31: =SUM(F31:T31) -> #REF!
B32: Q3.2026 | C32: LK | D32: =#REF! -> #REF! | E32: =D32*$E$2 -> #REF! | M32: 0.3 | N32: 0.65 | O32: 0.05 | U32: =SUM(F32:T32) -> 1
M33: =$E$32*M32 -> #REF! | N33: =$E$32*N32 -> #REF! | O33: =$E$32*O32 -> #REF! | U33: =SUM(F33:T33) -> #REF!
C34: SH | D34: =#REF! -> #REF! | E34: =D34*$E$2 -> #REF! | M34: 0.3 | N34: 0.4 | R34: 0.25 | S34: 0.05 | U34: =SUM(F34:T34) -> 1
M35: =$E$34*M34 -> #REF! | N35: =$E$34*N34 -> #REF! | O35: =$E$34*O34 -> #REF! | P35: =$E$34*P34 -> #REF! | Q35: =$E$34*Q34 -> #REF! | R35: =$E$34*R34 -> #REF! | S35: =$E$34*S34 -> #REF! | U35: =SUM(F35:T35) -> #REF!
B36: Q4.2026 | C36: LK | D36: =#REF! -> #REF! | E36: =D36*$E$2 -> #REF! | N36: 0.3 | O36: 0.65 | P36: 0.05 | U36: =SUM(F36:T36) -> 1
N37: =$E$36*N36 -> #REF! | O37: =$E$36*O36 -> #REF! | P37: =$E$36*P36 -> #REF! | U37: =SUM(F37:T37) -> #REF!
C38: SH | D38: =#REF! -> #REF! | E38: =D38*$E$2 -> #REF! | N38: 0.3 | O38: 0.4 | S38: 0.25 | T38: 0.05 | U38: =SUM(F38:T38) -> 1
N39: =$E$38*N38 -> #REF! | O39: =$E$38*O38 -> #REF! | P39: =$E$38*P38 -> #REF! | Q39: =$E$38*Q38 -> #REF! | R39: =$E$38*R38 -> #REF! | S39: =$E$38*S38 -> #REF! | T39: =$E$38*T38 -> #REF! | U39: =SUM(F39:T39) -> #REF!
E40: =SUM(E4:E39) -> #REF! | F40: =SUM(F4:F39) -> #REF! | G40: =SUM(G4:G39) -> #REF! | H40: =SUM(H4:H39) -> #REF! | I40: =SUM(I4:I39) -> #REF! | J40: =SUM(J4:J39) -> #REF! | K40: =SUM(K4:K39) -> #REF! | L40: =SUM(L4:L39) -> #REF! | ... T40: =SUM(T4:T39) -> #REF! | U40: =SUM(F40:T40) -> #REF!
B43: THANH TOÁN TIẾN ĐỘ | E43: =1-E2 -> 0.5
D44: TỔN DOANH THU | E44: TỶ LỆ DOANH THU KH TT TTĐ | F44: T12.2024 | G44: Q1.2025 | H44: Q2.2025 | I44: Q3.2025 | J44: Q4.2025 | K44: Q1.2026 | L44: Q2.2026 | M44: Q3.2026 | N44: Q4.2026 | O44: Q1.2026 | P44: Q2.2026 | Q44: Q3.2026 | R44: Q4.2026 | S44: Q1.2027 | T44: Q2.2026-7 | U44: TỔNG
B45: T12/2024 | C45: LK | D45: =#REF! -> #REF! | E45: =D45*$E$43 -> #REF! | F45: 0.3 | G45: 0.2 | H45: 0.2 | I45: 0.25 | J45: 0.05 | U45: =SUM(F45:T45) -> 1
E46: =D46*$E$43 -> 0 | F46: =$E$45*F45 -> #REF! | G46: =$E$45*G45 -> #REF! | H46: =$E$45*H45 -> #REF! | I46: =$E$45*I45 -> #REF! | J46: =$E$45*J45 -> #REF! | U46: =SUM(F46:T46) -> #REF!
C47: SH | D47: =#REF! -> #REF! | E47: =D47*$E$43 -> #REF! | F47: 0.3 | G47: 0.1 | H47: 0.1 | I47: 0.1 | J47: 0.1 | K47: 0.25 | L47: 0.05 | U47: =SUM(F47:T47) -> 1
E48: =D48*$E$43 -> 0 | F48: =$E$47*F47 -> #REF! | G48: =$E$47*G47 -> #REF! | H48: =$E$47*H47 -> #REF! | I48: =$E$47*I47 -> #REF! | J48: =$E$47*J47 -> #REF! | K48: =$E$47*K47 -> #REF! | L48: =$E$47*L47 -> #REF! | U48: =SUM(F48:T48) -> #REF!
B49: Q1/2025 | C49: LK | D49: =#REF! -> #REF! | E49: =D49*$E$43 -> #REF! | G49: 0.3 | H49: 0.2 | I49: 0.2 | J49: 0.25 | K49: 0.05 | U49: =SUM(F49:T49) -> 1
E50: =D50*$E$43 -> 0 | G50: =$E$49*G49 -> #REF! | H50: =$E$49*H49 -> #REF! | I50: =$E$49*I49 -> #REF! | J50: =$E$49*J49 -> #REF! | K50: =$E$49*K49 -> #REF! | U50: =SUM(F50:T50) -> #REF!
C51: SH | D51: =#REF! -> #REF! | E51: =D51*$E$43 -> #REF! | G51: 0.3 | H51: 0.1 | I51: 0.1 | J51: 0.1 | K51: 0.1 | L51: 0.25 | M51: 0.05 | U51: =SUM(F51:T51) -> 1
E52: =D52*$E$43 -> 0 | G52: =$E$51*G51 -> #REF! | H52: =$E$51*H51 -> #REF! | I52: =$E$51*I51 -> #REF! | J52: =$E$51*J51 -> #REF! | K52: =$E$51*K51 -> #REF! | L52: =$E$51*L51 -> #REF! | M52: =$E$51*M51 -> #REF! | U52: =SUM(F52:T52) -> #REF!
B53: Q2/2025 | C53: LK | D53: =#REF! -> #REF! | E53: =D53*$E$43 -> #REF! | H53: 0.3 | I53: 0.2 | J53: 0.2 | K53: 0.25 | L53: 0.05 | U53: =SUM(F53:T53) -> 1
E54: =D54*$E$43 -> 0 | H54: =$E$53*H53 -> #REF! | I54: =$E$53*I53 -> #REF! | J54: =$E$53*J53 -> #REF! | K54: =$E$53*K53 -> #REF! | L54: =$E$53*L53 -> #REF! | U54: =SUM(F54:T54) -> #REF!
C55: SH | D55: =#REF! -> #REF! | E55: =D55*$E$43 -> #REF! | H55: 0.3 | I55: 0.1 | J55: 0.1 | K55: 0.1 | L55: 0.1 | M55: 0.25 | N55: 0.05 | U55: =SUM(F55:T55) -> 1
E56: =D56*$E$43 -> 0 | H56: =$E$55*H55 -> #REF! | I56: =$E$55*I55 -> #REF! | J56: =$E$55*J55 -> #REF! | K56: =$E$55*K55 -> #REF! | L56: =$E$55*L55 -> #REF! | M56: =$E$55*M55 -> #REF! | N56: =$E$55*N55 -> #REF! | U56: =SUM(F56:T56) -> #REF!
B57: Q3/2025 | C57: LK | D57: =#REF! -> #REF! | E57: =D57*$E$43 -> #REF! | I57: 0.3 | J57: 0.2 | K57: 0.2 | L57: 0.25 | M57: 0.05 | U57: =SUM(F57:T57) -> 1
E58: =D58*$E$43 -> 0 | I58: =$E$57*I57 -> #REF! | J58: =$E$57*J57 -> #REF! | K58: =$E$57*K57 -> #REF! | L58: =$E$57*L57 -> #REF! | M58: =$E$57*M57 -> #REF! | U58: =SUM(F58:T58) -> #REF!
C59: SH | D59: =#REF! -> #REF! | E59: =D59*$E$43 -> #REF! | I59: 0.3 | J59: 0.1 | K59: 0.1 | L59: 0.1 | M59: 0.1 | N59: 0.25 | O59: 0.05 | U59: =SUM(F59:T59) -> 1
E60: =D60*$E$43 -> 0 | I60: =$E$59*I59 -> #REF! | J60: =$E$59*J59 -> #REF! | K60: =$E$59*K59 -> #REF! | L60: =$E$59*L59 -> #REF! | M60: =$E$59*M59 -> #REF! | N60: =$E$59*N59 -> #REF! | O60: =$E$59*O59 -> #REF! | U60: =SUM(F60:T60) -> #REF!
B61: Q4/2025 | C61: LK | D61: =#REF! -> #REF! | E61: =D61*$E$43 -> #REF! | J61: 0.3 | K61: 0.2 | L61: 0.2 | M61: 0.25 | N61: 0.05 | U61: =SUM(F61:T61) -> 1
E62: =D62*$E$43 -> 0 | J62: =$E$61*J61 -> #REF! | K62: =$E$61*K61 -> #REF! | L62: =$E$61*L61 -> #REF! | M62: =$E$61*M61 -> #REF! | N62: =$E$61*N61 -> #REF! | U62: =SUM(F62:T62) -> #REF!
C63: SH | D63: =#REF! -> #REF! | E63: =D63*$E$43 -> #REF! | J63: 0.3 | K63: 0.1 | L63: 0.1 | M63: 0.1 | N63: 0.1 | O63: 0.25 | P63: 0.05 | U63: =SUM(F63:T63) -> 1
E64: =D64*$E$43 -> 0 | J64: =$E$63*J63 -> #REF! | K64: =$E$63*K63 -> #REF! | L64: =$E$63*L63 -> #REF! | M64: =$E$63*M63 -> #REF! | N64: =$E$63*N63 -> #REF! | O64: =$E$63*O63 -> #REF! | P64: =$E$63*P63 -> #REF! | U64: =SUM(F64:T64) -> #REF!
B65: Q1/2026 | C65: LK | D65: =#REF! -> #REF! | E65: =D65*$E$43 -> #REF! | K65: 0.3 | L65: 0.2 | M65: 0.2 | N65: 0.25 | O65: 0.05 | U65: =SUM(F65:T65) -> 1
E66: =D66*$E$43 -> 0 | K66: =$E$65*K65 -> #REF! | L66: =$E$65*L65 -> #REF! | M66: =$E$65*M65 -> #REF! | N66: =$E$65*N65 -> #REF! | O66: =$E$65*O65 -> #REF! | U66: =SUM(F66:T66) -> #REF!
C67: SH | D67: =#REF! -> #REF! | E67: =D67*$E$43 -> #REF! | K67: 0.3 | L67: 0.1 | M67: 0.1 | N67: 0.1 | O67: 0.1 | P67: 0.25 | Q67: 0.05 | U67: =SUM(F67:T67) -> 1
E68: =D68*$E$43 -> 0 | K68: =$E$67*K67 -> #REF! | L68: =$E$67*L67 -> #REF! | M68: =$E$67*M67 -> #REF! | N68: =$E$67*N67 -> #REF! | O68: =$E$67*O67 -> #REF! | P68: =$E$67*P67 -> #REF! | Q68: =$E$67*Q67 -> #REF! | U68: =SUM(F68:T68) -> #REF!
B69: Q2/2026 | C69: LK | D69: =#REF! -> #REF! | E69: =D69*$E$43 -> #REF! | L69: 0.3 | M69: 0.2 | N69: 0.2 | O69: 0.25 | P69: 0.05 | U69: =SUM(F69:T69) -> 1
E70: =D70*$E$43 -> 0 | L70: =$E$69*L69 -> #REF! | M70: =$E$69*M69 -> #REF! | N70: =$E$69*N69 -> #REF! | O70: =$E$69*O69 -> #REF! | P70: =$E$69*P69 -> #REF! | U70: =SUM(F70:T70) -> #REF!
C71: SH | D71: =#REF! -> #REF! | E71: =D71*$E$43 -> #REF! | L71: 0.3 | M71: 0.1 | N71: 0.1 | O71: 0.1 | P71: 0.1 | Q71: 0.25 | R71: 0.05 | U71: =SUM(F71:T71) -> 1
E72: =D72*$E$43 -> 0 | L72: =$E$71*L71 -> #REF! | M72: =$E$71*M71 -> #REF! | N72: =$E$71*N71 -> #REF! | O72: =$E$71*O71 -> #REF! | P72: =$E$71*P71 -> #REF! | Q72: =$E$71*Q71 -> #REF! | R72: =$E$71*R71 -> #REF! | U72: =SUM(F72:T72) -> #REF!
B73: Q3/2026 | C73: LK | D73: =#REF! -> #REF! | E73: =D73*$E$43 -> #REF! | M73: 0.3 | N73: 0.2 | O73: 0.2 | P73: 0.25 | Q73: 0.05 | U73: =SUM(F73:T73) -> 1
E74: =D74*$E$43 -> 0 | M74: =$E$73*M73 -> #REF! | N74: =$E$73*N73 -> #REF! | O74: =$E$73*O73 -> #REF! | P74: =$E$73*P73 -> #REF! | Q74: =$E$73*Q73 -> #REF! | U74: =SUM(F74:T74) -> #REF!
C75: SH | D75: =#REF! -> #REF! | E75: =D75*$E$43 -> #REF! | M75: 0.3 | N75: 0.1 | O75: 0.1 | P75: 0.1 | Q75: 0.1 | R75: 0.25 | S75: 0.05 | U75: =SUM(F75:T75) -> 1
E76: =D76*$E$43 -> 0 | M76: =$E$75*M75 -> #REF! | N76: =$E$75*N75 -> #REF! | O76: =$E$75*O75 -> #REF! | P76: =$E$75*P75 -> #REF! | Q76: =$E$75*Q75 -> #REF! | R76: =$E$75*R75 -> #REF! | S76: =$E$75*S75 -> #REF! | U76: =SUM(F76:T76) -> #REF!
B77: Q4/2026 | C77: LK | D77: =#REF! -> #REF! | E77: =D77*$E$43 -> #REF! | N77: 0.3 | O77: 0.2 | P77: 0.2 | Q77: 0.25 | R77: 0.05 | U77: =SUM(F77:T77) -> 1
E78: =D78*$E$43 -> 0 | N78: =$E$77*N77 -> #REF! | O78: =$E$77*O77 -> #REF! | P78: =$E$77*P77 -> #REF! | Q78: =$E$77*Q77 -> #REF! | R78: =$E$77*R77 -> #REF! | U78: =SUM(F78:T78) -> #REF!
C79: SH | D79: =#REF! -> #REF! | E79: =D79*$E$43 -> #REF! | N79: 0.3 | O79: 0.1 | P79: 0.1 | Q79: 0.1 | R79: 0.1 | S79: 0.25 | T79: 0.05 | U79: =SUM(F79:T79) -> 1
N80: =$E$79*N79 -> #REF! | O80: =$E$79*O79 -> #REF! | P80: =$E$79*P79 -> #REF! | Q80: =$E$79*Q79 -> #REF! | R80: =$E$79*R79 -> #REF! | S80: =$E$79*S79 -> #REF! | T80: =$E$79*T79 -> #REF! | U80: =SUM(F80:T80) -> #REF!
F81: =SUM(F45:F80) -> #REF! | G81: =SUM(G45:G80) -> #REF! | H81: =SUM(H45:H80) -> #REF! | I81: =SUM(I45:I80) -> #REF! | J81: =SUM(J45:J80) -> #REF! | K81: =SUM(K45:K80) -> #REF! | L81: =SUM(L45:L80) -> #REF! | M81: =SUM(M45:M80) -> #REF! | ... T81: =SUM(T45:T80) -> #REF! | U81: =SUM(F81:T81) -> #REF!
U82: =U81+U40 -> #REF!
F83: =F40+F81 -> #REF! | G83: =G40+G81 -> #REF! | H83: =H40+H81 -> #REF! | I83: =I40+I81 -> #REF! | J83: =J40+J81 -> #REF! | K83: =K40+K81 -> #REF! | L83: =L40+L81 -> #REF! | M83: =M40+M81 -> #REF! | ... T83: =T40+T81 -> #REF! | U83: =SUM(F83:T83) -> #REF!
